Workbook

Sheet Dashboard
A1: Franchise Development — Strategic Dashboard
A2: EXECUTIVE LAYER · Live roll-up across all 1:1 trackers. Updated automatically — no duplicate data entry. (Open the file in Excel and allow recalculation for live values.)
A4: =COUNTIF(Projects!$H$5:$H$47,">0") -> 14 | C4: =COUNTIF(Projects!$I$5:$I$47,"In Progress") -> 9 | E4: =COUNTIF(Projects!$I$5:$I$47,"At Risk") -> 1 | G4: =COUNTIF(Projects!$I$5:$I$47,"Blocked") -> 1 | I4: =COUNTIF(Projects!$I$5:$I$47,"Complete") -> 1 | K4: =IFERROR(SUM('All Tasks'!$U$5:$U$404)/SUM('All Tasks'!$W$5:$W$404),0) -> 0.38142857
A5: Active Projects | C5: On Track | E5: At Risk | G5: Blocked | I5: Complete | K5: Avg % Complete
A7: =SUM('All Tasks'!$W$5:$W$404) -> 35 | C7: =SUM('All Tasks'!$R$5:$R$404) -> 1 | E7: =SUM('All Tasks'!$S$5:$S$404) -> 1 | G7: =COUNTIF(Projects!$I$5:$I$47,"Not Started") -> 2 | I7: =COUNTIF(Projects!$I$5:$I$47,"No Tasks Yet") -> 29 | K7: =10 -> 10
A8: Total Active Tasks | C8: Overdue Tasks | E8: Due in 7 Days | G8: Not Started | I8: No Tasks Yet | K8: Total People
A11: Status by Focus Area | I11: Workload by Individual
A12: Focus Area | B12: Tasks | C12: Complete | D12: In Progress | E12: Overdue | F12: % Complete | G12: Health | I12: Person | J12: Tasks | K12: Open | L12: Complete | M12: Overdue | N12: % Complete
A13: 1 – Unified Development System | B13: =SUMIFS('All Tasks'!$W$5:$W$404,'All Tasks'!$C$5:$C$404,$A13) -> 11 | C13: =COUNTIFS('All Tasks'!$C$5:$C$404,$A13,'All Tasks'!$I$5:$I$404,"Complete") -> 0 | D13: =COUNTIFS('All Tasks'!$C$5:$C$404,$A13,'All Tasks'!$I$5:$I$404,"In Progress") -> 11 | E13: =SUMIFS('All Tasks'!$R$5:$R$404,'All Tasks'!$C$5:$C$404,$A13) -> 1 | F13: =IFERROR(SUMIFS('All Tasks'!$U$5:$U$404,'All Tasks'!$C$5:$C$404,$A13)/SUMIFS('All Tasks'!$W$5:$W$404,'All Tasks'!$C$5:$C$404,$A13),"") -> 0.5 | G13: =IF(COUNTIFS(Projects!$B$5:$B$47,$A13,Projects!$O$5:$O$47,"R")>0,"R",IF(COUNTIFS(Projects!$B$5:$B$47,$A13,Projects!$O$5:$O$47,"Y")>0,"Y",IF($B13=0,"-","G"))) -> R | I13: Quick Chadwick | J13: =SUMIFS('All Tasks'!$W$5:$W$404,'All Tasks'!$Q$5:$Q$404,$I13) -> 10 | K13: =$J13-$L13 -> 8 | L13: =COUNTIFS('All Tasks'!$Q$5:$Q$404,$I13,'All Tasks'!$I$5:$I$404,"Complete") -> 2 | M13: =SUMIFS('All Tasks'!$R$5:$R$404,'All Tasks'!$Q$5:$Q$404,$I13) -> 0 | N13: =IFERROR(SUMIFS('All Tasks'!$U$5:$U$404,'All Tasks'!$Q$5:$Q$404,$I13)/$J13,"") -> 0.415
A14: 2 – Top-of-Funnel Lead Gen | B14: =SUMIFS('All Tasks'!$W$5:$W$404,'All Tasks'!$C$5:$C$404,$A14) -> 3 | C14: =COUNTIFS('All Tasks'!$C$5:$C$404,$A14,'All Tasks'!$I$5:$I$404,"Complete") -> 1 | D14: =COUNTIFS('All Tasks'!$C$5:$C$404,$A14,'All Tasks'!$I$5:$I$404,"In Progress") -> 2 | E14: =SUMIFS('All Tasks'!$R$5:$R$404,'All Tasks'!$C$5:$C$404,$A14) -> 0 | F14: =IFERROR(SUMIFS('All Tasks'!$U$5:$U$404,'All Tasks'!$C$5:$C$404,$A14)/SUMIFS('All Tasks'!$W$5:$W$404,'All Tasks'!$C$5:$C$404,$A14),"") -> 0.53333333 | G14: =IF(COUNTIFS(Projects!$B$5:$B$47,$A14,Projects!$O$5:$O$47,"R")>0,"R",IF(COUNTIFS(Projects!$B$5:$B$47,$A14,Projects!$O$5:$O$47,"Y")>0,"Y",IF($B14=0,"-","G"))) -> G | I14: MaryFran Anderson | J14: =SUMIFS('All Tasks'!$W$5:$W$404,'All Tasks'!$Q$5:$Q$404,$I14) -> 6 | K14: =$J14-$L14 -> 6 | L14: =COUNTIFS('All Tasks'!$Q$5:$Q$404,$I14,'All Tasks'!$I$5:$I$404,"Complete") -> 0 | M14: =SUMIFS('All Tasks'!$R$5:$R$404,'All Tasks'!$Q$5:$Q$404,$I14) -> 0 | N14: =IFERROR(SUMIFS('All Tasks'!$U$5:$U$404,'All Tasks'!$Q$5:$Q$404,$I14)/$J14,"") -> 0.25
A15: 3 – Broker Channel | B15: =SUMIFS('All Tasks'!$W$5:$W$404,'All Tasks'!$C$5:$C$404,$A15) -> 7 | C15: =COUNTIFS('All Tasks'!$C$5:$C$404,$A15,'All Tasks'!$I$5:$I$404,"Complete") -> 0 | D15: =COUNTIFS('All Tasks'!$C$5:$C$404,$A15,'All Tasks'!$I$5:$I$404,"In Progress") -> 4 | E15: =SUMIFS('All Tasks'!$R$5:$R$404,'All Tasks'!$C$5:$C$404,$A15) -> 0 | F15: =IFERROR(SUMIFS('All Tasks'!$U$5:$U$404,'All Tasks'!$C$5:$C$404,$A15)/SUMIFS('All Tasks'!$W$5:$W$404,'All Tasks'!$C$5:$C$404,$A15),"") -> 0.2 | G15: =IF(COUNTIFS(Projects!$B$5:$B$47,$A15,Projects!$O$5:$O$47,"R")>0,"R",IF(COUNTIFS(Projects!$B$5:$B$47,$A15,Projects!$O$5:$O$47,"Y")>0,"Y",IF($B15=0,"-","G"))) -> R | I15: Shane Mattingly | J15: =SUMIFS('All Tasks'!$W$5:$W$404,'All Tasks'!$Q$5:$Q$404,$I15) -> 7 | K15: =$J15-$L15 -> 7 | L15: =COUNTIFS('All Tasks'!$Q$5:$Q$404,$I15,'All Tasks'!$I$5:$I$404,"Complete") -> 0 | M15: =SUMIFS('All Tasks'!$R$5:$R$404,'All Tasks'!$Q$5:$Q$404,$I15) -> 1 | N15: =IFERROR(SUMIFS('All Tasks'!$U$5:$U$404,'All Tasks'!$Q$5:$Q$404,$I15)/$J15,"") -> 0.27142857
A16: 4 – Portfolio Brand Strategy | B16: =SUMIFS('All Tasks'!$W$5:$W$404,'All Tasks'!$C$5:$C$404,$A16) -> 2 | C16: =COUNTIFS('All Tasks'!$C$5:$C$404,$A16,'All Tasks'!$I$5:$I$404,"Complete") -> 0 | D16: =COUNTIFS('All Tasks'!$C$5:$C$404,$A16,'All Tasks'!$I$5:$I$404,"In Progress") -> 2 | E16: =SUMIFS('All Tasks'!$R$5:$R$404,'All Tasks'!$C$5:$C$404,$A16) -> 0 | F16: =IFERROR(SUMIFS('All Tasks'!$U$5:$U$404,'All Tasks'!$C$5:$C$404,$A16)/SUMIFS('All Tasks'!$W$5:$W$404,'All Tasks'!$C$5:$C$404,$A16),"") -> 0.25 | G16: =IF(COUNTIFS(Projects!$B$5:$B$47,$A16,Projects!$O$5:$O$47,"R")>0,"R",IF(COUNTIFS(Projects!$B$5:$B$47,$A16,Projects!$O$5:$O$47,"Y")>0,"Y",IF($B16=0,"-","G"))) -> G | I16: Leslie Toole | J16: =SUMIFS('All Tasks'!$W$5:$W$404,'All Tasks'!$Q$5:$Q$404,$I16) -> 1 | K16: =$J16-$L16 -> 1 | L16: =COUNTIFS('All Tasks'!$Q$5:$Q$404,$I16,'All Tasks'!$I$5:$I$404,"Complete") -> 0 | M16: =SUMIFS('All Tasks'!$R$5:$R$404,'All Tasks'!$Q$5:$Q$404,$I16) -> 0 | N16: =IFERROR(SUMIFS('All Tasks'!$U$5:$U$404,'All Tasks'!$Q$5:$Q$404,$I16)/$J16,"") -> 0.5
A17: 5 – Operational Infrastructure | B17: =SUMIFS('All Tasks'!$W$5:$W$404,'All Tasks'!$C$5:$C$404,$A17) -> 1 | C17: =COUNTIFS('All Tasks'!$C$5:$C$404,$A17,'All Tasks'!$I$5:$I$404,"Complete") -> 0 | D17: =COUNTIFS('All Tasks'!$C$5:$C$404,$A17,'All Tasks'!$I$5:$I$404,"In Progress") -> 0 | E17: =SUMIFS('All Tasks'!$R$5:$R$404,'All Tasks'!$C$5:$C$404,$A17) -> 0 | F17: =IFERROR(SUMIFS('All Tasks'!$U$5:$U$404,'All Tasks'!$C$5:$C$404,$A17)/SUMIFS('All Tasks'!$W$5:$W$404,'All Tasks'!$C$5:$C$404,$A17),"") -> 0 | G17: =IF(COUNTIFS(Projects!$B$5:$B$47,$A17,Projects!$O$5:$O$47,"R")>0,"R",IF(COUNTIFS(Projects!$B$5:$B$47,$A17,Projects!$O$5:$O$47,"Y")>0,"Y",IF($B17=0,"-","G"))) -> Y | I17: Leah Hanlon | J17: =SUMIFS('All Tasks'!$W$5:$W$404,'All Tasks'!$Q$5:$Q$404,$I17) -> 1 | K17: =$J17-$L17 -> 1 | L17: =COUNTIFS('All Tasks'!$Q$5:$Q$404,$I17,'All Tasks'!$I$5:$I$404,"Complete") -> 0 | M17: =SUMIFS('All Tasks'!$R$5:$R$404,'All Tasks'!$Q$5:$Q$404,$I17) -> 0 | N17: =IFERROR(SUMIFS('All Tasks'!$U$5:$U$404,'All Tasks'!$Q$5:$Q$404,$I17)/$J17,"") -> 0.5
A18: 6 – Automation & Content | B18: =SUMIFS('All Tasks'!$W$5:$W$404,'All Tasks'!$C$5:$C$404,$A18) -> 9 | C18: =COUNTIFS('All Tasks'!$C$5:$C$404,$A18,'All Tasks'!$I$5:$I$404,"Complete") -> 2 | D18: =COUNTIFS('All Tasks'!$C$5:$C$404,$A18,'All Tasks'!$I$5:$I$404,"In Progress") -> 5 | E18: =SUMIFS('All Tasks'!$R$5:$R$404,'All Tasks'!$C$5:$C$404,$A18) -> 0 | F18: =IFERROR(SUMIFS('All Tasks'!$U$5:$U$404,'All Tasks'!$C$5:$C$404,$A18)/SUMIFS('All Tasks'!$W$5:$W$404,'All Tasks'!$C$5:$C$404,$A18),"") -> 0.42777778 | G18: =IF(COUNTIFS(Projects!$B$5:$B$47,$A18,Projects!$O$5:$O$47,"R")>0,"R",IF(COUNTIFS(Projects!$B$5:$B$47,$A18,Projects!$O$5:$O$47,"Y")>0,"Y",IF($B18=0,"-","G"))) -> G | I18: Jamie Lavigne | J18: =SUMIFS('All Tasks'!$W$5:$W$404,'All Tasks'!$Q$5:$Q$404,$I18) -> 2 | K18: =$J18-$L18 -> 2 | L18: =COUNTIFS('All Tasks'!$Q$5:$Q$404,$I18,'All Tasks'!$I$5:$I$404,"Complete") -> 0 | M18: =SUMIFS('All Tasks'!$R$5:$R$404,'All Tasks'!$Q$5:$Q$404,$I18) -> 0 | N18: =IFERROR(SUMIFS('All Tasks'!$U$5:$U$404,'All Tasks'!$Q$5:$Q$404,$I18)/$J18,"") -> 0.5
A19: 7 – Operating Rhythm | B19: =SUMIFS('All Tasks'!$W$5:$W$404,'All Tasks'!$C$5:$C$404,$A19) -> 2 | C19: =COUNTIFS('All Tasks'!$C$5:$C$404,$A19,'All Tasks'!$I$5:$I$404,"Complete") -> 0 | D19: =COUNTIFS('All Tasks'!$C$5:$C$404,$A19,'All Tasks'!$I$5:$I$404,"In Progress") -> 2 | E19: =SUMIFS('All Tasks'!$R$5:$R$404,'All Tasks'!$C$5:$C$404,$A19) -> 0 | F19: =IFERROR(SUMIFS('All Tasks'!$U$5:$U$404,'All Tasks'!$C$5:$C$404,$A19)/SUMIFS('All Tasks'!$W$5:$W$404,'All Tasks'!$C$5:$C$404,$A19),"") -> 0.25 | G19: =IF(COUNTIFS(Projects!$B$5:$B$47,$A19,Projects!$O$5:$O$47,"R")>0,"R",IF(COUNTIFS(Projects!$B$5:$B$47,$A19,Projects!$O$5:$O$47,"Y")>0,"Y",IF($B19=0,"-","G"))) -> G | I19: Steve Griffith | J19: =SUMIFS('All Tasks'!$W$5:$W$404,'All Tasks'!$Q$5:$Q$404,$I19) -> 2 | K19: =$J19-$L19 -> 2 | L19: =COUNTIFS('All Tasks'!$Q$5:$Q$404,$I19,'All Tasks'!$I$5:$I$404,"Complete") -> 0 | M19: =SUMIFS('All Tasks'!$R$5:$R$404,'All Tasks'!$Q$5:$Q$404,$I19) -> 0 | N19: =IFERROR(SUMIFS('All Tasks'!$U$5:$U$404,'All Tasks'!$Q$5:$Q$404,$I19)/$J19,"") -> 0.35
A20: 8 – Talent Evaluation | B20: =SUMIFS('All Tasks'!$W$5:$W$404,'All Tasks'!$C$5:$C$404,$A20) -> 0 | C20: =COUNTIFS('All Tasks'!$C$5:$C$404,$A20,'All Tasks'!$I$5:$I$404,"Complete") -> 0 | D20: =COUNTIFS('All Tasks'!$C$5:$C$404,$A20,'All Tasks'!$I$5:$I$404,"In Progress") -> 0 | E20: =SUMIFS('All Tasks'!$R$5:$R$404,'All Tasks'!$C$5:$C$404,$A20) -> 0 | F20: =IFERROR(SUMIFS('All Tasks'!$U$5:$U$404,'All Tasks'!$C$5:$C$404,$A20)/SUMIFS('All Tasks'!$W$5:$W$404,'All Tasks'!$C$5:$C$404,$A20),"") | G20: =IF(COUNTIFS(Projects!$B$5:$B$47,$A20,Projects!$O$5:$O$47,"R")>0,"R",IF(COUNTIFS(Projects!$B$5:$B$47,$A20,Projects!$O$5:$O$47,"Y")>0,"Y",IF($B20=0,"-","G"))) -> - | I20: Matt Motyka | J20: =SUMIFS('All Tasks'!$W$5:$W$404,'All Tasks'!$Q$5:$Q$404,$I20) -> 2 | K20: =$J20-$L20 -> 2 | L20: =COUNTIFS('All Tasks'!$Q$5:$Q$404,$I20,'All Tasks'!$I$5:$I$404,"Complete") -> 0 | M20: =SUMIFS('All Tasks'!$R$5:$R$404,'All Tasks'!$Q$5:$Q$404,$I20) -> 0 | N20: =IFERROR(SUMIFS('All Tasks'!$U$5:$U$404,'All Tasks'!$Q$5:$Q$404,$I20)/$J20,"") -> 0.4
I21: Alvaro Leal | J21: =SUMIFS('All Tasks'!$W$5:$W$404,'All Tasks'!$Q$5:$Q$404,$I21) -> 3 | K21: =$J21-$L21 -> 2 | L21: =COUNTIFS('All Tasks'!$Q$5:$Q$404,$I21,'All Tasks'!$I$5:$I$404,"Complete") -> 1 | M21: =SUMIFS('All Tasks'!$R$5:$R$404,'All Tasks'!$Q$5:$Q$404,$I21) -> 0 | N21: =IFERROR(SUMIFS('All Tasks'!$U$5:$U$404,'All Tasks'!$Q$5:$Q$404,$I21)/$J21,"") -> 0.6
I22: Cassidy Ford | J22: =SUMIFS('All Tasks'!$W$5:$W$404,'All Tasks'!$Q$5:$Q$404,$I22) -> 1 | K22: =$J22-$L22 -> 1 | L22: =COUNTIFS('All Tasks'!$Q$5:$Q$404,$I22,'All Tasks'!$I$5:$I$404,"Complete") -> 0 | M22: =SUMIFS('All Tasks'!$R$5:$R$404,'All Tasks'!$Q$5:$Q$404,$I22) -> 0 | N22: =IFERROR(SUMIFS('All Tasks'!$U$5:$U$404,'All Tasks'!$Q$5:$Q$404,$I22)/$J22,"") -> 0.5
A25: Project Status Distribution
A26: In Progress | B26: =COUNTIF(Projects!$I$5:$I$47,"In Progress") -> 9
A27: At Risk | B27: =COUNTIF(Projects!$I$5:$I$47,"At Risk") -> 1
A28: Blocked | B28: =COUNTIF(Projects!$I$5:$I$47,"Blocked") -> 1
A29: Complete | B29: =COUNTIF(Projects!$I$5:$I$47,"Complete") -> 1
A30: Not Started | B30: =COUNTIF(Projects!$I$5:$I$47,"Not Started") -> 2
A31: No Tasks Yet | B31: =COUNTIF(Projects!$I$5:$I$47,"No Tasks Yet") -> 29

Sheet Strategic Plan
B1: CGO - Strategic Plan
B3: Plan includes 8 focus areas comprised of 44 total tactics to completion over the next 100 days.
B5: 1 | C5: Build a Unified Franchise Development System | F5: Proj ID | G5: Lead | H5: Other | I5: Timing | J5: Status | K5: Notes / Commentary | M5: Legend | N5: Notes
D6: 1 | E6: Implement standardized Mutual Evaluation Process (MEP) across all brands | F6: =HYPERLINK("#Projects!A2","P1-1") -> P1-1 | G6: Developers | H6: Dobelbower | I6: Short (90) | J6: G | K6: Current franchise development processes vary significantly by brand, creating inconsistent candidate experiences and reducing scalability. | M6: na | N6: not started
D7: 2 | E7: Standardize pipeline stages, definitions, and reporting in CRM | F7: =HYPERLINK("#Projects!A3","P1-2") -> P1-2 | G7: Mattingly/Ruhlig | H7: Dobelbower | I7: Short (90) | J7: G | K7: Inconsistent pipeline definitions and reporting currently limit forecasting accuracy and portfolio-level visibility. | M7: G | N7: started & on track
D8: 3 | E8: Implement DAP (Development Action Plan) timelines for all candidates | F8: =HYPERLINK("#Projects!A4","P1-3") -> P1-3 | G8: Developers | H8: Dobelbower | I8: Short (90) | J8: G | K8: Current candidate progression lacks consistent timelines and accountability, creating unnecessary delays and reduced closing certainty. | M8: Y | N8: resolving minor issues
D9: 4 | E9: Standardize MTTD structure (confirmation event, not sales event) | F9: =HYPERLINK("#Projects!A5","P1-4") -> P1-4 | G9: Developers | H9: Dobelbower | I9: Mid (180) | J9: na | K9: MTTD execution varies significantly by brand and should function as a confirmation milestone rather than a late-stage persuasion event. | M9: R | N9: off track / needs attention
D10: 5 | E10: Standardize lead qualification across brands (Lumin, SDR, etc.) | F10: =HYPERLINK("#Projects!A6","P1-5") -> P1-5 | G10: Mattingly/Ruhlig | H10: Dobelbower | I10: Short (90) | J10: na | K10: Qualification standards currently vary by brand, resulting in inconsistent lead quality and inefficient developer utilization.
D11: 6 | E11: Launch weekly portfolio-wide pipeline call (eliminate silos) | F11: =HYPERLINK("#Projects!A7","P1-6") -> P1-6 | G11: Developers | H11: Dobelbower | I11: Short (90) | J11: C | K11: Weekly Pipeline Review kicked off 5/5
B13: =+B5+1 -> 2 | C13: Rebuild Top-of-Funnel Lead Generation | F13: Proj ID | G13: Lead | H13: Other | I13: Timing | J13: Status | K13: Notes / Commentary
D14: 1 | E14: Centralize non-broker marketing under Chadwick | F14: =HYPERLINK("#Projects!A8","P2-1") -> P2-1 | G14: Chadwick | H14: Dobelbower | I14: Short (90) | J14: C | K14: Non-broker lead generation efforts are currently fragmented across brands and lack centralized strategic prioritzation.
D15: 2 | E15: Reallocate spend toward non-broker sourced channels | F15: =HYPERLINK("#Projects!A9","P2-2") -> P2-2 | G15: Thoma/Chadwick | H15: Dobelbower | I15: Short (90) | J15: na | K15: Marketing spend allocation is not consistently aligned with lead quality, conversion performance, or long-term scalability objectives.
D16: 3 | E16: Build video-first funnel | F16: =HYPERLINK("#Projects!A10","P2-3") -> P2-3 | G16: M. Anderson/Leal | H16: Dobelbower | I16: Short (90) | J16: G | K16: Video and automation create an opportunity to improve candidate education, consistency, and developer scalability across all brands.
D17: 4 | E17: Establish portfolio-level KPIs benchmarked against AFDR ratios | F17: =HYPERLINK("#Projects!A11","P2-4") -> P2-4 | G17: Mattingly | H17: Dobelbower | I17: Mid (180) | J17: na | K17: Portfolio-level KPIs are necessary to properly evaluate marketing efficiency, lead quality, and channel performance across brands.
D18: 5 | E18: Eliminate low-quality lead sources | F18: =HYPERLINK("#Projects!A12","P2-5") -> P2-5 | G18: Chadwick | H18: Dobelbower | I18: Short (90) | J18: na | K18: Certain lead sources currently produce volume without corresponding conversion performance or franchisee quality.
B20: =+B13+1 -> 3 | C20: Optimize Broker Channel Performance | F20: Proj ID | G20: Lead | H20: Other | I20: Timing | J20: Status | K20: Notes / Commentary
D21: 1 | E21: Assign MaryFran as broker channel owner | F21: =HYPERLINK("#Projects!A13","P3-1") -> P3-1 | G21: MF. Anderson | H21: Dobelbower | I21: Short (90) | J21: C | K21: Broker relationships currently lack centralized ownership and consistent management across the portfolio.
D22: 2 | E22: Route 100% of broker leads through CRM for centralized intake and visibility. | F22: =HYPERLINK("#Projects!A14","P3-2") -> P3-2 | G22: Mattingly | H22: Dobelbower | I22: Short (90) | J22: G | K22: Shared inboxes and inconsistent lead routing create missed opportunities and limited visibility into broker activity.
D23: 3 | E23: Implement rules-based lead distribution | F23: =HYPERLINK("#Projects!A15","P3-3") -> P3-3 | G23: Mattingly/Ruhlig | H23: Dobelbower | I23: Short (90) | J23: na | K23: Lead distribution should prioritize fairness, responsiveness, and performance while eliminating perception of uneven opportunity.
D24: 4 | E24: Enforce speed-to-lead SLAs | F24: =HYPERLINK("#Projects!A16","P3-4") -> P3-4 | G24: MF. Anderson | H24: Dobelbower | I24: Short (90) | J24: na | K24: Response speed remains one of the largest drivers of broker lead conversion and candidate engagement.
D25: 5 | E25: Segment Brokers into Tier 1/Tier 2/ Tier 3 | F25: =HYPERLINK("#Projects!A17","P3-5") -> P3-5 | G25: MF. Anderson | H25: Dobelbower | J25: na | K25: Not all broker relationships generate equal value, requiring prioritization based on production and lead quality.
D26: 6 | E26: Introduce performance-based lead weighting | F26: =HYPERLINK("#Projects!A18","P3-6") -> P3-6 | G26: Mattingly/Ruhlig | H26: Dobelbower | J26: na | K26: Lead distribution should reward execution and conversion performance while maintaining equitable opportunity across the team.
D27: 7 | E27: Build weekly broker channel performance reporting | F27: =HYPERLINK("#Projects!A19","P3-7") -> P3-7 | G27: Mattingly/Ruhlig | H27: Dobelbower | I27: Short (90) | J27: na | K27: Broker performance visibility is currently limited, making it difficult to optimize relationships and conversion performance.
B29: =+B20+1 -> 4 | C29: Execute Portfolio-Based Brand Strategy | F29: Proj ID | G29: Lead | H29: Other | I29: Timing | J29: Status | K29: Notes / Commentary
D30: 1 | E30: Position The Seals as a low-cost, high-whitespace growth brand | F30: =HYPERLINK("#Projects!A20","P4-1") -> P4-1 | G30: Anderson/Chadwick | H30: Dobelbower | I30: Short (90) | J30: G | K30: The Seals presents an opportunity for accelerated unit growth due to low investment requirements, recurring revenue characteristics, and significant whitespace availability.
D31: 2 | E31: Position 1-Tom as a flagship growth brand | F31: =HYPERLINK("#Projects!A21","P4-2") -> P4-2 | G31: Anderson/Chadwick | H31: Dobelbower | I31: Short (90) | J31: G | K31: 1-Tom possesses strong branding, broad market appeal, and favorable long-term scalability characteristics.
D32: 3 | E32: Align Kitchen Guard growth strategy with Strategic Accounts initiatives | F32: =HYPERLINK("#Projects!A22","P4-3") -> P4-3 | G32: Hatcher | H32: Dobelbower | I32: Long (270) | J32: G | K32: Kitchen Guard’s compliance-driven recurring revenue model aligns well with enterprise and Strategic Account positioning opportunities.
D33: 4 | E33: Reposition Prism as a multi-service platform opportunity | F33: =HYPERLINK("#Projects!A23","P4-4") -> P4-4 | G33: Anderson/Chadwick | H33: Dobelbower | I33: Short (90) | J33: G | K33: Prism’s multi-service structure creates an opportunity to increase average deal size and long-term franchisee value.
D34: 5 | E34: Maintain stable, quality-focused growth for U.S. Lawns | F34: =HYPERLINK("#Projects!A24","P4-5") -> P4-5 | G34: Steeves | H34: Dobelbower | I34: Short (90) | J34: G | K34: U.S. Lawns serves as a mature and stable portfolio brand with strong recognition and operational consistency.
D35: 6 | E35: Utilize Clintar as a selective strategic growth vehicle | F35: =HYPERLINK("#Projects!A25","P4-6") -> P4-6 | G35: Motyka | H35: Dobelbower | I35: Mid (180) | J35: G | K35: Clintar should be positioned toward experienced operators and strategic opportunities rather than high-volume franchise sales efforts.
D36: 7 | E36: Rebuild validation and franchisee confidence within MilliCare | F36: =HYPERLINK("#Projects!A26","P4-7") -> P4-7 | G36: Griffith/Weaver | H36: Dobelbower | I36: Long (270) | J36: na | K36: Long-term MilliCare growth requires improvement in franchisee sentiment, validation consistency, and economic confidence.
B38: =+B29+1 -> 5 | C38: Strengthen Operational Infrastructure & Visbility | F38: Proj ID | G38: Lead | H38: Other | I38: Timing | J38: Status | K38: Notes / Commentary
D39: 1 | E39: Replace shared territory check inboxes with CRM routing | F39: =HYPERLINK("#Projects!A27","P5-1") -> P5-1 | G39: Mattingly | H39: Dobelbower | I39: Short (90) | J39: na | K39: Shared territory check workflows currently create operational inefficiencies and inconsistent response times.
D40: 2 | E40: Implement territory check response SLA | F40: =HYPERLINK("#Projects!A28","P5-2") -> P5-2 | G40: MF. Anderson | H40: Dobelbower | I40: Short (90) | J40: G | K40: Fast and consistent response times are critical to broker experience and franchise sales momentum.
D41: 3 | E41: Standardize lead assignment and routing logic | F41: =HYPERLINK("#Projects!A29","P5-3") -> P5-3 | G41: Mattingly | H41: Dobelbower | I41: Short (90) | J41: na | K41: Lead routing should prioritize transparency, accountability, and operational consistency across brands.
D42: 4 | E42: Build centralized KPI dashboard and reporting visibility | F42: =HYPERLINK("#Projects!A30","P5-4") -> P5-4 | G42: Mattingly/Ruhlig | H42: Dobelbower | I42: Mid (180) | J42: na | K42: Leadership currently lacks consistent portfolio-wide visibility into funnel health and conversion trends.
D43: 5 | E43: Improve CRM adoption and reporting discipline | F43: =HYPERLINK("#Projects!A31","P5-5") -> P5-5 | G43: Developers | H43: Dobelbower/Mattingly | I43: Short (90) | J43: G | K43: Consistent CRM usage is required to improve forecasting accuracy and operational visibility.
C45: Leverage Automation & Content to Improve Scalability | F45: Proj ID | G45: Lead | H45: Other | I45: Timing | J45: Status | K45: Notes / Commentary
B46: 6 | D46: 1 | E46: Develop standardized brand overview videos | F46: =HYPERLINK("#Projects!A32","P6-1") -> P6-1 | G46: M Anderson/Leal | H46: Dobelbower | I46: Mid (180) | J46: G | K46: Standardized brand messaging improves candidate consistency and reduces repetitive developer workload.
D47: 2 | E47: Develop validation preparation and candidate education content | F47: =HYPERLINK("#Projects!A33","P6-2") -> P6-2 | G47: Dobelbower | H47: N/A | I47: Short (90) | J47: G | K47: Better-prepared candidates improve validation outcomes and increase overall process efficiency.
D48: 3 | E48: Create standardized FDD and process walkthrough videos | F48: =HYPERLINK("#Projects!A34","P6-3") -> P6-3 | G48: M Anderson/Leal | H48: Dobelbower | I48: Short (90) | J48: na | K48: Automation of repetitive educational content increases scalability and developer capacity.
D49: 4 | E49: Build centralized content library across brands | F49: =HYPERLINK("#Projects!A35","P6-4") -> P6-4 | G49: M Anderson/Leal | H49: Dobelbower | I49: Long (270) | J49: G | K49: Centralized content infrastructure improves consistency and speed of deployment across the portfolio.
D50: 6 | E50: Automate early-stage candidate education | F50: =HYPERLINK("#Projects!A36","P6-5") -> P6-5 | G50: Mattingly/Ruhlig | H50: Dobelbower | I50: Mid (180) | J50: G | K50: Automation creates operational leverage while improving consistency of the candidate experience.
B53: 7 | C53: Establish Operating Rhythm & Accountability | F53: Proj ID | G53: Lead | H53: Other | I53: Timing | J53: Status | K53: Notes / Commentary
D54: 1 | E54: Implement weekly KPI scorecards by brand, developer, and source | F54: =HYPERLINK("#Projects!A37","P7-1") -> P7-1 | G54: Mattingly | H54: Dobelbower | I54: Mid (180) | J54: G | K54: Transparent performance reporting improves visibility and operational decision-making.
D55: 2 | E55: Conduct monthly funnel conversion and marketing reviews | F55: =HYPERLINK("#Projects!A38","P7-2") -> P7-2 | G55: Chadwick/MF Anderson | H55: Dobelbower | I55: Short (90) | J55: G | K55: Regular conversion analysis is necessary to optimize marketing efficiency and franchise development performance.
D56: 3 | E56: Standardize forecasting methodology | F56: =HYPERLINK("#Projects!A39","P7-3") -> P7-3 | G56: Mattingly | H56: Dobelbower | I56: Short (90) | J56: G | K56: Forecasting methodologies currently vary across brands, limiting portfolio-level planning and visibility.
D57: 4 | E57: Establish clear initiative ownership and accountability | F57: =HYPERLINK("#Projects!A40","P7-4") -> P7-4 | G57: Dobelbower | H57: N/A | I57: Short (90) | J57: G | K57: Consistent ownership structures are required to improve execution discipline and cross-functional alignment.
B60: 8 | C60: Talent Evaluation | F60: Proj ID | G60: Lead | H60: Other | I60: Timing | J60: Status | K60: Notes / Commentary
D61: 1 | E61: Evaluate the current Franchise Development team to identify top performers, growth opportunities, and long-term leadership potential. | F61: =HYPERLINK("#Projects!A41","P8-1") -> P8-1 | G61: Dobelbower | H61: N/A | I61: Short (90) | J61: G | K61: This assessment will help ensure the organization has the right talent structure in place to support scalable growth across all brands.
D62: 2 | E62: Establish standardized performance expectations and KPI accountability across all Franchise Development roles. | F62: =HYPERLINK("#Projects!A42","P8-2") -> P8-2 | G62: Dobelbower | H62: N/A | I62: Short (90) | J62: G | K62: Creating consistent scorecards and benchmarks will improve visibility, alignment, and operational discipline throughout the department.
D63: 3 | E63: Identify capability gaps and organizational needs across recruiting, sales execution, broker management, and lead conversion. | F63: =HYPERLINK("#Projects!A43","P8-3") -> P8-3 | G63: Dobelbower | H63: N/A | I63: Short (90) | J63: G | K63: Understanding where additional support, training, or restructuring is needed will strengthen overall development effectiveness.
D64: 4 | E64: Build a long-term talent development strategy focused on coaching, succession planning, and cross-brand collaboration. | F64: =HYPERLINK("#Projects!A44","P8-4") -> P8-4 | G64: Dobelbower | H64: N/A | I64: Short (90) | J64: G | K64: Investing in team development will create a more scalable and sustainable franchise development organization over time.

Sheet Projects
A1: Projects — Tactic Roll-Up (auto)
A2: AGGREGATION LAYER · One row per tactic. Status, %, risks and milestones roll up automatically from the 1:1 tabs. Run project reviews here or open the Project Review tab.
A4: Project ID | B4: Focus Area | C4: Project / Tactic Name | D4: Exec Owner | E4: Lead Owner | F4: Strategic Goal (why) | G4: Timing | H4: Tasks | I4: Current Status | J4: % Complete | K4: Overdue | L4: Blocked | M4: Key Risks | N4: Next Milestone | O4: Health | P4: Review
A5: P1-1 | B5: 1 – Unified Development System | C5: Implement standardized Mutual Evaluation Process (MEP) across all brands | D5: Dobelbower | E5: Developers | F5: Current franchise development processes vary significantly by brand, creating inconsistent candidate experiences and reducing scalability. | G5: Short (90) | H5: =COUNTIF('All Tasks'!$B$2:$B$404,$A5) -> 10 | I5: =IF($H5=0,"No Tasks Yet",IF($L5>0,"Blocked",IF($K5>0,"At Risk",IF($R5=$H5,"Complete",IF($S5>0,"In Progress","Not Started"))))) -> In Progress | J5: =IF($H5=0,"",ROUND(SUMIFS('All Tasks'!$U$2:$U$404,'All Tasks'!$B$2:$B$404,$A5)/$H5,2)) -> 0.5 | K5: =SUMIFS('All Tasks'!$R$2:$R$404,'All Tasks'!$B$2:$B$404,$A5) -> 0 | L5: =COUNTIFS('All Tasks'!$B$2:$B$404,$A5,'All Tasks'!$I$2:$I$404,"Blocked") -> 0 | M5: =IF($H5=0,"",IF($L5>0,$L5&" blocked / "&$K5&" overdue",IF($K5>0,$K5&" overdue task(s)",IF($T5>0,$T5&" roadblock(s) flagged","On track")))) -> On track | N5: =IFERROR(minifs('All Tasks'!$L$2:$L$404,'All Tasks'!$B$2:$B$404,$A5,'All Tasks'!$I$2:$I$404,"<>Complete",'All Tasks'!$L$2:$L$404,">"&(TODAY()-1)),"") | O5: =IF($H5=0,"",IF(OR($I5="Blocked",$I5="At Risk"),"R",IF(OR($I5="Complete",$I5="In Progress"),"G","Y"))) -> G | P5: =HYPERLINK("#'Project Review'!C3","Open") -> Open | R5: =COUNTIFS('All Tasks'!$B$2:$B$404,$A5,'All Tasks'!$I$2:$I$404,"Complete") -> 0 | S5: =COUNTIFS('All Tasks'!$B$2:$B$404,$A5,'All Tasks'!$I$2:$I$404,"In Progress")+COUNTIFS('All Tasks'!$B$2:$B$404,$A5,'All Tasks'!$I$2:$I$404,"Waiting on Someone") -> 10 | T5: =SUMIFS('All Tasks'!$V$2:$V$404,'All Tasks'!$B$2:$B$404,$A5) -> 0
A6: P1-2 | B6: 1 – Unified Development System | C6: Standardize pipeline stages, definitions, and reporting in CRM | D6: Dobelbower | E6: Mattingly/Ruhlig | F6: Inconsistent pipeline definitions and reporting currently limit forecasting accuracy and portfolio-level visibility. | G6: Short (90) | H6: =COUNTIF('All Tasks'!$B$2:$B$404,$A6) -> 1 | I6: =IF($H6=0,"No Tasks Yet",IF($L6>0,"Blocked",IF($K6>0,"At Risk",IF($R6=$H6,"Complete",IF($S6>0,"In Progress","Not Started"))))) -> At Risk | J6: =IF($H6=0,"",ROUND(SUMIFS('All Tasks'!$U$2:$U$404,'All Tasks'!$B$2:$B$404,$A6)/$H6,2)) -> 0.5 | K6: =SUMIFS('All Tasks'!$R$2:$R$404,'All Tasks'!$B$2:$B$404,$A6) -> 1 | L6: =COUNTIFS('All Tasks'!$B$2:$B$404,$A6,'All Tasks'!$I$2:$I$404,"Blocked") -> 0 | M6: =IF($H6=0,"",IF($L6>0,$L6&" blocked / "&$K6&" overdue",IF($K6>0,$K6&" overdue task(s)",IF($T6>0,$T6&" roadblock(s) flagged","On track")))) -> 1 overdue task(s) | N6: =IFERROR(minifs('All Tasks'!$L$2:$L$404,'All Tasks'!$B$2:$B$404,$A6,'All Tasks'!$I$2:$I$404,"<>Complete",'All Tasks'!$L$2:$L$404,">"&(TODAY()-1)),"") | O6: =IF($H6=0,"",IF(OR($I6="Blocked",$I6="At Risk"),"R",IF(OR($I6="Complete",$I6="In Progress"),"G","Y"))) -> R | P6: =HYPERLINK("#'Project Review'!C3","Open") -> Open | R6: =COUNTIFS('All Tasks'!$B$2:$B$404,$A6,'All Tasks'!$I$2:$I$404,"Complete") -> 0 | S6: =COUNTIFS('All Tasks'!$B$2:$B$404,$A6,'All Tasks'!$I$2:$I$404,"In Progress")+COUNTIFS('All Tasks'!$B$2:$B$404,$A6,'All Tasks'!$I$2:$I$404,"Waiting on Someone") -> 1 | T6: =SUMIFS('All Tasks'!$V$2:$V$404,'All Tasks'!$B$2:$B$404,$A6) -> 0
A7: P1-3 | B7: 1 – Unified Development System | C7: Implement DAP (Development Action Plan) timelines for all candidates | D7: Dobelbower | E7: Developers | F7: Current candidate progression lacks consistent timelines and accountability, creating unnecessary delays and reduced closing certainty. | G7: Short (90) | H7: =COUNTIF('All Tasks'!$B$2:$B$404,$A7) -> 0 | I7: =IF($H7=0,"No Tasks Yet",IF($L7>0,"Blocked",IF($K7>0,"At Risk",IF($R7=$H7,"Complete",IF($S7>0,"In Progress","Not Started"))))) -> No Tasks Yet | J7: =IF($H7=0,"",ROUND(SUMIFS('All Tasks'!$U$2:$U$404,'All Tasks'!$B$2:$B$404,$A7)/$H7,2)) | K7: =SUMIFS('All Tasks'!$R$2:$R$404,'All Tasks'!$B$2:$B$404,$A7) -> 0 | L7: =COUNTIFS('All Tasks'!$B$2:$B$404,$A7,'All Tasks'!$I$2:$I$404,"Blocked") -> 0 | M7: =IF($H7=0,"",IF($L7>0,$L7&" blocked / "&$K7&" overdue",IF($K7>0,$K7&" overdue task(s)",IF($T7>0,$T7&" roadblock(s) flagged","On track")))) | N7: =IFERROR(minifs('All Tasks'!$L$2:$L$404,'All Tasks'!$B$2:$B$404,$A7,'All Tasks'!$I$2:$I$404,"<>Complete",'All Tasks'!$L$2:$L$404,">"&(TODAY()-1)),"") | O7: =IF($H7=0,"",IF(OR($I7="Blocked",$I7="At Risk"),"R",IF(OR($I7="Complete",$I7="In Progress"),"G","Y"))) | P7: =HYPERLINK("#'Project Review'!C3","Open") -> Open | R7: =COUNTIFS('All Tasks'!$B$2:$B$404,$A7,'All Tasks'!$I$2:$I$404,"Complete") -> 0 | S7: =COUNTIFS('All Tasks'!$B$2:$B$404,$A7,'All Tasks'!$I$2:$I$404,"In Progress")+COUNTIFS('All Tasks'!$B$2:$B$404,$A7,'All Tasks'!$I$2:$I$404,"Waiting on Someone") -> 0 | T7: =SUMIFS('All Tasks'!$V$2:$V$404,'All Tasks'!$B$2:$B$404,$A7) -> 0
A8: P1-4 | B8: 1 – Unified Development System | C8: Standardize MTTD structure (confirmation event, not sales event) | D8: Dobelbower | E8: Developers | F8: MTTD execution varies significantly by brand and should function as a confirmation milestone rather than a late-stage persuasion event. | G8: Mid (180) | H8: =COUNTIF('All Tasks'!$B$2:$B$404,$A8) -> 0 | I8: =IF($H8=0,"No Tasks Yet",IF($L8>0,"Blocked",IF($K8>0,"At Risk",IF($R8=$H8,"Complete",IF($S8>0,"In Progress","Not Started"))))) -> No Tasks Yet | J8: =IF($H8=0,"",ROUND(SUMIFS('All Tasks'!$U$2:$U$404,'All Tasks'!$B$2:$B$404,$A8)/$H8,2)) | K8: =SUMIFS('All Tasks'!$R$2:$R$404,'All Tasks'!$B$2:$B$404,$A8) -> 0 | L8: =COUNTIFS('All Tasks'!$B$2:$B$404,$A8,'All Tasks'!$I$2:$I$404,"Blocked") -> 0 | M8: =IF($H8=0,"",IF($L8>0,$L8&" blocked / "&$K8&" overdue",IF($K8>0,$K8&" overdue task(s)",IF($T8>0,$T8&" roadblock(s) flagged","On track")))) | N8: =IFERROR(minifs('All Tasks'!$L$2:$L$404,'All Tasks'!$B$2:$B$404,$A8,'All Tasks'!$I$2:$I$404,"<>Complete",'All Tasks'!$L$2:$L$404,">"&(TODAY()-1)),"") | O8: =IF($H8=0,"",IF(OR($I8="Blocked",$I8="At Risk"),"R",IF(OR($I8="Complete",$I8="In Progress"),"G","Y"))) | P8: =HYPERLINK("#'Project Review'!C3","Open") -> Open | R8: =COUNTIFS('All Tasks'!$B$2:$B$404,$A8,'All Tasks'!$I$2:$I$404,"Complete") -> 0 | S8: =COUNTIFS('All Tasks'!$B$2:$B$404,$A8,'All Tasks'!$I$2:$I$404,"In Progress")+COUNTIFS('All Tasks'!$B$2:$B$404,$A8,'All Tasks'!$I$2:$I$404,"Waiting on Someone") -> 0 | T8: =SUMIFS('All Tasks'!$V$2:$V$404,'All Tasks'!$B$2:$B$404,$A8) -> 0
A9: P1-5 | B9: 1 – Unified Development System | C9: Standardize lead qualification across brands (Lumin, SDR, etc.) | D9: Dobelbower | E9: Mattingly/Ruhlig | F9: Qualification standards currently vary by brand, resulting in inconsistent lead quality and inefficient developer utilization. | G9: Short (90) | H9: =COUNTIF('All Tasks'!$B$2:$B$404,$A9) -> 0 | I9: =IF($H9=0,"No Tasks Yet",IF($L9>0,"Blocked",IF($K9>0,"At Risk",IF($R9=$H9,"Complete",IF($S9>0,"In Progress","Not Started"))))) -> No Tasks Yet | J9: =IF($H9=0,"",ROUND(SUMIFS('All Tasks'!$U$2:$U$404,'All Tasks'!$B$2:$B$404,$A9)/$H9,2)) | K9: =SUMIFS('All Tasks'!$R$2:$R$404,'All Tasks'!$B$2:$B$404,$A9) -> 0 | L9: =COUNTIFS('All Tasks'!$B$2:$B$404,$A9,'All Tasks'!$I$2:$I$404,"Blocked") -> 0 | M9: =IF($H9=0,"",IF($L9>0,$L9&" blocked / "&$K9&" overdue",IF($K9>0,$K9&" overdue task(s)",IF($T9>0,$T9&" roadblock(s) flagged","On track")))) | N9: =IFERROR(minifs('All Tasks'!$L$2:$L$404,'All Tasks'!$B$2:$B$404,$A9,'All Tasks'!$I$2:$I$404,"<>Complete",'All Tasks'!$L$2:$L$404,">"&(TODAY()-1)),"") | O9: =IF($H9=0,"",IF(OR($I9="Blocked",$I9="At Risk"),"R",IF(OR($I9="Complete",$I9="In Progress"),"G","Y"))) | P9: =HYPERLINK("#'Project Review'!C3","Open") -> Open | R9: =COUNTIFS('All Tasks'!$B$2:$B$404,$A9,'All Tasks'!$I$2:$I$404,"Complete") -> 0 | S9: =COUNTIFS('All Tasks'!$B$2:$B$404,$A9,'All Tasks'!$I$2:$I$404,"In Progress")+COUNTIFS('All Tasks'!$B$2:$B$404,$A9,'All Tasks'!$I$2:$I$404,"Waiting on Someone") -> 0 | T9: =SUMIFS('All Tasks'!$V$2:$V$404,'All Tasks'!$B$2:$B$404,$A9) -> 0
A10: P1-6 | B10: 1 – Unified Development System | C10: Launch weekly portfolio-wide pipeline call (eliminate silos) | D10: Dobelbower | E10: Developers | F10: Weekly Pipeline Review kicked off 5/5 | G10: Short (90) | H10: =COUNTIF('All Tasks'!$B$2:$B$404,$A10) -> 0 | I10: =IF($H10=0,"No Tasks Yet",IF($L10>0,"Blocked",IF($K10>0,"At Risk",IF($R10=$H10,"Complete",IF($S10>0,"In Progress","Not Started"))))) -> No Tasks Yet | J10: =IF($H10=0,"",ROUND(SUMIFS('All Tasks'!$U$2:$U$404,'All Tasks'!$B$2:$B$404,$A10)/$H10,2)) | K10: =SUMIFS('All Tasks'!$R$2:$R$404,'All Tasks'!$B$2:$B$404,$A10) -> 0 | L10: =COUNTIFS('All Tasks'!$B$2:$B$404,$A10,'All Tasks'!$I$2:$I$404,"Blocked") -> 0 | M10: =IF($H10=0,"",IF($L10>0,$L10&" blocked / "&$K10&" overdue",IF($K10>0,$K10&" overdue task(s)",IF($T10>0,$T10&" roadblock(s) flagged","On track")))) | N10: =IFERROR(minifs('All Tasks'!$L$2:$L$404,'All Tasks'!$B$2:$B$404,$A10,'All Tasks'!$I$2:$I$404,"<>Complete",'All Tasks'!$L$2:$L$404,">"&(TODAY()-1)),"") | O10: =IF($H10=0,"",IF(OR($I10="Blocked",$I10="At Risk"),"R",IF(OR($I10="Complete",$I10="In Progress"),"G","Y"))) | P10: =HYPERLINK("#'Project Review'!C3","Open") -> Open | R10: =COUNTIFS('All Tasks'!$B$2:$B$404,$A10,'All Tasks'!$I$2:$I$404,"Complete") -> 0 | S10: =COUNTIFS('All Tasks'!$B$2:$B$404,$A10,'All Tasks'!$I$2:$I$404,"In Progress")+COUNTIFS('All Tasks'!$B$2:$B$404,$A10,'All Tasks'!$I$2:$I$404,"Waiting on Someone") -> 0 | T10: =SUMIFS('All Tasks'!$V$2:$V$404,'All Tasks'!$B$2:$B$404,$A10) -> 0
A11: P2-1 | B11: 2 – Top-of-Funnel Lead Gen | C11: Centralize non-broker marketing under Chadwick | D11: Dobelbower | E11: Chadwick | F11: Non-broker lead generation efforts are currently fragmented across brands and lack centralized strategic prioritzation. | G11: Short (90) | H11: =COUNTIF('All Tasks'!$B$2:$B$404,$A11) -> 0 | I11: =IF($H11=0,"No Tasks Yet",IF($L11>0,"Blocked",IF($K11>0,"At Risk",IF($R11=$H11,"Complete",IF($S11>0,"In Progress","Not Started"))))) -> No Tasks Yet | J11: =IF($H11=0,"",ROUND(SUMIFS('All Tasks'!$U$2:$U$404,'All Tasks'!$B$2:$B$404,$A11)/$H11,2)) | K11: =SUMIFS('All Tasks'!$R$2:$R$404,'All Tasks'!$B$2:$B$404,$A11) -> 0 | L11: =COUNTIFS('All Tasks'!$B$2:$B$404,$A11,'All Tasks'!$I$2:$I$404,"Blocked") -> 0 | M11: =IF($H11=0,"",IF($L11>0,$L11&" blocked / "&$K11&" overdue",IF($K11>0,$K11&" overdue task(s)",IF($T11>0,$T11&" roadblock(s) flagged","On track")))) | N11: =IFERROR(minifs('All Tasks'!$L$2:$L$404,'All Tasks'!$B$2:$B$404,$A11,'All Tasks'!$I$2:$I$404,"<>Complete",'All Tasks'!$L$2:$L$404,">"&(TODAY()-1)),"") | O11: =IF($H11=0,"",IF(OR($I11="Blocked",$I11="At Risk"),"R",IF(OR($I11="Complete",$I11="In Progress"),"G","Y"))) | P11: =HYPERLINK("#'Project Review'!C3","Open") -> Open | R11: =COUNTIFS('All Tasks'!$B$2:$B$404,$A11,'All Tasks'!$I$2:$I$404,"Complete") -> 0 | S11: =COUNTIFS('All Tasks'!$B$2:$B$404,$A11,'All Tasks'!$I$2:$I$404,"In Progress")+COUNTIFS('All Tasks'!$B$2:$B$404,$A11,'All Tasks'!$I$2:$I$404,"Waiting on Someone") -> 0 | T11: =SUMIFS('All Tasks'!$V$2:$V$404,'All Tasks'!$B$2:$B$404,$A11) -> 0
A12: P2-2 | B12: 2 – Top-of-Funnel Lead Gen | C12: Reallocate spend toward non-broker sourced channels | D12: Dobelbower | E12: Thoma/Chadwick | F12: Marketing spend allocation is not consistently aligned with lead quality, conversion performance, or long-term scalability objectives. | G12: Short (90) | H12: =COUNTIF('All Tasks'!$B$2:$B$404,$A12) -> 1 | I12: =IF($H12=0,"No Tasks Yet",IF($L12>0,"Blocked",IF($K12>0,"At Risk",IF($R12=$H12,"Complete",IF($S12>0,"In Progress","Not Started"))))) -> Complete | J12: =IF($H12=0,"",ROUND(SUMIFS('All Tasks'!$U$2:$U$404,'All Tasks'!$B$2:$B$404,$A12)/$H12,2)) -> 1 | K12: =SUMIFS('All Tasks'!$R$2:$R$404,'All Tasks'!$B$2:$B$404,$A12) -> 0 | L12: =COUNTIFS('All Tasks'!$B$2:$B$404,$A12,'All Tasks'!$I$2:$I$404,"Blocked") -> 0 | M12: =IF($H12=0,"",IF($L12>0,$L12&" blocked / "&$K12&" overdue",IF($K12>0,$K12&" overdue task(s)",IF($T12>0,$T12&" roadblock(s) flagged","On track")))) -> On track | N12: =IFERROR(minifs('All Tasks'!$L$2:$L$404,'All Tasks'!$B$2:$B$404,$A12,'All Tasks'!$I$2:$I$404,"<>Complete",'All Tasks'!$L$2:$L$404,">"&(TODAY()-1)),"") | O12: =IF($H12=0,"",IF(OR($I12="Blocked",$I12="At Risk"),"R",IF(OR($I12="Complete",$I12="In Progress"),"G","Y"))) -> G | P12: =HYPERLINK("#'Project Review'!C3","Open") -> Open | R12: =COUNTIFS('All Tasks'!$B$2:$B$404,$A12,'All Tasks'!$I$2:$I$404,"Complete") -> 1 | S12: =COUNTIFS('All Tasks'!$B$2:$B$404,$A12,'All Tasks'!$I$2:$I$404,"In Progress")+COUNTIFS('All Tasks'!$B$2:$B$404,$A12,'All Tasks'!$I$2:$I$404,"Waiting on Someone") -> 0 | T12: =SUMIFS('All Tasks'!$V$2:$V$404,'All Tasks'!$B$2:$B$404,$A12) -> 0
A13: P2-3 | B13: 2 – Top-of-Funnel Lead Gen | C13: Build video-first funnel | D13: Dobelbower | E13: M. Anderson/Leal | F13: Video and automation create an opportunity to improve candidate education, consistency, and developer scalability across all brands. | G13: Short (90) | H13: =COUNTIF('All Tasks'!$B$2:$B$404,$A13) -> 2 | I13: =IF($H13=0,"No Tasks Yet",IF($L13>0,"Blocked",IF($K13>0,"At Risk",IF($R13=$H13,"Complete",IF($S13>0,"In Progress","Not Started"))))) -> In Progress | J13: =IF($H13=0,"",ROUND(SUMIFS('All Tasks'!$U$2:$U$404,'All Tasks'!$B$2:$B$404,$A13)/$H13,2)) -> 0.3 | K13: =SUMIFS('All Tasks'!$R$2:$R$404,'All Tasks'!$B$2:$B$404,$A13) -> 0 | L13: =COUNTIFS('All Tasks'!$B$2:$B$404,$A13,'All Tasks'!$I$2:$I$404,"Blocked") -> 0 | M13: =IF($H13=0,"",IF($L13>0,$L13&" blocked / "&$K13&" overdue",IF($K13>0,$K13&" overdue task(s)",IF($T13>0,$T13&" roadblock(s) flagged","On track")))) -> On track | N13: =IFERROR(minifs('All Tasks'!$L$2:$L$404,'All Tasks'!$B$2:$B$404,$A13,'All Tasks'!$I$2:$I$404,"<>Complete",'All Tasks'!$L$2:$L$404,">"&(TODAY()-1)),"") | O13: =IF($H13=0,"",IF(OR($I13="Blocked",$I13="At Risk"),"R",IF(OR($I13="Complete",$I13="In Progress"),"G","Y"))) -> G | P13: =HYPERLINK("#'Project Review'!C3","Open") -> Open | R13: =COUNTIFS('All Tasks'!$B$2:$B$404,$A13,'All Tasks'!$I$2:$I$404,"Complete") -> 0 | S13: =COUNTIFS('All Tasks'!$B$2:$B$404,$A13,'All Tasks'!$I$2:$I$404,"In Progress")+COUNTIFS('All Tasks'!$B$2:$B$404,$A13,'All Tasks'!$I$2:$I$404,"Waiting on Someone") -> 2 | T13: =SUMIFS('All Tasks'!$V$2:$V$404,'All Tasks'!$B$2:$B$404,$A13) -> 0
A14: P2-4 | B14: 2 – Top-of-Funnel Lead Gen | C14: Establish portfolio-level KPIs benchmarked against AFDR ratios | D14: Dobelbower | E14: Mattingly | F14: Portfolio-level KPIs are necessary to properly evaluate marketing efficiency, lead quality, and channel performance across brands. | G14: Mid (180) | H14: =COUNTIF('All Tasks'!$B$2:$B$404,$A14) -> 0 | I14: =IF($H14=0,"No Tasks Yet",IF($L14>0,"Blocked",IF($K14>0,"At Risk",IF($R14=$H14,"Complete",IF($S14>0,"In Progress","Not Started"))))) -> No Tasks Yet | J14: =IF($H14=0,"",ROUND(SUMIFS('All Tasks'!$U$2:$U$404,'All Tasks'!$B$2:$B$404,$A14)/$H14,2)) | K14: =SUMIFS('All Tasks'!$R$2:$R$404,'All Tasks'!$B$2:$B$404,$A14) -> 0 | L14: =COUNTIFS('All Tasks'!$B$2:$B$404,$A14,'All Tasks'!$I$2:$I$404,"Blocked") -> 0 | M14: =IF($H14=0,"",IF($L14>0,$L14&" blocked / "&$K14&" overdue",IF($K14>0,$K14&" overdue task(s)",IF($T14>0,$T14&" roadblock(s) flagged","On track")))) | N14: =IFERROR(minifs('All Tasks'!$L$2:$L$404,'All Tasks'!$B$2:$B$404,$A14,'All Tasks'!$I$2:$I$404,"<>Complete",'All Tasks'!$L$2:$L$404,">"&(TODAY()-1)),"") | O14: =IF($H14=0,"",IF(OR($I14="Blocked",$I14="At Risk"),"R",IF(OR($I14="Complete",$I14="In Progress"),"G","Y"))) | P14: =HYPERLINK("#'Project Review'!C3","Open") -> Open | R14: =COUNTIFS('All Tasks'!$B$2:$B$404,$A14,'All Tasks'!$I$2:$I$404,"Complete") -> 0 | S14: =COUNTIFS('All Tasks'!$B$2:$B$404,$A14,'All Tasks'!$I$2:$I$404,"In Progress")+COUNTIFS('All Tasks'!$B$2:$B$404,$A14,'All Tasks'!$I$2:$I$404,"Waiting on Someone") -> 0 | T14: =SUMIFS('All Tasks'!$V$2:$V$404,'All Tasks'!$B$2:$B$404,$A14) -> 0
A15: P2-5 | B15: 2 – Top-of-Funnel Lead Gen | C15: Eliminate low-quality lead sources | D15: Dobelbower | E15: Chadwick | F15: Certain lead sources currently produce volume without corresponding conversion performance or franchisee quality. | G15: Short (90) | H15: =COUNTIF('All Tasks'!$B$2:$B$404,$A15) -> 0 | I15: =IF($H15=0,"No Tasks Yet",IF($L15>0,"Blocked",IF($K15>0,"At Risk",IF($R15=$H15,"Complete",IF($S15>0,"In Progress","Not Started"))))) -> No Tasks Yet | J15: =IF($H15=0,"",ROUND(SUMIFS('All Tasks'!$U$2:$U$404,'All Tasks'!$B$2:$B$404,$A15)/$H15,2)) | K15: =SUMIFS('All Tasks'!$R$2:$R$404,'All Tasks'!$B$2:$B$404,$A15) -> 0 | L15: =COUNTIFS('All Tasks'!$B$2:$B$404,$A15,'All Tasks'!$I$2:$I$404,"Blocked") -> 0 | M15: =IF($H15=0,"",IF($L15>0,$L15&" blocked / "&$K15&" overdue",IF($K15>0,$K15&" overdue task(s)",IF($T15>0,$T15&" roadblock(s) flagged","On track")))) | N15: =IFERROR(minifs('All Tasks'!$L$2:$L$404,'All Tasks'!$B$2:$B$404,$A15,'All Tasks'!$I$2:$I$404,"<>Complete",'All Tasks'!$L$2:$L$404,">"&(TODAY()-1)),"") | O15: =IF($H15=0,"",IF(OR($I15="Blocked",$I15="At Risk"),"R",IF(OR($I15="Complete",$I15="In Progress"),"G","Y"))) | P15: =HYPERLINK("#'Project Review'!C3","Open") -> Open | R15: =COUNTIFS('All Tasks'!$B$2:$B$404,$A15,'All Tasks'!$I$2:$I$404,"Complete") -> 0 | S15: =COUNTIFS('All Tasks'!$B$2:$B$404,$A15,'All Tasks'!$I$2:$I$404,"In Progress")+COUNTIFS('All Tasks'!$B$2:$B$404,$A15,'All Tasks'!$I$2:$I$404,"Waiting on Someone") -> 0 | T15: =SUMIFS('All Tasks'!$V$2:$V$404,'All Tasks'!$B$2:$B$404,$A15) -> 0
A16: P3-1 | B16: 3 – Broker Channel | C16: Assign MaryFran as broker channel owner | D16: Dobelbower | E16: MF. Anderson | F16: Broker relationships currently lack centralized ownership and consistent management across the portfolio. | G16: Short (90) | H16: =COUNTIF('All Tasks'!$B$2:$B$404,$A16) -> 3 | I16: =IF($H16=0,"No Tasks Yet",IF($L16>0,"Blocked",IF($K16>0,"At Risk",IF($R16=$H16,"Complete",IF($S16>0,"In Progress","Not Started"))))) -> Blocked | J16: =IF($H16=0,"",ROUND(SUMIFS('All Tasks'!$U$2:$U$404,'All Tasks'!$B$2:$B$404,$A16)/$H16,2)) -> 0.13 | K16: =SUMIFS('All Tasks'!$R$2:$R$404,'All Tasks'!$B$2:$B$404,$A16) -> 0 | L16: =COUNTIFS('All Tasks'!$B$2:$B$404,$A16,'All Tasks'!$I$2:$I$404,"Blocked") -> 1 | M16: =IF($H16=0,"",IF($L16>0,$L16&" blocked / "&$K16&" overdue",IF($K16>0,$K16&" overdue task(s)",IF($T16>0,$T16&" roadblock(s) flagged","On track")))) -> 1 blocked / 0 overdue | N16: =IFERROR(minifs('All Tasks'!$L$2:$L$404,'All Tasks'!$B$2:$B$404,$A16,'All Tasks'!$I$2:$I$404,"<>Complete",'All Tasks'!$L$2:$L$404,">"&(TODAY()-1)),"") | O16: =IF($H16=0,"",IF(OR($I16="Blocked",$I16="At Risk"),"R",IF(OR($I16="Complete",$I16="In Progress"),"G","Y"))) -> R | P16: =HYPERLINK("#'Project Review'!C3","Open") -> Open | R16: =COUNTIFS('All Tasks'!$B$2:$B$404,$A16,'All Tasks'!$I$2:$I$404,"Complete") -> 0 | S16: =COUNTIFS('All Tasks'!$B$2:$B$404,$A16,'All Tasks'!$I$2:$I$404,"In Progress")+COUNTIFS('All Tasks'!$B$2:$B$404,$A16,'All Tasks'!$I$2:$I$404,"Waiting on Someone") -> 1 | T16: =SUMIFS('All Tasks'!$V$2:$V$404,'All Tasks'!$B$2:$B$404,$A16) -> 1
... A19: P3-4 | B19: 3 – Broker Channel | C19: Enforce speed-to-lead SLAs | D19: Dobelbower | E19: MF. Anderson | F19: Response speed remains one of the largest drivers of broker lead conversion and candidate engagement. | G19: Short (90) | H19: =COUNTIF('All Tasks'!$B$2:$B$404,$A19) -> 1 | I19: =IF($H19=0,"No Tasks Yet",IF($L19>0,"Blocked",IF($K19>0,"At Risk",IF($R19=$H19,"Complete",IF($S19>0,"In Progress","Not Started"))))) -> In Progress | J19: =IF($H19=0,"",ROUND(SUMIFS('All Tasks'!$U$2:$U$404,'All Tasks'!$B$2:$B$404,$A19)/$H19,2)) -> 0.2 | K19: =SUMIFS('All Tasks'!$R$2:$R$404,'All Tasks'!$B$2:$B$404,$A19) -> 0 | L19: =COUNTIFS('All Tasks'!$B$2:$B$404,$A19,'All Tasks'!$I$2:$I$404,"Blocked") -> 0 | M19: =IF($H19=0,"",IF($L19>0,$L19&" blocked / "&$K19&" overdue",IF($K19>0,$K19&" overdue task(s)",IF($T19>0,$T19&" roadblock(s) flagged","On track")))) -> On track | N19: =IFERROR(minifs('All Tasks'!$L$2:$L$404,'All Tasks'!$B$2:$B$404,$A19,'All Tasks'!$I$2:$I$404,"<>Complete",'All Tasks'!$L$2:$L$404,">"&(TODAY()-1)),"") | O19: =IF($H19=0,"",IF(OR($I19="Blocked",$I19="At Risk"),"R",IF(OR($I19="Complete",$I19="In Progress"),"G","Y"))) -> G | P19: =HYPERLINK("#'Project Review'!C3","Open") -> Open | R19: =COUNTIFS('All Tasks'!$B$2:$B$404,$A19,'All Tasks'!$I$2:$I$404,"Complete") -> 0 | S19: =COUNTIFS('All Tasks'!$B$2:$B$404,$A19,'All Tasks'!$I$2:$I$404,"In Progress")+COUNTIFS('All Tasks'!$B$2:$B$404,$A19,'All Tasks'!$I$2:$I$404,"Waiting on Someone") -> 1 | T19: =SUMIFS('All Tasks'!$V$2:$V$404,'All Tasks'!$B$2:$B$404,$A19) -> 0
A20: P3-5 | B20: 3 – Broker Channel | C20: Segment Brokers into Tier 1/Tier 2/ Tier 3 | D20: Dobelbower | E20: MF. Anderson | F20: Not all broker relationships generate equal value, requiring prioritization based on production and lead quality. | H20: =COUNTIF('All Tasks'!$B$2:$B$404,$A20) -> 0 | I20: =IF($H20=0,"No Tasks Yet",IF($L20>0,"Blocked",IF($K20>0,"At Risk",IF($R20=$H20,"Complete",IF($S20>0,"In Progress","Not Started"))))) -> No Tasks Yet | J20: =IF($H20=0,"",ROUND(SUMIFS('All Tasks'!$U$2:$U$404,'All Tasks'!$B$2:$B$404,$A20)/$H20,2)) | K20: =SUMIFS('All Tasks'!$R$2:$R$404,'All Tasks'!$B$2:$B$404,$A20) -> 0 | L20: =COUNTIFS('All Tasks'!$B$2:$B$404,$A20,'All Tasks'!$I$2:$I$404,"Blocked") -> 0 | M20: =IF($H20=0,"",IF($L20>0,$L20&" blocked / "&$K20&" overdue",IF($K20>0,$K20&" overdue task(s)",IF($T20>0,$T20&" roadblock(s) flagged","On track")))) | N20: =IFERROR(minifs('All Tasks'!$L$2:$L$404,'All Tasks'!$B$2:$B$404,$A20,'All Tasks'!$I$2:$I$404,"<>Complete",'All Tasks'!$L$2:$L$404,">"&(TODAY()-1)),"") | O20: =IF($H20=0,"",IF(OR($I20="Blocked",$I20="At Risk"),"R",IF(OR($I20="Complete",$I20="In Progress"),"G","Y"))) | P20: =HYPERLINK("#'Project Review'!C3","Open") -> Open | R20: =COUNTIFS('All Tasks'!$B$2:$B$404,$A20,'All Tasks'!$I$2:$I$404,"Complete") -> 0 | S20: =COUNTIFS('All Tasks'!$B$2:$B$404,$A20,'All Tasks'!$I$2:$I$404,"In Progress")+COUNTIFS('All Tasks'!$B$2:$B$404,$A20,'All Tasks'!$I$2:$I$404,"Waiting on Someone") -> 0 | T20: =SUMIFS('All Tasks'!$V$2:$V$404,'All Tasks'!$B$2:$B$404,$A20) -> 0
A21: P3-6 | B21: 3 – Broker Channel | C21: Introduce performance-based lead weighting | D21: Dobelbower | E21: Mattingly/Ruhlig | F21: Lead distribution should reward execution and conversion performance while maintaining equitable opportunity across the team. | H21: =COUNTIF('All Tasks'!$B$2:$B$404,$A21) -> 0 | I21: =IF($H21=0,"No Tasks Yet",IF($L21>0,"Blocked",IF($K21>0,"At Risk",IF($R21=$H21,"Complete",IF($S21>0,"In Progress","Not Started"))))) -> No Tasks Yet | J21: =IF($H21=0,"",ROUND(SUMIFS('All Tasks'!$U$2:$U$404,'All Tasks'!$B$2:$B$404,$A21)/$H21,2)) | K21: =SUMIFS('All Tasks'!$R$2:$R$404,'All Tasks'!$B$2:$B$404,$A21) -> 0 | L21: =COUNTIFS('All Tasks'!$B$2:$B$404,$A21,'All Tasks'!$I$2:$I$404,"Blocked") -> 0 | M21: =IF($H21=0,"",IF($L21>0,$L21&" blocked / "&$K21&" overdue",IF($K21>0,$K21&" overdue task(s)",IF($T21>0,$T21&" roadblock(s) flagged","On track")))) | N21: =IFERROR(minifs('All Tasks'!$L$2:$L$404,'All Tasks'!$B$2:$B$404,$A21,'All Tasks'!$I$2:$I$404,"<>Complete",'All Tasks'!$L$2:$L$404,">"&(TODAY()-1)),"") | O21: =IF($H21=0,"",IF(OR($I21="Blocked",$I21="At Risk"),"R",IF(OR($I21="Complete",$I21="In Progress"),"G","Y"))) | P21: =HYPERLINK("#'Project Review'!C3","Open") -> Open | R21: =COUNTIFS('All Tasks'!$B$2:$B$404,$A21,'All Tasks'!$I$2:$I$404,"Complete") -> 0 | S21: =COUNTIFS('All Tasks'!$B$2:$B$404,$A21,'All Tasks'!$I$2:$I$404,"In Progress")+COUNTIFS('All Tasks'!$B$2:$B$404,$A21,'All Tasks'!$I$2:$I$404,"Waiting on Someone") -> 0 | T21: =SUMIFS('All Tasks'!$V$2:$V$404,'All Tasks'!$B$2:$B$404,$A21) -> 0
A22: P3-7 | B22: 3 – Broker Channel | C22: Build weekly broker channel performance reporting | D22: Dobelbower | E22: Mattingly/Ruhlig | F22: Broker performance visibility is currently limited, making it difficult to optimize relationships and conversion performance. | G22: Short (90) | H22: =COUNTIF('All Tasks'!$B$2:$B$404,$A22) -> 0 | I22: =IF($H22=0,"No Tasks Yet",IF($L22>0,"Blocked",IF($K22>0,"At Risk",IF($R22=$H22,"Complete",IF($S22>0,"In Progress","Not Started"))))) -> No Tasks Yet | J22: =IF($H22=0,"",ROUND(SUMIFS('All Tasks'!$U$2:$U$404,'All Tasks'!$B$2:$B$404,$A22)/$H22,2)) | K22: =SUMIFS('All Tasks'!$R$2:$R$404,'All Tasks'!$B$2:$B$404,$A22) -> 0 | L22: =COUNTIFS('All Tasks'!$B$2:$B$404,$A22,'All Tasks'!$I$2:$I$404,"Blocked") -> 0 | M22: =IF($H22=0,"",IF($L22>0,$L22&" blocked / "&$K22&" overdue",IF($K22>0,$K22&" overdue task(s)",IF($T22>0,$T22&" roadblock(s) flagged","On track")))) | N22: =IFERROR(minifs('All Tasks'!$L$2:$L$404,'All Tasks'!$B$2:$B$404,$A22,'All Tasks'!$I$2:$I$404,"<>Complete",'All Tasks'!$L$2:$L$404,">"&(TODAY()-1)),"") | O22: =IF($H22=0,"",IF(OR($I22="Blocked",$I22="At Risk"),"R",IF(OR($I22="Complete",$I22="In Progress"),"G","Y"))) | P22: =HYPERLINK("#'Project Review'!C3","Open") -> Open | R22: =COUNTIFS('All Tasks'!$B$2:$B$404,$A22,'All Tasks'!$I$2:$I$404,"Complete") -> 0 | S22: =COUNTIFS('All Tasks'!$B$2:$B$404,$A22,'All Tasks'!$I$2:$I$404,"In Progress")+COUNTIFS('All Tasks'!$B$2:$B$404,$A22,'All Tasks'!$I$2:$I$404,"Waiting on Someone") -> 0 | T22: =SUMIFS('All Tasks'!$V$2:$V$404,'All Tasks'!$B$2:$B$404,$A22) -> 0
A23: P4-1 | B23: 4 – Portfolio Brand Strategy | C23: Position The Seals as a low-cost, high-whitespace growth brand | D23: Dobelbower | E23: Anderson/Chadwick | F23: The Seals presents an opportunity for accelerated unit growth due to low investment requirements, recurring revenue characteristics, and significant whitespace availability. | G23: Short (90) | H23: =COUNTIF('All Tasks'!$B$2:$B$404,$A23) -> 0 | I23: =IF($H23=0,"No Tasks Yet",IF($L23>0,"Blocked",IF($K23>0,"At Risk",IF($R23=$H23,"Complete",IF($S23>0,"In Progress","Not Started"))))) -> No Tasks Yet | J23: =IF($H23=0,"",ROUND(SUMIFS('All Tasks'!$U$2:$U$404,'All Tasks'!$B$2:$B$404,$A23)/$H23,2)) | K23: =SUMIFS('All Tasks'!$R$2:$R$404,'All Tasks'!$B$2:$B$404,$A23) -> 0 | L23: =COUNTIFS('All Tasks'!$B$2:$B$404,$A23,'All Tasks'!$I$2:$I$404,"Blocked") -> 0 | M23: =IF($H23=0,"",IF($L23>0,$L23&" blocked / "&$K23&" overdue",IF($K23>0,$K23&" overdue task(s)",IF($T23>0,$T23&" roadblock(s) flagged","On track")))) | N23: =IFERROR(minifs('All Tasks'!$L$2:$L$404,'All Tasks'!$B$2:$B$404,$A23,'All Tasks'!$I$2:$I$404,"<>Complete",'All Tasks'!$L$2:$L$404,">"&(TODAY()-1)),"") | O23: =IF($H23=0,"",IF(OR($I23="Blocked",$I23="At Risk"),"R",IF(OR($I23="Complete",$I23="In Progress"),"G","Y"))) | P23: =HYPERLINK("#'Project Review'!C3","Open") -> Open | R23: =COUNTIFS('All Tasks'!$B$2:$B$404,$A23,'All Tasks'!$I$2:$I$404,"Complete") -> 0 | S23: =COUNTIFS('All Tasks'!$B$2:$B$404,$A23,'All Tasks'!$I$2:$I$404,"In Progress")+COUNTIFS('All Tasks'!$B$2:$B$404,$A23,'All Tasks'!$I$2:$I$404,"Waiting on Someone") -> 0 | T23: =SUMIFS('All Tasks'!$V$2:$V$404,'All Tasks'!$B$2:$B$404,$A23) -> 0
A24: P4-2 | B24: 4 – Portfolio Brand Strategy | C24: Position 1-Tom as a flagship growth brand | D24: Dobelbower | E24: Anderson/Chadwick | F24: 1-Tom possesses strong branding, broad market appeal, and favorable long-term scalability characteristics. | G24: Short (90) | H24: =COUNTIF('All Tasks'!$B$2:$B$404,$A24) -> 0 | I24: =IF($H24=0,"No Tasks Yet",IF($L24>0,"Blocked",IF($K24>0,"At Risk",IF($R24=$H24,"Complete",IF($S24>0,"In Progress","Not Started"))))) -> No Tasks Yet | J24: =IF($H24=0,"",ROUND(SUMIFS('All Tasks'!$U$2:$U$404,'All Tasks'!$B$2:$B$404,$A24)/$H24,2)) | K24: =SUMIFS('All Tasks'!$R$2:$R$404,'All Tasks'!$B$2:$B$404,$A24) -> 0 | L24: =COUNTIFS('All Tasks'!$B$2:$B$404,$A24,'All Tasks'!$I$2:$I$404,"Blocked") -> 0 | M24: =IF($H24=0,"",IF($L24>0,$L24&" blocked / "&$K24&" overdue",IF($K24>0,$K24&" overdue task(s)",IF($T24>0,$T24&" roadblock(s) flagged","On track")))) | N24: =IFERROR(minifs('All Tasks'!$L$2:$L$404,'All Tasks'!$B$2:$B$404,$A24,'All Tasks'!$I$2:$I$404,"<>Complete",'All Tasks'!$L$2:$L$404,">"&(TODAY()-1)),"") | O24: =IF($H24=0,"",IF(OR($I24="Blocked",$I24="At Risk"),"R",IF(OR($I24="Complete",$I24="In Progress"),"G","Y"))) | P24: =HYPERLINK("#'Project Review'!C3","Open") -> Open | R24: =COUNTIFS('All Tasks'!$B$2:$B$404,$A24,'All Tasks'!$I$2:$I$404,"Complete") -> 0 | S24: =COUNTIFS('All Tasks'!$B$2:$B$404,$A24,'All Tasks'!$I$2:$I$404,"In Progress")+COUNTIFS('All Tasks'!$B$2:$B$404,$A24,'All Tasks'!$I$2:$I$404,"Waiting on Someone") -> 0 | T24: =SUMIFS('All Tasks'!$V$2:$V$404,'All Tasks'!$B$2:$B$404,$A24) -> 0
A25: P4-3 | B25: 4 – Portfolio Brand Strategy | C25: Align Kitchen Guard growth strategy with Strategic Accounts initiatives | D25: Dobelbower | E25: Hatcher | F25: Kitchen Guard’s compliance-driven recurring revenue model aligns well with enterprise and Strategic Account positioning opportunities. | G25: Long (270) | H25: =COUNTIF('All Tasks'!$B$2:$B$404,$A25) -> 0 | I25: =IF($H25=0,"No Tasks Yet",IF($L25>0,"Blocked",IF($K25>0,"At Risk",IF($R25=$H25,"Complete",IF($S25>0,"In Progress","Not Started"))))) -> No Tasks Yet | J25: =IF($H25=0,"",ROUND(SUMIFS('All Tasks'!$U$2:$U$404,'All Tasks'!$B$2:$B$404,$A25)/$H25,2)) | K25: =SUMIFS('All Tasks'!$R$2:$R$404,'All Tasks'!$B$2:$B$404,$A25) -> 0 | L25: =COUNTIFS('All Tasks'!$B$2:$B$404,$A25,'All Tasks'!$I$2:$I$404,"Blocked") -> 0 | M25: =IF($H25=0,"",IF($L25>0,$L25&" blocked / "&$K25&" overdue",IF($K25>0,$K25&" overdue task(s)",IF($T25>0,$T25&" roadblock(s) flagged","On track")))) | N25: =IFERROR(minifs('All Tasks'!$L$2:$L$404,'All Tasks'!$B$2:$B$404,$A25,'All Tasks'!$I$2:$I$404,"<>Complete",'All Tasks'!$L$2:$L$404,">"&(TODAY()-1)),"") | O25: =IF($H25=0,"",IF(OR($I25="Blocked",$I25="At Risk"),"R",IF(OR($I25="Complete",$I25="In Progress"),"G","Y"))) | P25: =HYPERLINK("#'Project Review'!C3","Open") -> Open | R25: =COUNTIFS('All Tasks'!$B$2:$B$404,$A25,'All Tasks'!$I$2:$I$404,"Complete") -> 0 | S25: =COUNTIFS('All Tasks'!$B$2:$B$404,$A25,'All Tasks'!$I$2:$I$404,"In Progress")+COUNTIFS('All Tasks'!$B$2:$B$404,$A25,'All Tasks'!$I$2:$I$404,"Waiting on Someone") -> 0 | T25: =SUMIFS('All Tasks'!$V$2:$V$404,'All Tasks'!$B$2:$B$404,$A25) -> 0
A26: P4-4 | B26: 4 – Portfolio Brand Strategy | C26: Reposition Prism as a multi-service platform opportunity | D26: Dobelbower | E26: Anderson/Chadwick | F26: Prism’s multi-service structure creates an opportunity to increase average deal size and long-term franchisee value. | G26: Short (90) | H26: =COUNTIF('All Tasks'!$B$2:$B$404,$A26) -> 0 | I26: =IF($H26=0,"No Tasks Yet",IF($L26>0,"Blocked",IF($K26>0,"At Risk",IF($R26=$H26,"Complete",IF($S26>0,"In Progress","Not Started"))))) -> No Tasks Yet | J26: =IF($H26=0,"",ROUND(SUMIFS('All Tasks'!$U$2:$U$404,'All Tasks'!$B$2:$B$404,$A26)/$H26,2)) | K26: =SUMIFS('All Tasks'!$R$2:$R$404,'All Tasks'!$B$2:$B$404,$A26) -> 0 | L26: =COUNTIFS('All Tasks'!$B$2:$B$404,$A26,'All Tasks'!$I$2:$I$404,"Blocked") -> 0 | M26: =IF($H26=0,"",IF($L26>0,$L26&" blocked / "&$K26&" overdue",IF($K26>0,$K26&" overdue task(s)",IF($T26>0,$T26&" roadblock(s) flagged","On track")))) | N26: =IFERROR(minifs('All Tasks'!$L$2:$L$404,'All Tasks'!$B$2:$B$404,$A26,'All Tasks'!$I$2:$I$404,"<>Complete",'All Tasks'!$L$2:$L$404,">"&(TODAY()-1)),"") | O26: =IF($H26=0,"",IF(OR($I26="Blocked",$I26="At Risk"),"R",IF(OR($I26="Complete",$I26="In Progress"),"G","Y"))) | P26: =HYPERLINK("#'Project Review'!C3","Open") -> Open | R26: =COUNTIFS('All Tasks'!$B$2:$B$404,$A26,'All Tasks'!$I$2:$I$404,"Complete") -> 0 | S26: =COUNTIFS('All Tasks'!$B$2:$B$404,$A26,'All Tasks'!$I$2:$I$404,"In Progress")+COUNTIFS('All Tasks'!$B$2:$B$404,$A26,'All Tasks'!$I$2:$I$404,"Waiting on Someone") -> 0 | T26: =SUMIFS('All Tasks'!$V$2:$V$404,'All Tasks'!$B$2:$B$404,$A26) -> 0
A27: P4-5 | B27: 4 – Portfolio Brand Strategy | C27: Maintain stable, quality-focused growth for U.S. Lawns | D27: Dobelbower | E27: Steeves | F27: U.S. Lawns serves as a mature and stable portfolio brand with strong recognition and operational consistency. | G27: Short (90) | H27: =COUNTIF('All Tasks'!$B$2:$B$404,$A27) -> 0 | I27: =IF($H27=0,"No Tasks Yet",IF($L27>0,"Blocked",IF($K27>0,"At Risk",IF($R27=$H27,"Complete",IF($S27>0,"In Progress","Not Started"))))) -> No Tasks Yet | J27: =IF($H27=0,"",ROUND(SUMIFS('All Tasks'!$U$2:$U$404,'All Tasks'!$B$2:$B$404,$A27)/$H27,2)) | K27: =SUMIFS('All Tasks'!$R$2:$R$404,'All Tasks'!$B$2:$B$404,$A27) -> 0 | L27: =COUNTIFS('All Tasks'!$B$2:$B$404,$A27,'All Tasks'!$I$2:$I$404,"Blocked") -> 0 | M27: =IF($H27=0,"",IF($L27>0,$L27&" blocked / "&$K27&" overdue",IF($K27>0,$K27&" overdue task(s)",IF($T27>0,$T27&" roadblock(s) flagged","On track")))) | N27: =IFERROR(minifs('All Tasks'!$L$2:$L$404,'All Tasks'!$B$2:$B$404,$A27,'All Tasks'!$I$2:$I$404,"<>Complete",'All Tasks'!$L$2:$L$404,">"&(TODAY()-1)),"") | O27: =IF($H27=0,"",IF(OR($I27="Blocked",$I27="At Risk"),"R",IF(OR($I27="Complete",$I27="In Progress"),"G","Y"))) | P27: =HYPERLINK("#'Project Review'!C3","Open") -> Open | R27: =COUNTIFS('All Tasks'!$B$2:$B$404,$A27,'All Tasks'!$I$2:$I$404,"Complete") -> 0 | S27: =COUNTIFS('All Tasks'!$B$2:$B$404,$A27,'All Tasks'!$I$2:$I$404,"In Progress")+COUNTIFS('All Tasks'!$B$2:$B$404,$A27,'All Tasks'!$I$2:$I$404,"Waiting on Someone") -> 0 | T27: =SUMIFS('All Tasks'!$V$2:$V$404,'All Tasks'!$B$2:$B$404,$A27) -> 0
A28: P4-6 | B28: 4 – Portfolio Brand Strategy | C28: Utilize Clintar as a selective strategic growth vehicle | D28: Dobelbower | E28: Motyka | F28: Clintar should be positioned toward experienced operators and strategic opportunities rather than high-volume franchise sales efforts. | G28: Mid (180) | H28: =COUNTIF('All Tasks'!$B$2:$B$404,$A28) -> 1 | I28: =IF($H28=0,"No Tasks Yet",IF($L28>0,"Blocked",IF($K28>0,"At Risk",IF($R28=$H28,"Complete",IF($S28>0,"In Progress","Not Started"))))) -> In Progress | J28: =IF($H28=0,"",ROUND(SUMIFS('All Tasks'!$U$2:$U$404,'All Tasks'!$B$2:$B$404,$A28)/$H28,2)) -> 0.3 | K28: =SUMIFS('All Tasks'!$R$2:$R$404,'All Tasks'!$B$2:$B$404,$A28) -> 0 | L28: =COUNTIFS('All Tasks'!$B$2:$B$404,$A28,'All Tasks'!$I$2:$I$404,"Blocked") -> 0 | M28: =IF($H28=0,"",IF($L28>0,$L28&" blocked / "&$K28&" overdue",IF($K28>0,$K28&" overdue task(s)",IF($T28>0,$T28&" roadblock(s) flagged","On track")))) -> On track | N28: =IFERROR(minifs('All Tasks'!$L$2:$L$404,'All Tasks'!$B$2:$B$404,$A28,'All Tasks'!$I$2:$I$404,"<>Complete",'All Tasks'!$L$2:$L$404,">"&(TODAY()-1)),"") | O28: =IF($H28=0,"",IF(OR($I28="Blocked",$I28="At Risk"),"R",IF(OR($I28="Complete",$I28="In Progress"),"G","Y"))) -> G | P28: =HYPERLINK("#'Project Review'!C3","Open") -> Open | R28: =COUNTIFS('All Tasks'!$B$2:$B$404,$A28,'All Tasks'!$I$2:$I$404,"Complete") -> 0 | S28: =COUNTIFS('All Tasks'!$B$2:$B$404,$A28,'All Tasks'!$I$2:$I$404,"In Progress")+COUNTIFS('All Tasks'!$B$2:$B$404,$A28,'All Tasks'!$I$2:$I$404,"Waiting on Someone") -> 1 | T28: =SUMIFS('All Tasks'!$V$2:$V$404,'All Tasks'!$B$2:$B$404,$A28) -> 0
A29: P4-7 | B29: 4 – Portfolio Brand Strategy | C29: Rebuild validation and franchisee confidence within MilliCare | D29: Dobelbower | E29: Griffith/Weaver | F29: Long-term MilliCare growth requires improvement in franchisee sentiment, validation consistency, and economic confidence. | G29: Long (270) | H29: =COUNTIF('All Tasks'!$B$2:$B$404,$A29) -> 1 | I29: =IF($H29=0,"No Tasks Yet",IF($L29>0,"Blocked",IF($K29>0,"At Risk",IF($R29=$H29,"Complete",IF($S29>0,"In Progress","Not Started"))))) -> In Progress | J29: =IF($H29=0,"",ROUND(SUMIFS('All Tasks'!$U$2:$U$404,'All Tasks'!$B$2:$B$404,$A29)/$H29,2)) -> 0.2 | K29: =SUMIFS('All Tasks'!$R$2:$R$404,'All Tasks'!$B$2:$B$404,$A29) -> 0 | L29: =COUNTIFS('All Tasks'!$B$2:$B$404,$A29,'All Tasks'!$I$2:$I$404,"Blocked") -> 0 | M29: =IF($H29=0,"",IF($L29>0,$L29&" blocked / "&$K29&" overdue",IF($K29>0,$K29&" overdue task(s)",IF($T29>0,$T29&" roadblock(s) flagged","On track")))) -> 1 roadblock(s) flagged | N29: =IFERROR(minifs('All Tasks'!$L$2:$L$404,'All Tasks'!$B$2:$B$404,$A29,'All Tasks'!$I$2:$I$404,"<>Complete",'All Tasks'!$L$2:$L$404,">"&(TODAY()-1)),"") | O29: =IF($H29=0,"",IF(OR($I29="Blocked",$I29="At Risk"),"R",IF(OR($I29="Complete",$I29="In Progress"),"G","Y"))) -> G | P29: =HYPERLINK("#'Project Review'!C3","Open") -> Open | R29: =COUNTIFS('All Tasks'!$B$2:$B$404,$A29,'All Tasks'!$I$2:$I$404,"Complete") -> 0 | S29: =COUNTIFS('All Tasks'!$B$2:$B$404,$A29,'All Tasks'!$I$2:$I$404,"In Progress")+COUNTIFS('All Tasks'!$B$2:$B$404,$A29,'All Tasks'!$I$2:$I$404,"Waiting on Someone") -> 1 | T29: =SUMIFS('All Tasks'!$V$2:$V$404,'All Tasks'!$B$2:$B$404,$A29) -> 1
A30: P5-1 | B30: 5 – Operational Infrastructure | C30: Replace shared territory check inboxes with CRM routing | D30: Dobelbower | E30: Mattingly | F30: Shared territory check workflows currently create operational inefficiencies and inconsistent response times. | G30: Short (90) | H30: =COUNTIF('All Tasks'!$B$2:$B$404,$A30) -> 0 | I30: =IF($H30=0,"No Tasks Yet",IF($L30>0,"Blocked",IF($K30>0,"At Risk",IF($R30=$H30,"Complete",IF($S30>0,"In Progress","Not Started"))))) -> No Tasks Yet | J30: =IF($H30=0,"",ROUND(SUMIFS('All Tasks'!$U$2:$U$404,'All Tasks'!$B$2:$B$404,$A30)/$H30,2)) | K30: =SUMIFS('All Tasks'!$R$2:$R$404,'All Tasks'!$B$2:$B$404,$A30) -> 0 | L30: =COUNTIFS('All Tasks'!$B$2:$B$404,$A30,'All Tasks'!$I$2:$I$404,"Blocked") -> 0 | M30: =IF($H30=0,"",IF($L30>0,$L30&" blocked / "&$K30&" overdue",IF($K30>0,$K30&" overdue task(s)",IF($T30>0,$T30&" roadblock(s) flagged","On track")))) | N30: =IFERROR(minifs('All Tasks'!$L$2:$L$404,'All Tasks'!$B$2:$B$404,$A30,'All Tasks'!$I$2:$I$404,"<>Complete",'All Tasks'!$L$2:$L$404,">"&(TODAY()-1)),"") | O30: =IF($H30=0,"",IF(OR($I30="Blocked",$I30="At Risk"),"R",IF(OR($I30="Complete",$I30="In Progress"),"G","Y"))) | P30: =HYPERLINK("#'Project Review'!C3","Open") -> Open | R30: =COUNTIFS('All Tasks'!$B$2:$B$404,$A30,'All Tasks'!$I$2:$I$404,"Complete") -> 0 | S30: =COUNTIFS('All Tasks'!$B$2:$B$404,$A30,'All Tasks'!$I$2:$I$404,"In Progress")+COUNTIFS('All Tasks'!$B$2:$B$404,$A30,'All Tasks'!$I$2:$I$404,"Waiting on Someone") -> 0 | T30: =SUMIFS('All Tasks'!$V$2:$V$404,'All Tasks'!$B$2:$B$404,$A30) -> 0
A31: P5-2 | B31: 5 – Operational Infrastructure | C31: Implement territory check response SLA | D31: Dobelbower | E31: MF. Anderson | F31: Fast and consistent response times are critical to broker experience and franchise sales momentum. | G31: Short (90) | H31: =COUNTIF('All Tasks'!$B$2:$B$404,$A31) -> 0 | I31: =IF($H31=0,"No Tasks Yet",IF($L31>0,"Blocked",IF($K31>0,"At Risk",IF($R31=$H31,"Complete",IF($S31>0,"In Progress","Not Started"))))) -> No Tasks Yet | J31: =IF($H31=0,"",ROUND(SUMIFS('All Tasks'!$U$2:$U$404,'All Tasks'!$B$2:$B$404,$A31)/$H31,2)) | K31: =SUMIFS('All Tasks'!$R$2:$R$404,'All Tasks'!$B$2:$B$404,$A31) -> 0 | L31: =COUNTIFS('All Tasks'!$B$2:$B$404,$A31,'All Tasks'!$I$2:$I$404,"Blocked") -> 0 | M31: =IF($H31=0,"",IF($L31>0,$L31&" blocked / "&$K31&" overdue",IF($K31>0,$K31&" overdue task(s)",IF($T31>0,$T31&" roadblock(s) flagged","On track")))) | N31: =IFERROR(minifs('All Tasks'!$L$2:$L$404,'All Tasks'!$B$2:$B$404,$A31,'All Tasks'!$I$2:$I$404,"<>Complete",'All Tasks'!$L$2:$L$404,">"&(TODAY()-1)),"") | O31: =IF($H31=0,"",IF(OR($I31="Blocked",$I31="At Risk"),"R",IF(OR($I31="Complete",$I31="In Progress"),"G","Y"))) | P31: =HYPERLINK("#'Project Review'!C3","Open") -> Open | R31: =COUNTIFS('All Tasks'!$B$2:$B$404,$A31,'All Tasks'!$I$2:$I$404,"Complete") -> 0 | S31: =COUNTIFS('All Tasks'!$B$2:$B$404,$A31,'All Tasks'!$I$2:$I$404,"In Progress")+COUNTIFS('All Tasks'!$B$2:$B$404,$A31,'All Tasks'!$I$2:$I$404,"Waiting on Someone") -> 0 | T31: =SUMIFS('All Tasks'!$V$2:$V$404,'All Tasks'!$B$2:$B$404,$A31) -> 0
A32: P5-3 | B32: 5 – Operational Infrastructure | C32: Standardize lead assignment and routing logic | D32: Dobelbower | E32: Mattingly | F32: Lead routing should prioritize transparency, accountability, and operational consistency across brands. | G32: Short (90) | H32: =COUNTIF('All Tasks'!$B$2:$B$404,$A32) -> 0 | I32: =IF($H32=0,"No Tasks Yet",IF($L32>0,"Blocked",IF($K32>0,"At Risk",IF($R32=$H32,"Complete",IF($S32>0,"In Progress","Not Started"))))) -> No Tasks Yet | J32: =IF($H32=0,"",ROUND(SUMIFS('All Tasks'!$U$2:$U$404,'All Tasks'!$B$2:$B$404,$A32)/$H32,2)) | K32: =SUMIFS('All Tasks'!$R$2:$R$404,'All Tasks'!$B$2:$B$404,$A32) -> 0 | L32: =COUNTIFS('All Tasks'!$B$2:$B$404,$A32,'All Tasks'!$I$2:$I$404,"Blocked") -> 0 | M32: =IF($H32=0,"",IF($L32>0,$L32&" blocked / "&$K32&" overdue",IF($K32>0,$K32&" overdue task(s)",IF($T32>0,$T32&" roadblock(s) flagged","On track")))) | N32: =IFERROR(minifs('All Tasks'!$L$2:$L$404,'All Tasks'!$B$2:$B$404,$A32,'All Tasks'!$I$2:$I$404,"<>Complete",'All Tasks'!$L$2:$L$404,">"&(TODAY()-1)),"") | O32: =IF($H32=0,"",IF(OR($I32="Blocked",$I32="At Risk"),"R",IF(OR($I32="Complete",$I32="In Progress"),"G","Y"))) | P32: =HYPERLINK("#'Project Review'!C3","Open") -> Open | R32: =COUNTIFS('All Tasks'!$B$2:$B$404,$A32,'All Tasks'!$I$2:$I$404,"Complete") -> 0 | S32: =COUNTIFS('All Tasks'!$B$2:$B$404,$A32,'All Tasks'!$I$2:$I$404,"In Progress")+COUNTIFS('All Tasks'!$B$2:$B$404,$A32,'All Tasks'!$I$2:$I$404,"Waiting on Someone") -> 0 | T32: =SUMIFS('All Tasks'!$V$2:$V$404,'All Tasks'!$B$2:$B$404,$A32) -> 0
A33: P5-4 | B33: 5 – Operational Infrastructure | C33: Build centralized KPI dashboard and reporting visibility | D33: Dobelbower | E33: Mattingly/Ruhlig | F33: Leadership currently lacks consistent portfolio-wide visibility into funnel health and conversion trends. | G33: Mid (180) | H33: =COUNTIF('All Tasks'!$B$2:$B$404,$A33) -> 1 | I33: =IF($H33=0,"No Tasks Yet",IF($L33>0,"Blocked",IF($K33>0,"At Risk",IF($R33=$H33,"Complete",IF($S33>0,"In Progress","Not Started"))))) -> Not Started | J33: =IF($H33=0,"",ROUND(SUMIFS('All Tasks'!$U$2:$U$404,'All Tasks'!$B$2:$B$404,$A33)/$H33,2)) -> 0 | K33: =SUMIFS('All Tasks'!$R$2:$R$404,'All Tasks'!$B$2:$B$404,$A33) -> 0 | L33: =COUNTIFS('All Tasks'!$B$2:$B$404,$A33,'All Tasks'!$I$2:$I$404,"Blocked") -> 0 | M33: =IF($H33=0,"",IF($L33>0,$L33&" blocked / "&$K33&" overdue",IF($K33>0,$K33&" overdue task(s)",IF($T33>0,$T33&" roadblock(s) flagged","On track")))) -> On track | N33: =IFERROR(minifs('All Tasks'!$L$2:$L$404,'All Tasks'!$B$2:$B$404,$A33,'All Tasks'!$I$2:$I$404,"<>Complete",'All Tasks'!$L$2:$L$404,">"&(TODAY()-1)),"") | O33: =IF($H33=0,"",IF(OR($I33="Blocked",$I33="At Risk"),"R",IF(OR($I33="Complete",$I33="In Progress"),"G","Y"))) -> Y | P33: =HYPERLINK("#'Project Review'!C3","Open") -> Open | R33: =COUNTIFS('All Tasks'!$B$2:$B$404,$A33,'All Tasks'!$I$2:$I$404,"Complete") -> 0 | S33: =COUNTIFS('All Tasks'!$B$2:$B$404,$A33,'All Tasks'!$I$2:$I$404,"In Progress")+COUNTIFS('All Tasks'!$B$2:$B$404,$A33,'All Tasks'!$I$2:$I$404,"Waiting on Someone") -> 0 | T33: =SUMIFS('All Tasks'!$V$2:$V$404,'All Tasks'!$B$2:$B$404,$A33) -> 0
... A47: P8-4 | B47: 8 – Talent Evaluation | C47: Build a long-term talent development strategy focused on coaching, succession planning, and cross-brand collaboration. | D47: N/A | E47: Dobelbower | F47: Investing in team development will create a more scalable and sustainable franchise development organization over time. | G47: Short (90) | H47: =COUNTIF('All Tasks'!$B$2:$B$404,$A47) -> 0 | I47: =IF($H47=0,"No Tasks Yet",IF($L47>0,"Blocked",IF($K47>0,"At Risk",IF($R47=$H47,"Complete",IF($S47>0,"In Progress","Not Started"))))) -> No Tasks Yet | J47: =IF($H47=0,"",ROUND(SUMIFS('All Tasks'!$U$2:$U$404,'All Tasks'!$B$2:$B$404,$A47)/$H47,2)) | K47: =SUMIFS('All Tasks'!$R$2:$R$404,'All Tasks'!$B$2:$B$404,$A47) -> 0 | L47: =COUNTIFS('All Tasks'!$B$2:$B$404,$A47,'All Tasks'!$I$2:$I$404,"Blocked") -> 0 | M47: =IF($H47=0,"",IF($L47>0,$L47&" blocked / "&$K47&" overdue",IF($K47>0,$K47&" overdue task(s)",IF($T47>0,$T47&" roadblock(s) flagged","On track")))) | N47: =IFERROR(minifs('All Tasks'!$L$2:$L$404,'All Tasks'!$B$2:$B$404,$A47,'All Tasks'!$I$2:$I$404,"<>Complete",'All Tasks'!$L$2:$L$404,">"&(TODAY()-1)),"") | O47: =IF($H47=0,"",IF(OR($I47="Blocked",$I47="At Risk"),"R",IF(OR($I47="Complete",$I47="In Progress"),"G","Y"))) | P47: =HYPERLINK("#'Project Review'!C3","Open") -> Open | R47: =COUNTIFS('All Tasks'!$B$2:$B$404,$A47,'All Tasks'!$I$2:$I$404,"Complete") -> 0 | S47: =COUNTIFS('All Tasks'!$B$2:$B$404,$A47,'All Tasks'!$I$2:$I$404,"In Progress")+COUNTIFS('All Tasks'!$B$2:$B$404,$A47,'All Tasks'!$I$2:$I$404,"Waiting on Someone") -> 0 | T47: =SUMIFS('All Tasks'!$V$2:$V$404,'All Tasks'!$B$2:$B$404,$A47) -> 0

Sheet Project Review
B1: Project Review
B2: Pick a Project ID — the header and the full task list (everyone working on that tactic) populate automatically.
B3: Select Project ID > | C3: P1-1
B5: Project / Tactic Name | C5: =IFERROR(VLOOKUP($C$3,Projects!$A:$C,3,FALSE()),"") -> Implement standardized Mutual Evaluation Process (MEP) across all brands
B6: Focus Area | C6: =IFERROR(VLOOKUP($C$3,Projects!$A:$B,2,FALSE()),"") -> 1 – Unified Development System
B7: Executive Owner | C7: =IFERROR(VLOOKUP($C$3,Projects!$A:$D,4,FALSE()),"") -> Dobelbower
B8: Lead Owner | C8: =IFERROR(VLOOKUP($C$3,Projects!$A:$E,5,FALSE()),"") -> Developers
B9: Timing | C9: =IFERROR(VLOOKUP($C$3,Lists!$A:$F,6,FALSE()),"") -> Short (90)
B10: Strategic Goal (why) | C10: =IFERROR(VLOOKUP($C$3,Lists!$A:$E,5,FALSE()),"") -> Current franchise development processes vary significantly by brand, creating inconsistent candidate experiences and reducing scalability.
B11: Current Status | C11: =IFERROR(VLOOKUP($C$3,Projects!$A:$I,9,FALSE()),"") -> In Progress
B12: % Complete | C12: =IFERROR(VLOOKUP($C$3,Projects!$A:$J,10,FALSE()),"") -> 0.5
B13: Overdue Tasks | C13: =IFERROR(VLOOKUP($C$3,Projects!$A:$K,11,FALSE()),"") -> 0
B14: Blocked Tasks | C14: =IFERROR(VLOOKUP($C$3,Projects!$A:$L,12,FALSE()),"") -> 0
B15: Key Risks | C15: =IFERROR(VLOOKUP($C$3,Projects!$A:$M,13,FALSE()),"") -> On track
B16: Next Milestone | C16: =IFERROR(VLOOKUP($C$3,Projects!$A:$N,14,FALSE()),"")
B18: Tasks for this Project (everyone working on the tactic)
B19: Task ID | C19: Assigned To | D19: Task Description | E19: Role | F19: Priority | G19: Status | H19: % Comp | I19: Start | J19: Due | K19: Days Left | L19: Roadblock | M19: Last Update | N19: Next Step
A20: =IFERROR(aggregate(15,6,ROW('All Tasks'!$B$2:$B$404)/('All Tasks'!$B$2:$B$404=$C$3),ROWS($A$20:$A20)),"") | B20: =IF($A20="","",INDEX('All Tasks'!$A:$A,$A20)) | C20: =IF($A20="","",INDEX('All Tasks'!$E:$E,$A20)) | D20: =IF($A20="","",INDEX('All Tasks'!$G:$G,$A20)) | E20: =IF($A20="","",INDEX('All Tasks'!$F:$F,$A20)) | F20: =IF($A20="","",INDEX('All Tasks'!$H:$H,$A20)) | G20: =IF($A20="","",INDEX('All Tasks'!$I:$I,$A20)) | H20: =IF($A20="","",INDEX('All Tasks'!$J:$J,$A20)) | I20: =IF($A20="","",INDEX('All Tasks'!$K:$K,$A20)) | J20: =IF($A20="","",INDEX('All Tasks'!$L:$L,$A20)) | K20: =IF($A20="","",INDEX('All Tasks'!$T:$T,$A20)) | L20: =IF($A20="","",INDEX('All Tasks'!$N:$N,$A20)) | M20: =IF($A20="","",INDEX('All Tasks'!$O:$O,$A20)) | N20: =IF($A20="","",INDEX('All Tasks'!$P:$P,$A20))
A21: =IFERROR(aggregate(15,6,ROW('All Tasks'!$B$2:$B$404)/('All Tasks'!$B$2:$B$404=$C$3),ROWS($A$20:$A21)),"") | B21: =IF($A21="","",INDEX('All Tasks'!$A:$A,$A21)) | C21: =IF($A21="","",INDEX('All Tasks'!$E:$E,$A21)) | D21: =IF($A21="","",INDEX('All Tasks'!$G:$G,$A21)) | E21: =IF($A21="","",INDEX('All Tasks'!$F:$F,$A21)) | F21: =IF($A21="","",INDEX('All Tasks'!$H:$H,$A21)) | G21: =IF($A21="","",INDEX('All Tasks'!$I:$I,$A21)) | H21: =IF($A21="","",INDEX('All Tasks'!$J:$J,$A21)) | I21: =IF($A21="","",INDEX('All Tasks'!$K:$K,$A21)) | J21: =IF($A21="","",INDEX('All Tasks'!$L:$L,$A21)) | K21: =IF($A21="","",INDEX('All Tasks'!$T:$T,$A21)) | L21: =IF($A21="","",INDEX('All Tasks'!$N:$N,$A21)) | M21: =IF($A21="","",INDEX('All Tasks'!$O:$O,$A21)) | N21: =IF($A21="","",INDEX('All Tasks'!$P:$P,$A21))
A22: =IFERROR(aggregate(15,6,ROW('All Tasks'!$B$2:$B$404)/('All Tasks'!$B$2:$B$404=$C$3),ROWS($A$20:$A22)),"") | B22: =IF($A22="","",INDEX('All Tasks'!$A:$A,$A22)) | C22: =IF($A22="","",INDEX('All Tasks'!$E:$E,$A22)) | D22: =IF($A22="","",INDEX('All Tasks'!$G:$G,$A22)) | E22: =IF($A22="","",INDEX('All Tasks'!$F:$F,$A22)) | F22: =IF($A22="","",INDEX('All Tasks'!$H:$H,$A22)) | G22: =IF($A22="","",INDEX('All Tasks'!$I:$I,$A22)) | H22: =IF($A22="","",INDEX('All Tasks'!$J:$J,$A22)) | I22: =IF($A22="","",INDEX('All Tasks'!$K:$K,$A22)) | J22: =IF($A22="","",INDEX('All Tasks'!$L:$L,$A22)) | K22: =IF($A22="","",INDEX('All Tasks'!$T:$T,$A22)) | L22: =IF($A22="","",INDEX('All Tasks'!$N:$N,$A22)) | M22: =IF($A22="","",INDEX('All Tasks'!$O:$O,$A22)) | N22: =IF($A22="","",INDEX('All Tasks'!$P:$P,$A22))
A23: =IFERROR(aggregate(15,6,ROW('All Tasks'!$B$2:$B$404)/('All Tasks'!$B$2:$B$404=$C$3),ROWS($A$20:$A23)),"") | B23: =IF($A23="","",INDEX('All Tasks'!$A:$A,$A23)) | C23: =IF($A23="","",INDEX('All Tasks'!$E:$E,$A23)) | D23: =IF($A23="","",INDEX('All Tasks'!$G:$G,$A23)) | E23: =IF($A23="","",INDEX('All Tasks'!$F:$F,$A23)) | F23: =IF($A23="","",INDEX('All Tasks'!$H:$H,$A23)) | G23: =IF($A23="","",INDEX('All Tasks'!$I:$I,$A23)) | H23: =IF($A23="","",INDEX('All Tasks'!$J:$J,$A23)) | I23: =IF($A23="","",INDEX('All Tasks'!$K:$K,$A23)) | J23: =IF($A23="","",INDEX('All Tasks'!$L:$L,$A23)) | K23: =IF($A23="","",INDEX('All Tasks'!$T:$T,$A23)) | L23: =IF($A23="","",INDEX('All Tasks'!$N:$N,$A23)) | M23: =IF($A23="","",INDEX('All Tasks'!$O:$O,$A23)) | N23: =IF($A23="","",INDEX('All Tasks'!$P:$P,$A23))
A24: =IFERROR(aggregate(15,6,ROW('All Tasks'!$B$2:$B$404)/('All Tasks'!$B$2:$B$404=$C$3),ROWS($A$20:$A24)),"") | B24: =IF($A24="","",INDEX('All Tasks'!$A:$A,$A24)) | C24: =IF($A24="","",INDEX('All Tasks'!$E:$E,$A24)) | D24: =IF($A24="","",INDEX('All Tasks'!$G:$G,$A24)) | E24: =IF($A24="","",INDEX('All Tasks'!$F:$F,$A24)) | F24: =IF($A24="","",INDEX('All Tasks'!$H:$H,$A24)) | G24: =IF($A24="","",INDEX('All Tasks'!$I:$I,$A24)) | H24: =IF($A24="","",INDEX('All Tasks'!$J:$J,$A24)) | I24: =IF($A24="","",INDEX('All Tasks'!$K:$K,$A24)) | J24: =IF($A24="","",INDEX('All Tasks'!$L:$L,$A24)) | K24: =IF($A24="","",INDEX('All Tasks'!$T:$T,$A24)) | L24: =IF($A24="","",INDEX('All Tasks'!$N:$N,$A24)) | M24: =IF($A24="","",INDEX('All Tasks'!$O:$O,$A24)) | N24: =IF($A24="","",INDEX('All Tasks'!$P:$P,$A24))
A25: =IFERROR(aggregate(15,6,ROW('All Tasks'!$B$2:$B$404)/('All Tasks'!$B$2:$B$404=$C$3),ROWS($A$20:$A25)),"") | B25: =IF($A25="","",INDEX('All Tasks'!$A:$A,$A25)) | C25: =IF($A25="","",INDEX('All Tasks'!$E:$E,$A25)) | D25: =IF($A25="","",INDEX('All Tasks'!$G:$G,$A25)) | E25: =IF($A25="","",INDEX('All Tasks'!$F:$F,$A25)) | F25: =IF($A25="","",INDEX('All Tasks'!$H:$H,$A25)) | G25: =IF($A25="","",INDEX('All Tasks'!$I:$I,$A25)) | H25: =IF($A25="","",INDEX('All Tasks'!$J:$J,$A25)) | I25: =IF($A25="","",INDEX('All Tasks'!$K:$K,$A25)) | J25: =IF($A25="","",INDEX('All Tasks'!$L:$L,$A25)) | K25: =IF($A25="","",INDEX('All Tasks'!$T:$T,$A25)) | L25: =IF($A25="","",INDEX('All Tasks'!$N:$N,$A25)) | M25: =IF($A25="","",INDEX('All Tasks'!$O:$O,$A25)) | N25: =IF($A25="","",INDEX('All Tasks'!$P:$P,$A25))
A26: =IFERROR(aggregate(15,6,ROW('All Tasks'!$B$2:$B$404)/('All Tasks'!$B$2:$B$404=$C$3),ROWS($A$20:$A26)),"") | B26: =IF($A26="","",INDEX('All Tasks'!$A:$A,$A26)) | C26: =IF($A26="","",INDEX('All Tasks'!$E:$E,$A26)) | D26: =IF($A26="","",INDEX('All Tasks'!$G:$G,$A26)) | E26: =IF($A26="","",INDEX('All Tasks'!$F:$F,$A26)) | F26: =IF($A26="","",INDEX('All Tasks'!$H:$H,$A26)) | G26: =IF($A26="","",INDEX('All Tasks'!$I:$I,$A26)) | H26: =IF($A26="","",INDEX('All Tasks'!$J:$J,$A26)) | I26: =IF($A26="","",INDEX('All Tasks'!$K:$K,$A26)) | J26: =IF($A26="","",INDEX('All Tasks'!$L:$L,$A26)) | K26: =IF($A26="","",INDEX('All Tasks'!$T:$T,$A26)) | L26: =IF($A26="","",INDEX('All Tasks'!$N:$N,$A26)) | M26: =IF($A26="","",INDEX('All Tasks'!$O:$O,$A26)) | N26: =IF($A26="","",INDEX('All Tasks'!$P:$P,$A26))
A27: =IFERROR(aggregate(15,6,ROW('All Tasks'!$B$2:$B$404)/('All Tasks'!$B$2:$B$404=$C$3),ROWS($A$20:$A27)),"") | B27: =IF($A27="","",INDEX('All Tasks'!$A:$A,$A27)) | C27: =IF($A27="","",INDEX('All Tasks'!$E:$E,$A27)) | D27: =IF($A27="","",INDEX('All Tasks'!$G:$G,$A27)) | E27: =IF($A27="","",INDEX('All Tasks'!$F:$F,$A27)) | F27: =IF($A27="","",INDEX('All Tasks'!$H:$H,$A27)) | G27: =IF($A27="","",INDEX('All Tasks'!$I:$I,$A27)) | H27: =IF($A27="","",INDEX('All Tasks'!$J:$J,$A27)) | I27: =IF($A27="","",INDEX('All Tasks'!$K:$K,$A27)) | J27: =IF($A27="","",INDEX('All Tasks'!$L:$L,$A27)) | K27: =IF($A27="","",INDEX('All Tasks'!$T:$T,$A27)) | L27: =IF($A27="","",INDEX('All Tasks'!$N:$N,$A27)) | M27: =IF($A27="","",INDEX('All Tasks'!$O:$O,$A27)) | N27: =IF($A27="","",INDEX('All Tasks'!$P:$P,$A27))
A28: =IFERROR(aggregate(15,6,ROW('All Tasks'!$B$2:$B$404)/('All Tasks'!$B$2:$B$404=$C$3),ROWS($A$20:$A28)),"") | B28: =IF($A28="","",INDEX('All Tasks'!$A:$A,$A28)) | C28: =IF($A28="","",INDEX('All Tasks'!$E:$E,$A28)) | D28: =IF($A28="","",INDEX('All Tasks'!$G:$G,$A28)) | E28: =IF($A28="","",INDEX('All Tasks'!$F:$F,$A28)) | F28: =IF($A28="","",INDEX('All Tasks'!$H:$H,$A28)) | G28: =IF($A28="","",INDEX('All Tasks'!$I:$I,$A28)) | H28: =IF($A28="","",INDEX('All Tasks'!$J:$J,$A28)) | I28: =IF($A28="","",INDEX('All Tasks'!$K:$K,$A28)) | J28: =IF($A28="","",INDEX('All Tasks'!$L:$L,$A28)) | K28: =IF($A28="","",INDEX('All Tasks'!$T:$T,$A28)) | L28: =IF($A28="","",INDEX('All Tasks'!$N:$N,$A28)) | M28: =IF($A28="","",INDEX('All Tasks'!$O:$O,$A28)) | N28: =IF($A28="","",INDEX('All Tasks'!$P:$P,$A28))
A29: =IFERROR(aggregate(15,6,ROW('All Tasks'!$B$2:$B$404)/('All Tasks'!$B$2:$B$404=$C$3),ROWS($A$20:$A29)),"") | B29: =IF($A29="","",INDEX('All Tasks'!$A:$A,$A29)) | C29: =IF($A29="","",INDEX('All Tasks'!$E:$E,$A29)) | D29: =IF($A29="","",INDEX('All Tasks'!$G:$G,$A29)) | E29: =IF($A29="","",INDEX('All Tasks'!$F:$F,$A29)) | F29: =IF($A29="","",INDEX('All Tasks'!$H:$H,$A29)) | G29: =IF($A29="","",INDEX('All Tasks'!$I:$I,$A29)) | H29: =IF($A29="","",INDEX('All Tasks'!$J:$J,$A29)) | I29: =IF($A29="","",INDEX('All Tasks'!$K:$K,$A29)) | J29: =IF($A29="","",INDEX('All Tasks'!$L:$L,$A29)) | K29: =IF($A29="","",INDEX('All Tasks'!$T:$T,$A29)) | L29: =IF($A29="","",INDEX('All Tasks'!$N:$N,$A29)) | M29: =IF($A29="","",INDEX('All Tasks'!$O:$O,$A29)) | N29: =IF($A29="","",INDEX('All Tasks'!$P:$P,$A29))
A30: =IFERROR(aggregate(15,6,ROW('All Tasks'!$B$2:$B$404)/('All Tasks'!$B$2:$B$404=$C$3),ROWS($A$20:$A30)),"") | B30: =IF($A30="","",INDEX('All Tasks'!$A:$A,$A30)) | C30: =IF($A30="","",INDEX('All Tasks'!$E:$E,$A30)) | D30: =IF($A30="","",INDEX('All Tasks'!$G:$G,$A30)) | E30: =IF($A30="","",INDEX('All Tasks'!$F:$F,$A30)) | F30: =IF($A30="","",INDEX('All Tasks'!$H:$H,$A30)) | G30: =IF($A30="","",INDEX('All Tasks'!$I:$I,$A30)) | H30: =IF($A30="","",INDEX('All Tasks'!$J:$J,$A30)) | I30: =IF($A30="","",INDEX('All Tasks'!$K:$K,$A30)) | J30: =IF($A30="","",INDEX('All Tasks'!$L:$L,$A30)) | K30: =IF($A30="","",INDEX('All Tasks'!$T:$T,$A30)) | L30: =IF($A30="","",INDEX('All Tasks'!$N:$N,$A30)) | M30: =IF($A30="","",INDEX('All Tasks'!$O:$O,$A30)) | N30: =IF($A30="","",INDEX('All Tasks'!$P:$P,$A30))
A31: =IFERROR(aggregate(15,6,ROW('All Tasks'!$B$2:$B$404)/('All Tasks'!$B$2:$B$404=$C$3),ROWS($A$20:$A31)),"") | B31: =IF($A31="","",INDEX('All Tasks'!$A:$A,$A31)) | C31: =IF($A31="","",INDEX('All Tasks'!$E:$E,$A31)) | D31: =IF($A31="","",INDEX('All Tasks'!$G:$G,$A31)) | E31: =IF($A31="","",INDEX('All Tasks'!$F:$F,$A31)) | F31: =IF($A31="","",INDEX('All Tasks'!$H:$H,$A31)) | G31: =IF($A31="","",INDEX('All Tasks'!$I:$I,$A31)) | H31: =IF($A31="","",INDEX('All Tasks'!$J:$J,$A31)) | I31: =IF($A31="","",INDEX('All Tasks'!$K:$K,$A31)) | J31: =IF($A31="","",INDEX('All Tasks'!$L:$L,$A31)) | K31: =IF($A31="","",INDEX('All Tasks'!$T:$T,$A31)) | L31: =IF($A31="","",INDEX('All Tasks'!$N:$N,$A31)) | M31: =IF($A31="","",INDEX('All Tasks'!$O:$O,$A31)) | N31: =IF($A31="","",INDEX('All Tasks'!$P:$P,$A31))
... A49: =IFERROR(aggregate(15,6,ROW('All Tasks'!$B$2:$B$404)/('All Tasks'!$B$2:$B$404=$C$3),ROWS($A$20:$A49)),"") | B49: =IF($A49="","",INDEX('All Tasks'!$A:$A,$A49)) | C49: =IF($A49="","",INDEX('All Tasks'!$E:$E,$A49)) | D49: =IF($A49="","",INDEX('All Tasks'!$G:$G,$A49)) | E49: =IF($A49="","",INDEX('All Tasks'!$F:$F,$A49)) | F49: =IF($A49="","",INDEX('All Tasks'!$H:$H,$A49)) | G49: =IF($A49="","",INDEX('All Tasks'!$I:$I,$A49)) | H49: =IF($A49="","",INDEX('All Tasks'!$J:$J,$A49)) | I49: =IF($A49="","",INDEX('All Tasks'!$K:$K,$A49)) | J49: =IF($A49="","",INDEX('All Tasks'!$L:$L,$A49)) | K49: =IF($A49="","",INDEX('All Tasks'!$T:$T,$A49)) | L49: =IF($A49="","",INDEX('All Tasks'!$N:$N,$A49)) | M49: =IF($A49="","",INDEX('All Tasks'!$O:$O,$A49)) | N49: =IF($A49="","",INDEX('All Tasks'!$P:$P,$A49))

Sheet All Tasks
A1: All Tasks — Consolidated Feed (auto)
A2: ENGINE · Every task from every 1:1 tab is pulled here automatically. Do not type here — update tasks on the individual tabs. Filter by Project ID or Assigned To for any view.
A4: Task ID | B4: Project ID | C4: Focus Area | D4: Tactic / Project Name | E4: Assigned To | F4: Role | G4: Task Description | H4: Priority | I4: Status | J4: Percent Complete | K4: Start Date | L4: Due Date | M4: Dependency | N4: Roadblock | O4: Last Update | P4: Next Step | Q4: Source Tab | R4: Overdue | S4: Due7d | T4: DaysToDue | U4: EffPct | V4: HasRoad | W4: Active
A5: =IF('Quick Chadwick'!$B5="","",'Quick Chadwick'!$A5) -> QC-001 | B5: =IF('Quick Chadwick'!$B5="","",'Quick Chadwick'!$B5) -> P2-2 | C5: =IF('Quick Chadwick'!$B5="","",'Quick Chadwick'!$C5) -> 2 – Top-of-Funnel Lead Gen | D5: =IF('Quick Chadwick'!$B5="","",'Quick Chadwick'!$D5) -> Reallocate spend toward non-broker sourced channels | E5: =IF('Quick Chadwick'!$B5="","",'Quick Chadwick'!$E5) -> Quick Chadwick | F5: =IF('Quick Chadwick'!$B5="","",'Quick Chadwick'!$F5) -> Owner | G5: =IF('Quick Chadwick'!$B5="","",'Quick Chadwick'!$G5) -> Develop Marketing Spend Reallocation Plan | H5: =IF('Quick Chadwick'!$B5="","",'Quick Chadwick'!$H5) -> High | I5: =IF('Quick Chadwick'!$B5="","",'Quick Chadwick'!$I5) -> Complete | J5: =IF('Quick Chadwick'!$B5="","",'Quick Chadwick'!$J5) -> 1 | K5: =IF('Quick Chadwick'!$B5="","",'Quick Chadwick'!$K5) -> 46147 | L5: =IF('Quick Chadwick'!$B5="","",'Quick Chadwick'!$L5) -> 46164 | M5: =IF('Quick Chadwick'!$B5="","",'Quick Chadwick'!$M5) -> 0 | N5: =IF('Quick Chadwick'!$B5="","",'Quick Chadwick'!$N5) -> 0 | O5: =IF('Quick Chadwick'!$B5="","",'Quick Chadwick'!$O5) -> Reviewed plan; edits suggested & incorporated | P5: =IF('Quick Chadwick'!$B5="","",'Quick Chadwick'!$P5) -> Monitor reallocated spend vs broker channels | Q5: =IF('Quick Chadwick'!$B5="","","Quick Chadwick") -> Quick Chadwick | R5: =IF(OR($B5="",$I5="Complete",$L5=""),0,IF($L5<TODAY(),1,0)) -> 0 | S5: =IF(OR($B5="",$I5="Complete",$L5=""),0,IF(AND($L5>=TODAY(),$L5<=TODAY()+7),1,0)) -> 0 | T5: =IF(OR($B5="",$L5=""),"",$L5-TODAY()) -> -6 | U5: =IF($B5="","",IF($I5="Complete",1,IF($J5="",0,$J5))) -> 1 | V5: =IF($B5="",0,IF($N5="",0,1)) -> 0 | W5: =IF($B5="",0,1) -> 1
A6: =IF('Quick Chadwick'!$B6="","",'Quick Chadwick'!$A6) -> QC-002 | B6: =IF('Quick Chadwick'!$B6="","",'Quick Chadwick'!$B6) -> P1-1 | C6: =IF('Quick Chadwick'!$B6="","",'Quick Chadwick'!$C6) -> 1 – Unified Development System | D6: =IF('Quick Chadwick'!$B6="","",'Quick Chadwick'!$D6) -> Implement standardized Mutual Evaluation Process (MEP) across all brands | E6: =IF('Quick Chadwick'!$B6="","",'Quick Chadwick'!$E6) -> Quick Chadwick | F6: =IF('Quick Chadwick'!$B6="","",'Quick Chadwick'!$F6) -> Contributor | G6: =IF('Quick Chadwick'!$B6="","",'Quick Chadwick'!$G6) -> Training Section 1-3 in Fran Dev 101 | H6: =IF('Quick Chadwick'!$B6="","",'Quick Chadwick'!$H6) -> Medium | I6: =IF('Quick Chadwick'!$B6="","",'Quick Chadwick'!$I6) -> In Progress | J6: =IF('Quick Chadwick'!$B6="","",'Quick Chadwick'!$J6) -> 0.5 | K6: =IF('Quick Chadwick'!$B6="","",'Quick Chadwick'!$K6) -> 46162 | L6: =IF('Quick Chadwick'!$B6="","",'Quick Chadwick'!$L6) -> 46186 | M6: =IF('Quick Chadwick'!$B6="","",'Quick Chadwick'!$M6) -> 0 | N6: =IF('Quick Chadwick'!$B6="","",'Quick Chadwick'!$N6) -> 0 | O6: =IF('Quick Chadwick'!$B6="","",'Quick Chadwick'!$O6) -> Assigned 5/20 | P6: =IF('Quick Chadwick'!$B6="","",'Quick Chadwick'!$P6) -> Complete sections 2-3 | Q6: =IF('Quick Chadwick'!$B6="","","Quick Chadwick") -> Quick Chadwick | R6: =IF(OR($B6="",$I6="Complete",$L6=""),0,IF($L6<TODAY(),1,0)) -> 0 | S6: =IF(OR($B6="",$I6="Complete",$L6=""),0,IF(AND($L6>=TODAY(),$L6<=TODAY()+7),1,0)) -> 0 | T6: =IF(OR($B6="",$L6=""),"",$L6-TODAY()) -> 16 | U6: =IF($B6="","",IF($I6="Complete",1,IF($J6="",0,$J6))) -> 0.5 | V6: =IF($B6="",0,IF($N6="",0,1)) -> 0 | W6: =IF($B6="",0,1) -> 1
A7: =IF('Quick Chadwick'!$B7="","",'Quick Chadwick'!$A7) -> QC-003 | B7: =IF('Quick Chadwick'!$B7="","",'Quick Chadwick'!$B7) -> P2-3 | C7: =IF('Quick Chadwick'!$B7="","",'Quick Chadwick'!$C7) -> 2 – Top-of-Funnel Lead Gen | D7: =IF('Quick Chadwick'!$B7="","",'Quick Chadwick'!$D7) -> Build video-first funnel | E7: =IF('Quick Chadwick'!$B7="","",'Quick Chadwick'!$E7) -> Quick Chadwick | F7: =IF('Quick Chadwick'!$B7="","",'Quick Chadwick'!$F7) -> Owner | G7: =IF('Quick Chadwick'!$B7="","",'Quick Chadwick'!$G7) -> Video Coordination with Madsen Anderson | H7: =IF('Quick Chadwick'!$B7="","",'Quick Chadwick'!$H7) -> High | I7: =IF('Quick Chadwick'!$B7="","",'Quick Chadwick'!$I7) -> In Progress | J7: =IF('Quick Chadwick'!$B7="","",'Quick Chadwick'!$J7) -> 0.3 | K7: =IF('Quick Chadwick'!$B7="","",'Quick Chadwick'!$K7) -> 46157 | L7: =IF('Quick Chadwick'!$B7="","",'Quick Chadwick'!$L7) -> 46193 | M7: =IF('Quick Chadwick'!$B7="","",'Quick Chadwick'!$M7) -> 0 | N7: =IF('Quick Chadwick'!$B7="","",'Quick Chadwick'!$N7) -> 0 | O7: =IF('Quick Chadwick'!$B7="","",'Quick Chadwick'!$O7) -> Coordinating shoot schedule | P7: =IF('Quick Chadwick'!$B7="","",'Quick Chadwick'!$P7) -> Lock production calendar | Q7: =IF('Quick Chadwick'!$B7="","","Quick Chadwick") -> Quick Chadwick | R7: =IF(OR($B7="",$I7="Complete",$L7=""),0,IF($L7<TODAY(),1,0)) -> 0 | S7: =IF(OR($B7="",$I7="Complete",$L7=""),0,IF(AND($L7>=TODAY(),$L7<=TODAY()+7),1,0)) -> 0 | T7: =IF(OR($B7="",$L7=""),"",$L7-TODAY()) -> 23 | U7: =IF($B7="","",IF($I7="Complete",1,IF($J7="",0,$J7))) -> 0.3 | V7: =IF($B7="",0,IF($N7="",0,1)) -> 0 | W7: =IF($B7="",0,1) -> 1
A8: =IF('Quick Chadwick'!$B8="","",'Quick Chadwick'!$A8) -> QC-004 | B8: =IF('Quick Chadwick'!$B8="","",'Quick Chadwick'!$B8) -> P6-1 | C8: =IF('Quick Chadwick'!$B8="","",'Quick Chadwick'!$C8) -> 6 – Automation & Content | D8: =IF('Quick Chadwick'!$B8="","",'Quick Chadwick'!$D8) -> Develop standardized brand overview videos | E8: =IF('Quick Chadwick'!$B8="","",'Quick Chadwick'!$E8) -> Quick Chadwick | F8: =IF('Quick Chadwick'!$B8="","",'Quick Chadwick'!$F8) -> Owner | G8: =IF('Quick Chadwick'!$B8="","",'Quick Chadwick'!$G8) -> Video Project (Signature 7 – 1-Tom) | H8: =IF('Quick Chadwick'!$B8="","",'Quick Chadwick'!$H8) -> High | I8: =IF('Quick Chadwick'!$B8="","",'Quick Chadwick'!$I8) -> Complete | J8: =IF('Quick Chadwick'!$B8="","",'Quick Chadwick'!$J8) -> 1 | K8: =IF('Quick Chadwick'!$B8="","",'Quick Chadwick'!$K8) -> 46143 | L8: =IF('Quick Chadwick'!$B8="","",'Quick Chadwick'!$L8) -> 46162 | M8: =IF('Quick Chadwick'!$B8="","",'Quick Chadwick'!$M8) -> 0 | N8: =IF('Quick Chadwick'!$B8="","",'Quick Chadwick'!$N8) -> 0 | O8: =IF('Quick Chadwick'!$B8="","",'Quick Chadwick'!$O8) -> Completed | P8: =IF('Quick Chadwick'!$B8="","",'Quick Chadwick'!$P8) -> Publish to content library | Q8: =IF('Quick Chadwick'!$B8="","","Quick Chadwick") -> Quick Chadwick | R8: =IF(OR($B8="",$I8="Complete",$L8=""),0,IF($L8<TODAY(),1,0)) -> 0 | S8: =IF(OR($B8="",$I8="Complete",$L8=""),0,IF(AND($L8>=TODAY(),$L8<=TODAY()+7),1,0)) -> 0 | T8: =IF(OR($B8="",$L8=""),"",$L8-TODAY()) -> -8 | U8: =IF($B8="","",IF($I8="Complete",1,IF($J8="",0,$J8))) -> 1 | V8: =IF($B8="",0,IF($N8="",0,1)) -> 0 | W8: =IF($B8="",0,1) -> 1
A9: =IF('Quick Chadwick'!$B9="","",'Quick Chadwick'!$A9) -> QC-005 | B9: =IF('Quick Chadwick'!$B9="","",'Quick Chadwick'!$B9) -> P6-1 | C9: =IF('Quick Chadwick'!$B9="","",'Quick Chadwick'!$C9) -> 6 – Automation & Content | D9: =IF('Quick Chadwick'!$B9="","",'Quick Chadwick'!$D9) -> Develop standardized brand overview videos | E9: =IF('Quick Chadwick'!$B9="","",'Quick Chadwick'!$E9) -> Quick Chadwick | F9: =IF('Quick Chadwick'!$B9="","",'Quick Chadwick'!$F9) -> Owner | G9: =IF('Quick Chadwick'!$B9="","",'Quick Chadwick'!$G9) -> Video Project (Signature 7 – The Seals) | H9: =IF('Quick Chadwick'!$B9="","",'Quick Chadwick'!$H9) -> Medium | I9: =IF('Quick Chadwick'!$B9="","",'Quick Chadwick'!$I9) -> In Progress | J9: =IF('Quick Chadwick'!$B9="","",'Quick Chadwick'!$J9) -> 0.4 | K9: =IF('Quick Chadwick'!$B9="","",'Quick Chadwick'!$K9) -> 46152 | L9: =IF('Quick Chadwick'!$B9="","",'Quick Chadwick'!$L9) -> 46203 | M9: =IF('Quick Chadwick'!$B9="","",'Quick Chadwick'!$M9) -> 0 | N9: =IF('Quick Chadwick'!$B9="","",'Quick Chadwick'!$N9) -> 0 | O9: =IF('Quick Chadwick'!$B9="","",'Quick Chadwick'!$O9) -> JL has sample; could be used as sub | P9: =IF('Quick Chadwick'!$B9="","",'Quick Chadwick'!$P9) -> Confirm sub footage with Jamie | Q9: =IF('Quick Chadwick'!$B9="","","Quick Chadwick") -> Quick Chadwick | R9: =IF(OR($B9="",$I9="Complete",$L9=""),0,IF($L9<TODAY(),1,0)) -> 0 | S9: =IF(OR($B9="",$I9="Complete",$L9=""),0,IF(AND($L9>=TODAY(),$L9<=TODAY()+7),1,0)) -> 0 | T9: =IF(OR($B9="",$L9=""),"",$L9-TODAY()) -> 33 | U9: =IF($B9="","",IF($I9="Complete",1,IF($J9="",0,$J9))) -> 0.4 | V9: =IF($B9="",0,IF($N9="",0,1)) -> 0 | W9: =IF($B9="",0,1) -> 1
A10: =IF('Quick Chadwick'!$B10="","",'Quick Chadwick'!$A10) -> QC-006 | B10: =IF('Quick Chadwick'!$B10="","",'Quick Chadwick'!$B10) -> P6-1 | C10: =IF('Quick Chadwick'!$B10="","",'Quick Chadwick'!$C10) -> 6 – Automation & Content | D10: =IF('Quick Chadwick'!$B10="","",'Quick Chadwick'!$D10) -> Develop standardized brand overview videos | E10: =IF('Quick Chadwick'!$B10="","",'Quick Chadwick'!$E10) -> Quick Chadwick | F10: =IF('Quick Chadwick'!$B10="","",'Quick Chadwick'!$F10) -> Owner | G10: =IF('Quick Chadwick'!$B10="","",'Quick Chadwick'!$G10) -> Video Project (Signature 7 – Kitchen Guard) | H10: =IF('Quick Chadwick'!$B10="","",'Quick Chadwick'!$H10) -> Medium | I10: =IF('Quick Chadwick'!$B10="","",'Quick Chadwick'!$I10) -> In Progress | J10: =IF('Quick Chadwick'!$B10="","",'Quick Chadwick'!$J10) -> 0.25 | K10: =IF('Quick Chadwick'!$B10="","",'Quick Chadwick'!$K10) -> 46152 | L10: =IF('Quick Chadwick'!$B10="","",'Quick Chadwick'!$L10) -> 46218 | M10: =IF('Quick Chadwick'!$B10="","",'Quick Chadwick'!$M10) -> 0 | N10: =IF('Quick Chadwick'!$B10="","",'Quick Chadwick'!$N10) -> 0 | O10: =IF('Quick Chadwick'!$B10="","",'Quick Chadwick'!$O10) -> Could use Bytes & Insights for sub | P10: =IF('Quick Chadwick'!$B10="","",'Quick Chadwick'!$P10) -> Source sub footage | Q10: =IF('Quick Chadwick'!$B10="","","Quick Chadwick") -> Quick Chadwick | R10: =IF(OR($B10="",$I10="Complete",$L10=""),0,IF($L10<TODAY(),1,0)) -> 0 | S10: =IF(OR($B10="",$I10="Complete",$L10=""),0,IF(AND($L10>=TODAY(),$L10<=TODAY()+7),1,0)) -> 0 | T10: =IF(OR($B10="",$L10=""),"",$L10-TODAY()) -> 48 | U10: =IF($B10="","",IF($I10="Complete",1,IF($J10="",0,$J10))) -> 0.25 | V10: =IF($B10="",0,IF($N10="",0,1)) -> 0 | W10: =IF($B10="",0,1) -> 1
A11: =IF('Quick Chadwick'!$B11="","",'Quick Chadwick'!$A11) -> QC-007 | B11: =IF('Quick Chadwick'!$B11="","",'Quick Chadwick'!$B11) -> P6-1 | C11: =IF('Quick Chadwick'!$B11="","",'Quick Chadwick'!$C11) -> 6 – Automation & Content | D11: =IF('Quick Chadwick'!$B11="","",'Quick Chadwick'!$D11) -> Develop standardized brand overview videos | E11: =IF('Quick Chadwick'!$B11="","",'Quick Chadwick'!$E11) -> Quick Chadwick | F11: =IF('Quick Chadwick'!$B11="","",'Quick Chadwick'!$F11) -> Owner | G11: =IF('Quick Chadwick'!$B11="","",'Quick Chadwick'!$G11) -> Video Project (Signature 7 – MilliCare) | H11: =IF('Quick Chadwick'!$B11="","",'Quick Chadwick'!$H11) -> Medium | I11: =IF('Quick Chadwick'!$B11="","",'Quick Chadwick'!$I11) -> Not Started | J11: =IF('Quick Chadwick'!$B11="","",'Quick Chadwick'!$J11) -> 0 | K11: =IF('Quick Chadwick'!$B11="","",'Quick Chadwick'!$K11) -> 46174 | L11: =IF('Quick Chadwick'!$B11="","",'Quick Chadwick'!$L11) -> 46234 | M11: =IF('Quick Chadwick'!$B11="","",'Quick Chadwick'!$M11) -> Coordinate with Steve Griffith | N11: =IF('Quick Chadwick'!$B11="","",'Quick Chadwick'!$N11) -> 0 | O11: =IF('Quick Chadwick'!$B11="","",'Quick Chadwick'!$O11) -> 0 | P11: =IF('Quick Chadwick'!$B11="","",'Quick Chadwick'!$P11) -> Kickoff with SG | Q11: =IF('Quick Chadwick'!$B11="","","Quick Chadwick") -> Quick Chadwick | R11: =IF(OR($B11="",$I11="Complete",$L11=""),0,IF($L11<TODAY(),1,0)) -> 0 | S11: =IF(OR($B11="",$I11="Complete",$L11=""),0,IF(AND($L11>=TODAY(),$L11<=TODAY()+7),1,0)) -> 0 | T11: =IF(OR($B11="",$L11=""),"",$L11-TODAY()) -> 64 | U11: =IF($B11="","",IF($I11="Complete",1,IF($J11="",0,$J11))) -> 0 | V11: =IF($B11="",0,IF($N11="",0,1)) -> 0 | W11: =IF($B11="",0,1) -> 1
A12: =IF('Quick Chadwick'!$B12="","",'Quick Chadwick'!$A12) -> QC-008 | B12: =IF('Quick Chadwick'!$B12="","",'Quick Chadwick'!$B12) -> P6-1 | C12: =IF('Quick Chadwick'!$B12="","",'Quick Chadwick'!$C12) -> 6 – Automation & Content | D12: =IF('Quick Chadwick'!$B12="","",'Quick Chadwick'!$D12) -> Develop standardized brand overview videos | E12: =IF('Quick Chadwick'!$B12="","",'Quick Chadwick'!$E12) -> Quick Chadwick | F12: =IF('Quick Chadwick'!$B12="","",'Quick Chadwick'!$F12) -> Owner | G12: =IF('Quick Chadwick'!$B12="","",'Quick Chadwick'!$G12) -> Video Project (Signature 7 – Prism) | H12: =IF('Quick Chadwick'!$B12="","",'Quick Chadwick'!$H12) -> Medium | I12: =IF('Quick Chadwick'!$B12="","",'Quick Chadwick'!$I12) -> In Progress | J12: =IF('Quick Chadwick'!$B12="","",'Quick Chadwick'!$J12) -> 0.4 | K12: =IF('Quick Chadwick'!$B12="","",'Quick Chadwick'!$K12) -> 46152 | L12: =IF('Quick Chadwick'!$B12="","",'Quick Chadwick'!$L12) -> 46203 | M12: =IF('Quick Chadwick'!$B12="","",'Quick Chadwick'!$M12) -> 0 | N12: =IF('Quick Chadwick'!$B12="","",'Quick Chadwick'!$N12) -> 0 | O12: =IF('Quick Chadwick'!$B12="","",'Quick Chadwick'!$O12) -> JL has sample | P12: =IF('Quick Chadwick'!$B12="","",'Quick Chadwick'!$P12) -> Confirm sub footage | Q12: =IF('Quick Chadwick'!$B12="","","Quick Chadwick") -> Quick Chadwick | R12: =IF(OR($B12="",$I12="Complete",$L12=""),0,IF($L12<TODAY(),1,0)) -> 0 | S12: =IF(OR($B12="",$I12="Complete",$L12=""),0,IF(AND($L12>=TODAY(),$L12<=TODAY()+7),1,0)) -> 0 | T12: =IF(OR($B12="",$L12=""),"",$L12-TODAY()) -> 33 | U12: =IF($B12="","",IF($I12="Complete",1,IF($J12="",0,$J12))) -> 0.4 | V12: =IF($B12="",0,IF($N12="",0,1)) -> 0 | W12: =IF($B12="",0,1) -> 1
A13: =IF('Quick Chadwick'!$B13="","",'Quick Chadwick'!$A13) -> QC-009 | B13: =IF('Quick Chadwick'!$B13="","",'Quick Chadwick'!$B13) -> P6-1 | C13: =IF('Quick Chadwick'!$B13="","",'Quick Chadwick'!$C13) -> 6 – Automation & Content | D13: =IF('Quick Chadwick'!$B13="","",'Quick Chadwick'!$D13) -> Develop standardized brand overview videos | E13: =IF('Quick Chadwick'!$B13="","",'Quick Chadwick'!$E13) -> Quick Chadwick | F13: =IF('Quick Chadwick'!$B13="","",'Quick Chadwick'!$F13) -> Owner | G13: =IF('Quick Chadwick'!$B13="","",'Quick Chadwick'!$G13) -> Video Project (Signature 7 – Clintar) | H13: =IF('Quick Chadwick'!$B13="","",'Quick Chadwick'!$H13) -> Medium | I13: =IF('Quick Chadwick'!$B13="","",'Quick Chadwick'!$I13) -> In Progress | J13: =IF('Quick Chadwick'!$B13="","",'Quick Chadwick'!$J13) -> 0.3 | K13: =IF('Quick Chadwick'!$B13="","",'Quick Chadwick'!$K13) -> 46152 | L13: =IF('Quick Chadwick'!$B13="","",'Quick Chadwick'!$L13) -> 46218 | M13: =IF('Quick Chadwick'!$B13="","",'Quick Chadwick'!$M13) -> 0 | N13: =IF('Quick Chadwick'!$B13="","",'Quick Chadwick'!$N13) -> 0 | O13: =IF('Quick Chadwick'!$B13="","",'Quick Chadwick'!$O13) -> Could use TES for sub | P13: =IF('Quick Chadwick'!$B13="","",'Quick Chadwick'!$P13) -> Source sub footage | Q13: =IF('Quick Chadwick'!$B13="","","Quick Chadwick") -> Quick Chadwick | R13: =IF(OR($B13="",$I13="Complete",$L13=""),0,IF($L13<TODAY(),1,0)) -> 0 | S13: =IF(OR($B13="",$I13="Complete",$L13=""),0,IF(AND($L13>=TODAY(),$L13<=TODAY()+7),1,0)) -> 0 | T13: =IF(OR($B13="",$L13=""),"",$L13-TODAY()) -> 48 | U13: =IF($B13="","",IF($I13="Complete",1,IF($J13="",0,$J13))) -> 0.3 | V13: =IF($B13="",0,IF($N13="",0,1)) -> 0 | W13: =IF($B13="",0,1) -> 1
A14: =IF('Quick Chadwick'!$B14="","",'Quick Chadwick'!$A14) -> QC-010 | B14: =IF('Quick Chadwick'!$B14="","",'Quick Chadwick'!$B14) -> P6-1 | C14: =IF('Quick Chadwick'!$B14="","",'Quick Chadwick'!$C14) -> 6 – Automation & Content | D14: =IF('Quick Chadwick'!$B14="","",'Quick Chadwick'!$D14) -> Develop standardized brand overview videos | E14: =IF('Quick Chadwick'!$B14="","",'Quick Chadwick'!$E14) -> Quick Chadwick | F14: =IF('Quick Chadwick'!$B14="","",'Quick Chadwick'!$F14) -> Owner | G14: =IF('Quick Chadwick'!$B14="","",'Quick Chadwick'!$G14) -> Video Project (Signature 7 – US Lawns) | H14: =IF('Quick Chadwick'!$B14="","",'Quick Chadwick'!$H14) -> Medium | I14: =IF('Quick Chadwick'!$B14="","",'Quick Chadwick'!$I14) -> Not Started | J14: =IF('Quick Chadwick'!$B14="","",'Quick Chadwick'!$J14) -> 0 | K14: =IF('Quick Chadwick'!$B14="","",'Quick Chadwick'!$K14) -> 46174 | L14: =IF('Quick Chadwick'!$B14="","",'Quick Chadwick'!$L14) -> 46234 | M14: =IF('Quick Chadwick'!$B14="","",'Quick Chadwick'!$M14) -> Coordinate with JS | N14: =IF('Quick Chadwick'!$B14="","",'Quick Chadwick'!$N14) -> 0 | O14: =IF('Quick Chadwick'!$B14="","",'Quick Chadwick'!$O14) -> 0 | P14: =IF('Quick Chadwick'!$B14="","",'Quick Chadwick'!$P14) -> Kickoff with JS | Q14: =IF('Quick Chadwick'!$B14="","","Quick Chadwick") -> Quick Chadwick | R14: =IF(OR($B14="",$I14="Complete",$L14=""),0,IF($L14<TODAY(),1,0)) -> 0 | S14: =IF(OR($B14="",$I14="Complete",$L14=""),0,IF(AND($L14>=TODAY(),$L14<=TODAY()+7),1,0)) -> 0 | T14: =IF(OR($B14="",$L14=""),"",$L14-TODAY()) -> 64 | U14: =IF($B14="","",IF($I14="Complete",1,IF($J14="",0,$J14))) -> 0 | V14: =IF($B14="",0,IF($N14="",0,1)) -> 0 | W14: =IF($B14="",0,1) -> 1
A15: =IF('Quick Chadwick'!$B15="","",'Quick Chadwick'!$A15) | B15: =IF('Quick Chadwick'!$B15="","",'Quick Chadwick'!$B15) | C15: =IF('Quick Chadwick'!$B15="","",'Quick Chadwick'!$C15) | D15: =IF('Quick Chadwick'!$B15="","",'Quick Chadwick'!$D15) | E15: =IF('Quick Chadwick'!$B15="","",'Quick Chadwick'!$E15) | F15: =IF('Quick Chadwick'!$B15="","",'Quick Chadwick'!$F15) | G15: =IF('Quick Chadwick'!$B15="","",'Quick Chadwick'!$G15) | H15: =IF('Quick Chadwick'!$B15="","",'Quick Chadwick'!$H15) | I15: =IF('Quick Chadwick'!$B15="","",'Quick Chadwick'!$I15) | J15: =IF('Quick Chadwick'!$B15="","",'Quick Chadwick'!$J15) | K15: =IF('Quick Chadwick'!$B15="","",'Quick Chadwick'!$K15) | L15: =IF('Quick Chadwick'!$B15="","",'Quick Chadwick'!$L15) | M15: =IF('Quick Chadwick'!$B15="","",'Quick Chadwick'!$M15) | N15: =IF('Quick Chadwick'!$B15="","",'Quick Chadwick'!$N15) | O15: =IF('Quick Chadwick'!$B15="","",'Quick Chadwick'!$O15) | P15: =IF('Quick Chadwick'!$B15="","",'Quick Chadwick'!$P15) | Q15: =IF('Quick Chadwick'!$B15="","","Quick Chadwick") | R15: =IF(OR($B15="",$I15="Complete",$L15=""),0,IF($L15<TODAY(),1,0)) -> 0 | S15: =IF(OR($B15="",$I15="Complete",$L15=""),0,IF(AND($L15>=TODAY(),$L15<=TODAY()+7),1,0)) -> 0 | T15: =IF(OR($B15="",$L15=""),"",$L15-TODAY()) | U15: =IF($B15="","",IF($I15="Complete",1,IF($J15="",0,$J15))) | V15: =IF($B15="",0,IF($N15="",0,1)) -> 0 | W15: =IF($B15="",0,1) -> 0
A16: =IF('Quick Chadwick'!$B16="","",'Quick Chadwick'!$A16) | B16: =IF('Quick Chadwick'!$B16="","",'Quick Chadwick'!$B16) | C16: =IF('Quick Chadwick'!$B16="","",'Quick Chadwick'!$C16) | D16: =IF('Quick Chadwick'!$B16="","",'Quick Chadwick'!$D16) | E16: =IF('Quick Chadwick'!$B16="","",'Quick Chadwick'!$E16) | F16: =IF('Quick Chadwick'!$B16="","",'Quick Chadwick'!$F16) | G16: =IF('Quick Chadwick'!$B16="","",'Quick Chadwick'!$G16) | H16: =IF('Quick Chadwick'!$B16="","",'Quick Chadwick'!$H16) | I16: =IF('Quick Chadwick'!$B16="","",'Quick Chadwick'!$I16) | J16: =IF('Quick Chadwick'!$B16="","",'Quick Chadwick'!$J16) | K16: =IF('Quick Chadwick'!$B16="","",'Quick Chadwick'!$K16) | L16: =IF('Quick Chadwick'!$B16="","",'Quick Chadwick'!$L16) | M16: =IF('Quick Chadwick'!$B16="","",'Quick Chadwick'!$M16) | N16: =IF('Quick Chadwick'!$B16="","",'Quick Chadwick'!$N16) | O16: =IF('Quick Chadwick'!$B16="","",'Quick Chadwick'!$O16) | P16: =IF('Quick Chadwick'!$B16="","",'Quick Chadwick'!$P16) | Q16: =IF('Quick Chadwick'!$B16="","","Quick Chadwick") | R16: =IF(OR($B16="",$I16="Complete",$L16=""),0,IF($L16<TODAY(),1,0)) -> 0 | S16: =IF(OR($B16="",$I16="Complete",$L16=""),0,IF(AND($L16>=TODAY(),$L16<=TODAY()+7),1,0)) -> 0 | T16: =IF(OR($B16="",$L16=""),"",$L16-TODAY()) | U16: =IF($B16="","",IF($I16="Complete",1,IF($J16="",0,$J16))) | V16: =IF($B16="",0,IF($N16="",0,1)) -> 0 | W16: =IF($B16="",0,1) -> 0
... A44: =IF('Quick Chadwick'!$B44="","",'Quick Chadwick'!$A44) | B44: =IF('Quick Chadwick'!$B44="","",'Quick Chadwick'!$B44) | C44: =IF('Quick Chadwick'!$B44="","",'Quick Chadwick'!$C44) | D44: =IF('Quick Chadwick'!$B44="","",'Quick Chadwick'!$D44) | E44: =IF('Quick Chadwick'!$B44="","",'Quick Chadwick'!$E44) | F44: =IF('Quick Chadwick'!$B44="","",'Quick Chadwick'!$F44) | G44: =IF('Quick Chadwick'!$B44="","",'Quick Chadwick'!$G44) | H44: =IF('Quick Chadwick'!$B44="","",'Quick Chadwick'!$H44) | I44: =IF('Quick Chadwick'!$B44="","",'Quick Chadwick'!$I44) | J44: =IF('Quick Chadwick'!$B44="","",'Quick Chadwick'!$J44) | K44: =IF('Quick Chadwick'!$B44="","",'Quick Chadwick'!$K44) | L44: =IF('Quick Chadwick'!$B44="","",'Quick Chadwick'!$L44) | M44: =IF('Quick Chadwick'!$B44="","",'Quick Chadwick'!$M44) | N44: =IF('Quick Chadwick'!$B44="","",'Quick Chadwick'!$N44) | O44: =IF('Quick Chadwick'!$B44="","",'Quick Chadwick'!$O44) | P44: =IF('Quick Chadwick'!$B44="","",'Quick Chadwick'!$P44) | Q44: =IF('Quick Chadwick'!$B44="","","Quick Chadwick") | R44: =IF(OR($B44="",$I44="Complete",$L44=""),0,IF($L44<TODAY(),1,0)) -> 0 | S44: =IF(OR($B44="",$I44="Complete",$L44=""),0,IF(AND($L44>=TODAY(),$L44<=TODAY()+7),1,0)) -> 0 | T44: =IF(OR($B44="",$L44=""),"",$L44-TODAY()) | U44: =IF($B44="","",IF($I44="Complete",1,IF($J44="",0,$J44))) | V44: =IF($B44="",0,IF($N44="",0,1)) -> 0 | W44: =IF($B44="",0,1) -> 0
A45: =IF('MaryFran Anderson'!$B5="","",'MaryFran Anderson'!$A5) -> MFA-001 | B45: =IF('MaryFran Anderson'!$B5="","",'MaryFran Anderson'!$B5) -> P1-1 | C45: =IF('MaryFran Anderson'!$B5="","",'MaryFran Anderson'!$C5) -> 1 – Unified Development System | D45: =IF('MaryFran Anderson'!$B5="","",'MaryFran Anderson'!$D5) -> Implement standardized Mutual Evaluation Process (MEP) across all brands | E45: =IF('MaryFran Anderson'!$B5="","",'MaryFran Anderson'!$E5) -> MaryFran Anderson | F45: =IF('MaryFran Anderson'!$B5="","",'MaryFran Anderson'!$F5) -> Contributor | G45: =IF('MaryFran Anderson'!$B5="","",'MaryFran Anderson'!$G5) -> Training Section 1-3 in Fran Dev 101 | H45: =IF('MaryFran Anderson'!$B5="","",'MaryFran Anderson'!$H5) -> Medium | I45: =IF('MaryFran Anderson'!$B5="","",'MaryFran Anderson'!$I5) -> In Progress | J45: =IF('MaryFran Anderson'!$B5="","",'MaryFran Anderson'!$J5) -> 0.5 | K45: =IF('MaryFran Anderson'!$B5="","",'MaryFran Anderson'!$K5) -> 46162 | L45: =IF('MaryFran Anderson'!$B5="","",'MaryFran Anderson'!$L5) -> 46186 | M45: =IF('MaryFran Anderson'!$B5="","",'MaryFran Anderson'!$M5) -> 0 | N45: =IF('MaryFran Anderson'!$B5="","",'MaryFran Anderson'!$N5) -> 0 | O45: =IF('MaryFran Anderson'!$B5="","",'MaryFran Anderson'!$O5) -> Assigned 5/20 | P45: =IF('MaryFran Anderson'!$B5="","",'MaryFran Anderson'!$P5) -> Complete sections 2-3 | Q45: =IF('MaryFran Anderson'!$B5="","","MaryFran Anderson") -> MaryFran Anderson | R45: =IF(OR($B45="",$I45="Complete",$L45=""),0,IF($L45<TODAY(),1,0)) -> 0 | S45: =IF(OR($B45="",$I45="Complete",$L45=""),0,IF(AND($L45>=TODAY(),$L45<=TODAY()+7),1,0)) -> 0 | T45: =IF(OR($B45="",$L45=""),"",$L45-TODAY()) -> 16 | U45: =IF($B45="","",IF($I45="Complete",1,IF($J45="",0,$J45))) -> 0.5 | V45: =IF($B45="",0,IF($N45="",0,1)) -> 0 | W45: =IF($B45="",0,1) -> 1
A46: =IF('MaryFran Anderson'!$B6="","",'MaryFran Anderson'!$A6) -> MFA-002 | B46: =IF('MaryFran Anderson'!$B6="","",'MaryFran Anderson'!$B6) -> P3-2 | C46: =IF('MaryFran Anderson'!$B6="","",'MaryFran Anderson'!$C6) -> 3 – Broker Channel | D46: =IF('MaryFran Anderson'!$B6="","",'MaryFran Anderson'!$D6) -> Route 100% of broker leads through CRM for centralized intake and visibility. | E46: =IF('MaryFran Anderson'!$B6="","",'MaryFran Anderson'!$E6) -> MaryFran Anderson | F46: =IF('MaryFran Anderson'!$B6="","",'MaryFran Anderson'!$F6) -> Owner | G46: =IF('MaryFran Anderson'!$B6="","",'MaryFran Anderson'!$G6) -> Broker Portal Update | H46: =IF('MaryFran Anderson'!$B6="","",'MaryFran Anderson'!$H6) -> High | I46: =IF('MaryFran Anderson'!$B6="","",'MaryFran Anderson'!$I6) -> In Progress | J46: =IF('MaryFran Anderson'!$B6="","",'MaryFran Anderson'!$J6) -> 0.4 | K46: =IF('MaryFran Anderson'!$B6="","",'MaryFran Anderson'!$K6) -> 46154 | L46: =IF('MaryFran Anderson'!$B6="","",'MaryFran Anderson'!$L6) -> 46176 | M46: =IF('MaryFran Anderson'!$B6="","",'MaryFran Anderson'!$M6) -> 0 | N46: =IF('MaryFran Anderson'!$B6="","",'MaryFran Anderson'!$N6) -> 0 | O46: =IF('MaryFran Anderson'!$B6="","",'MaryFran Anderson'!$O6) -> Updating broker portal records | P46: =IF('MaryFran Anderson'!$B6="","",'MaryFran Anderson'!$P6) -> Finalize portal field mapping | Q46: =IF('MaryFran Anderson'!$B6="","","MaryFran Anderson") -> MaryFran Anderson | R46: =IF(OR($B46="",$I46="Complete",$L46=""),0,IF($L46<TODAY(),1,0)) -> 0 | S46: =IF(OR($B46="",$I46="Complete",$L46=""),0,IF(AND($L46>=TODAY(),$L46<=TODAY()+7),1,0)) -> 1 | T46: =IF(OR($B46="",$L46=""),"",$L46-TODAY()) -> 6 | U46: =IF($B46="","",IF($I46="Complete",1,IF($J46="",0,$J46))) -> 0.4 | V46: =IF($B46="",0,IF($N46="",0,1)) -> 0 | W46: =IF($B46="",0,1) -> 1
A47: =IF('MaryFran Anderson'!$B7="","",'MaryFran Anderson'!$A7) -> MFA-003 | B47: =IF('MaryFran Anderson'!$B7="","",'MaryFran Anderson'!$B7) -> P3-1 | C47: =IF('MaryFran Anderson'!$B7="","",'MaryFran Anderson'!$C7) -> 3 – Broker Channel | D47: =IF('MaryFran Anderson'!$B7="","",'MaryFran Anderson'!$D7) -> Assign MaryFran as broker channel owner | E47: =IF('MaryFran Anderson'!$B7="","",'MaryFran Anderson'!$E7) -> MaryFran Anderson | F47: =IF('MaryFran Anderson'!$B7="","",'MaryFran Anderson'!$F7) -> Owner | G47: =IF('MaryFran Anderson'!$B7="","",'MaryFran Anderson'!$G7) -> Broker Engagement Opportunities (membership opps) | H47: =IF('MaryFran Anderson'!$B7="","",'MaryFran Anderson'!$H7) -> Medium | I47: =IF('MaryFran Anderson'!$B7="","",'MaryFran Anderson'!$I7) -> In Progress | J47: =IF('MaryFran Anderson'!$B7="","",'MaryFran Anderson'!$J7) -> 0.3 | K47: =IF('MaryFran Anderson'!$B7="","",'MaryFran Anderson'!$K7) -> 46154 | L47: =IF('MaryFran Anderson'!$B7="","",'MaryFran Anderson'!$L7) -> 46188 | M47: =IF('MaryFran Anderson'!$B7="","",'MaryFran Anderson'!$M7) -> 0 | N47: =IF('MaryFran Anderson'!$B7="","",'MaryFran Anderson'!$N7) -> 0 | O47: =IF('MaryFran Anderson'!$B7="","",'MaryFran Anderson'!$O7) -> Coordinating with Chadwick | P47: =IF('MaryFran Anderson'!$B7="","",'MaryFran Anderson'!$P7) -> Identify missed membership opportunities | Q47: =IF('MaryFran Anderson'!$B7="","","MaryFran Anderson") -> MaryFran Anderson | R47: =IF(OR($B47="",$I47="Complete",$L47=""),0,IF($L47<TODAY(),1,0)) -> 0 | S47: =IF(OR($B47="",$I47="Complete",$L47=""),0,IF(AND($L47>=TODAY(),$L47<=TODAY()+7),1,0)) -> 0 | T47: =IF(OR($B47="",$L47=""),"",$L47-TODAY()) -> 18 | U47: =IF($B47="","",IF($I47="Complete",1,IF($J47="",0,$J47))) -> 0.3 | V47: =IF($B47="",0,IF($N47="",0,1)) -> 0 | W47: =IF($B47="",0,1) -> 1
A48: =IF('MaryFran Anderson'!$B8="","",'MaryFran Anderson'!$A8) -> MFA-004 | B48: =IF('MaryFran Anderson'!$B8="","",'MaryFran Anderson'!$B8) -> P3-1 | C48: =IF('MaryFran Anderson'!$B8="","",'MaryFran Anderson'!$C8) -> 3 – Broker Channel | D48: =IF('MaryFran Anderson'!$B8="","",'MaryFran Anderson'!$D8) -> Assign MaryFran as broker channel owner | E48: =IF('MaryFran Anderson'!$B8="","",'MaryFran Anderson'!$E8) -> MaryFran Anderson | F48: =IF('MaryFran Anderson'!$B8="","",'MaryFran Anderson'!$F8) -> Owner | G48: =IF('MaryFran Anderson'!$B8="","",'MaryFran Anderson'!$G8) -> Broker Outreach Campaign (HubSpot drip build) | H48: =IF('MaryFran Anderson'!$B8="","",'MaryFran Anderson'!$H8) -> High | I48: =IF('MaryFran Anderson'!$B8="","",'MaryFran Anderson'!$I8) -> Blocked | J48: =IF('MaryFran Anderson'!$B8="","",'MaryFran Anderson'!$J8) -> 0.1 | K48: =IF('MaryFran Anderson'!$B8="","",'MaryFran Anderson'!$K8) -> 46174 | L48: =IF('MaryFran Anderson'!$B8="","",'MaryFran Anderson'!$L8) -> 46200 | M48: =IF('MaryFran Anderson'!$B8="","",'MaryFran Anderson'!$M8) -> HubSpot drip assets from QC | N48: =IF('MaryFran Anderson'!$B8="","",'MaryFran Anderson'!$N8) -> Waiting on HubSpot drip assets from Chadwick | O48: =IF('MaryFran Anderson'!$B8="","",'MaryFran Anderson'!$O8) -> Coordinate with QC | P48: =IF('MaryFran Anderson'!$B8="","",'MaryFran Anderson'!$P8) -> Unblock drip assets, then define sequence | Q48: =IF('MaryFran Anderson'!$B8="","","MaryFran Anderson") -> MaryFran Anderson | R48: =IF(OR($B48="",$I48="Complete",$L48=""),0,IF($L48<TODAY(),1,0)) -> 0 | S48: =IF(OR($B48="",$I48="Complete",$L48=""),0,IF(AND($L48>=TODAY(),$L48<=TODAY()+7),1,0)) -> 0 | T48: =IF(OR($B48="",$L48=""),"",$L48-TODAY()) -> 30 | U48: =IF($B48="","",IF($I48="Complete",1,IF($J48="",0,$J48))) -> 0.1 | V48: =IF($B48="",0,IF($N48="",0,1)) -> 1 | W48: =IF($B48="",0,1) -> 1
A49: =IF('MaryFran Anderson'!$B9="","",'MaryFran Anderson'!$A9) -> MFA-005 | B49: =IF('MaryFran Anderson'!$B9="","",'MaryFran Anderson'!$B9) -> P3-1 | C49: =IF('MaryFran Anderson'!$B9="","",'MaryFran Anderson'!$C9) -> 3 – Broker Channel | D49: =IF('MaryFran Anderson'!$B9="","",'MaryFran Anderson'!$D9) -> Assign MaryFran as broker channel owner | E49: =IF('MaryFran Anderson'!$B9="","",'MaryFran Anderson'!$E9) -> MaryFran Anderson | F49: =IF('MaryFran Anderson'!$B9="","",'MaryFran Anderson'!$F9) -> Owner | G49: =IF('MaryFran Anderson'!$B9="","",'MaryFran Anderson'!$G9) -> In-Person Broker D-Day Event Planning | H49: =IF('MaryFran Anderson'!$B9="","",'MaryFran Anderson'!$H9) -> Medium | I49: =IF('MaryFran Anderson'!$B9="","",'MaryFran Anderson'!$I9) -> Not Started | J49: =IF('MaryFran Anderson'!$B9="","",'MaryFran Anderson'!$J9) -> 0 | K49: =IF('MaryFran Anderson'!$B9="","",'MaryFran Anderson'!$K9) -> 46188 | L49: =IF('MaryFran Anderson'!$B9="","",'MaryFran Anderson'!$L9) -> 46249 | M49: =IF('MaryFran Anderson'!$B9="","",'MaryFran Anderson'!$M9) -> 0 | N49: =IF('MaryFran Anderson'!$B9="","",'MaryFran Anderson'!$N9) -> 0 | O49: =IF('MaryFran Anderson'!$B9="","",'MaryFran Anderson'!$O9) -> Not started | P49: =IF('MaryFran Anderson'!$B9="","",'MaryFran Anderson'!$P9) -> Draft event concept & budget | Q49: =IF('MaryFran Anderson'!$B9="","","MaryFran Anderson") -> MaryFran Anderson | R49: =IF(OR($B49="",$I49="Complete",$L49=""),0,IF($L49<TODAY(),1,0)) -> 0 | S49: =IF(OR($B49="",$I49="Complete",$L49=""),0,IF(AND($L49>=TODAY(),$L49<=TODAY()+7),1,0)) -> 0 | T49: =IF(OR($B49="",$L49=""),"",$L49-TODAY()) -> 79 | U49: =IF($B49="","",IF($I49="Complete",1,IF($J49="",0,$J49))) -> 0 | V49: =IF($B49="",0,IF($N49="",0,1)) -> 0 | W49: =IF($B49="",0,1) -> 1
A50: =IF('MaryFran Anderson'!$B10="","",'MaryFran Anderson'!$A10) -> MFA-006 | B50: =IF('MaryFran Anderson'!$B10="","",'MaryFran Anderson'!$B10) -> P3-4 | C50: =IF('MaryFran Anderson'!$B10="","",'MaryFran Anderson'!$C10) -> 3 – Broker Channel | D50: =IF('MaryFran Anderson'!$B10="","",'MaryFran Anderson'!$D10) -> Enforce speed-to-lead SLAs | E50: =IF('MaryFran Anderson'!$B10="","",'MaryFran Anderson'!$E10) -> MaryFran Anderson | F50: =IF('MaryFran Anderson'!$B10="","",'MaryFran Anderson'!$F10) -> Owner | G50: =IF('MaryFran Anderson'!$B10="","",'MaryFran Anderson'!$G10) -> Enforce speed-to-lead SLAs | H50: =IF('MaryFran Anderson'!$B10="","",'MaryFran Anderson'!$H10) -> High | I50: =IF('MaryFran Anderson'!$B10="","",'MaryFran Anderson'!$I10) -> In Progress | J50: =IF('MaryFran Anderson'!$B10="","",'MaryFran Anderson'!$J10) -> 0.2 | K50: =IF('MaryFran Anderson'!$B10="","",'MaryFran Anderson'!$K10) -> 46162 | L50: =IF('MaryFran Anderson'!$B10="","",'MaryFran Anderson'!$L10) -> 46193 | M50: =IF('MaryFran Anderson'!$B10="","",'MaryFran Anderson'!$M10) -> 0 | N50: =IF('MaryFran Anderson'!$B10="","",'MaryFran Anderson'!$N10) -> 0 | O50: =IF('MaryFran Anderson'!$B10="","",'MaryFran Anderson'!$O10) -> Defining SLA thresholds | P50: =IF('MaryFran Anderson'!$B10="","",'MaryFran Anderson'!$P10) -> Publish SLA standard to broker team | Q50: =IF('MaryFran Anderson'!$B10="","","MaryFran Anderson") -> MaryFran Anderson | R50: =IF(OR($B50="",$I50="Complete",$L50=""),0,IF($L50<TODAY(),1,0)) -> 0 | S50: =IF(OR($B50="",$I50="Complete",$L50=""),0,IF(AND($L50>=TODAY(),$L50<=TODAY()+7),1,0)) -> 0 | T50: =IF(OR($B50="",$L50=""),"",$L50-TODAY()) -> 23 | U50: =IF($B50="","",IF($I50="Complete",1,IF($J50="",0,$J50))) -> 0.2 | V50: =IF($B50="",0,IF($N50="",0,1)) -> 0 | W50: =IF($B50="",0,1) -> 1
A51: =IF('MaryFran Anderson'!$B11="","",'MaryFran Anderson'!$A11) | B51: =IF('MaryFran Anderson'!$B11="","",'MaryFran Anderson'!$B11) | C51: =IF('MaryFran Anderson'!$B11="","",'MaryFran Anderson'!$C11) | D51: =IF('MaryFran Anderson'!$B11="","",'MaryFran Anderson'!$D11) | E51: =IF('MaryFran Anderson'!$B11="","",'MaryFran Anderson'!$E11) | F51: =IF('MaryFran Anderson'!$B11="","",'MaryFran Anderson'!$F11) | G51: =IF('MaryFran Anderson'!$B11="","",'MaryFran Anderson'!$G11) | H51: =IF('MaryFran Anderson'!$B11="","",'MaryFran Anderson'!$H11) | I51: =IF('MaryFran Anderson'!$B11="","",'MaryFran Anderson'!$I11) | J51: =IF('MaryFran Anderson'!$B11="","",'MaryFran Anderson'!$J11) | K51: =IF('MaryFran Anderson'!$B11="","",'MaryFran Anderson'!$K11) | L51: =IF('MaryFran Anderson'!$B11="","",'MaryFran Anderson'!$L11) | M51: =IF('MaryFran Anderson'!$B11="","",'MaryFran Anderson'!$M11) | N51: =IF('MaryFran Anderson'!$B11="","",'MaryFran Anderson'!$N11) | O51: =IF('MaryFran Anderson'!$B11="","",'MaryFran Anderson'!$O11) | P51: =IF('MaryFran Anderson'!$B11="","",'MaryFran Anderson'!$P11) | Q51: =IF('MaryFran Anderson'!$B11="","","MaryFran Anderson") | R51: =IF(OR($B51="",$I51="Complete",$L51=""),0,IF($L51<TODAY(),1,0)) -> 0 | S51: =IF(OR($B51="",$I51="Complete",$L51=""),0,IF(AND($L51>=TODAY(),$L51<=TODAY()+7),1,0)) -> 0 | T51: =IF(OR($B51="",$L51=""),"",$L51-TODAY()) | U51: =IF($B51="","",IF($I51="Complete",1,IF($J51="",0,$J51))) | V51: =IF($B51="",0,IF($N51="",0,1)) -> 0 | W51: =IF($B51="",0,1) -> 0
A52: =IF('MaryFran Anderson'!$B12="","",'MaryFran Anderson'!$A12) | B52: =IF('MaryFran Anderson'!$B12="","",'MaryFran Anderson'!$B12) | C52: =IF('MaryFran Anderson'!$B12="","",'MaryFran Anderson'!$C12) | D52: =IF('MaryFran Anderson'!$B12="","",'MaryFran Anderson'!$D12) | E52: =IF('MaryFran Anderson'!$B12="","",'MaryFran Anderson'!$E12) | F52: =IF('MaryFran Anderson'!$B12="","",'MaryFran Anderson'!$F12) | G52: =IF('MaryFran Anderson'!$B12="","",'MaryFran Anderson'!$G12) | H52: =IF('MaryFran Anderson'!$B12="","",'MaryFran Anderson'!$H12) | I52: =IF('MaryFran Anderson'!$B12="","",'MaryFran Anderson'!$I12) | J52: =IF('MaryFran Anderson'!$B12="","",'MaryFran Anderson'!$J12) | K52: =IF('MaryFran Anderson'!$B12="","",'MaryFran Anderson'!$K12) | L52: =IF('MaryFran Anderson'!$B12="","",'MaryFran Anderson'!$L12) | M52: =IF('MaryFran Anderson'!$B12="","",'MaryFran Anderson'!$M12) | N52: =IF('MaryFran Anderson'!$B12="","",'MaryFran Anderson'!$N12) | O52: =IF('MaryFran Anderson'!$B12="","",'MaryFran Anderson'!$O12) | P52: =IF('MaryFran Anderson'!$B12="","",'MaryFran Anderson'!$P12) | Q52: =IF('MaryFran Anderson'!$B12="","","MaryFran Anderson") | R52: =IF(OR($B52="",$I52="Complete",$L52=""),0,IF($L52<TODAY(),1,0)) -> 0 | S52: =IF(OR($B52="",$I52="Complete",$L52=""),0,IF(AND($L52>=TODAY(),$L52<=TODAY()+7),1,0)) -> 0 | T52: =IF(OR($B52="",$L52=""),"",$L52-TODAY()) | U52: =IF($B52="","",IF($I52="Complete",1,IF($J52="",0,$J52))) | V52: =IF($B52="",0,IF($N52="",0,1)) -> 0 | W52: =IF($B52="",0,1) -> 0
A53: =IF('MaryFran Anderson'!$B13="","",'MaryFran Anderson'!$A13) | B53: =IF('MaryFran Anderson'!$B13="","",'MaryFran Anderson'!$B13) | C53: =IF('MaryFran Anderson'!$B13="","",'MaryFran Anderson'!$C13) | D53: =IF('MaryFran Anderson'!$B13="","",'MaryFran Anderson'!$D13) | E53: =IF('MaryFran Anderson'!$B13="","",'MaryFran Anderson'!$E13) | F53: =IF('MaryFran Anderson'!$B13="","",'MaryFran Anderson'!$F13) | G53: =IF('MaryFran Anderson'!$B13="","",'MaryFran Anderson'!$G13) | H53: =IF('MaryFran Anderson'!$B13="","",'MaryFran Anderson'!$H13) | I53: =IF('MaryFran Anderson'!$B13="","",'MaryFran Anderson'!$I13) | J53: =IF('MaryFran Anderson'!$B13="","",'MaryFran Anderson'!$J13) | K53: =IF('MaryFran Anderson'!$B13="","",'MaryFran Anderson'!$K13) | L53: =IF('MaryFran Anderson'!$B13="","",'MaryFran Anderson'!$L13) | M53: =IF('MaryFran Anderson'!$B13="","",'MaryFran Anderson'!$M13) | N53: =IF('MaryFran Anderson'!$B13="","",'MaryFran Anderson'!$N13) | O53: =IF('MaryFran Anderson'!$B13="","",'MaryFran Anderson'!$O13) | P53: =IF('MaryFran Anderson'!$B13="","",'MaryFran Anderson'!$P13) | Q53: =IF('MaryFran Anderson'!$B13="","","MaryFran Anderson") | R53: =IF(OR($B53="",$I53="Complete",$L53=""),0,IF($L53<TODAY(),1,0)) -> 0 | S53: =IF(OR($B53="",$I53="Complete",$L53=""),0,IF(AND($L53>=TODAY(),$L53<=TODAY()+7),1,0)) -> 0 | T53: =IF(OR($B53="",$L53=""),"",$L53-TODAY()) | U53: =IF($B53="","",IF($I53="Complete",1,IF($J53="",0,$J53))) | V53: =IF($B53="",0,IF($N53="",0,1)) -> 0 | W53: =IF($B53="",0,1) -> 0
A54: =IF('MaryFran Anderson'!$B14="","",'MaryFran Anderson'!$A14) | B54: =IF('MaryFran Anderson'!$B14="","",'MaryFran Anderson'!$B14) | C54: =IF('MaryFran Anderson'!$B14="","",'MaryFran Anderson'!$C14) | D54: =IF('MaryFran Anderson'!$B14="","",'MaryFran Anderson'!$D14) | E54: =IF('MaryFran Anderson'!$B14="","",'MaryFran Anderson'!$E14) | F54: =IF('MaryFran Anderson'!$B14="","",'MaryFran Anderson'!$F14) | G54: =IF('MaryFran Anderson'!$B14="","",'MaryFran Anderson'!$G14) | H54: =IF('MaryFran Anderson'!$B14="","",'MaryFran Anderson'!$H14) | I54: =IF('MaryFran Anderson'!$B14="","",'MaryFran Anderson'!$I14) | J54: =IF('MaryFran Anderson'!$B14="","",'MaryFran Anderson'!$J14) | K54: =IF('MaryFran Anderson'!$B14="","",'MaryFran Anderson'!$K14) | L54: =IF('MaryFran Anderson'!$B14="","",'MaryFran Anderson'!$L14) | M54: =IF('MaryFran Anderson'!$B14="","",'MaryFran Anderson'!$M14) | N54: =IF('MaryFran Anderson'!$B14="","",'MaryFran Anderson'!$N14) | O54: =IF('MaryFran Anderson'!$B14="","",'MaryFran Anderson'!$O14) | P54: =IF('MaryFran Anderson'!$B14="","",'MaryFran Anderson'!$P14) | Q54: =IF('MaryFran Anderson'!$B14="","","MaryFran Anderson") | R54: =IF(OR($B54="",$I54="Complete",$L54=""),0,IF($L54<TODAY(),1,0)) -> 0 | S54: =IF(OR($B54="",$I54="Complete",$L54=""),0,IF(AND($L54>=TODAY(),$L54<=TODAY()+7),1,0)) -> 0 | T54: =IF(OR($B54="",$L54=""),"",$L54-TODAY()) | U54: =IF($B54="","",IF($I54="Complete",1,IF($J54="",0,$J54))) | V54: =IF($B54="",0,IF($N54="",0,1)) -> 0 | W54: =IF($B54="",0,1) -> 0
A55: =IF('MaryFran Anderson'!$B15="","",'MaryFran Anderson'!$A15) | B55: =IF('MaryFran Anderson'!$B15="","",'MaryFran Anderson'!$B15) | C55: =IF('MaryFran Anderson'!$B15="","",'MaryFran Anderson'!$C15) | D55: =IF('MaryFran Anderson'!$B15="","",'MaryFran Anderson'!$D15) | E55: =IF('MaryFran Anderson'!$B15="","",'MaryFran Anderson'!$E15) | F55: =IF('MaryFran Anderson'!$B15="","",'MaryFran Anderson'!$F15) | G55: =IF('MaryFran Anderson'!$B15="","",'MaryFran Anderson'!$G15) | H55: =IF('MaryFran Anderson'!$B15="","",'MaryFran Anderson'!$H15) | I55: =IF('MaryFran Anderson'!$B15="","",'MaryFran Anderson'!$I15) | J55: =IF('MaryFran Anderson'!$B15="","",'MaryFran Anderson'!$J15) | K55: =IF('MaryFran Anderson'!$B15="","",'MaryFran Anderson'!$K15) | L55: =IF('MaryFran Anderson'!$B15="","",'MaryFran Anderson'!$L15) | M55: =IF('MaryFran Anderson'!$B15="","",'MaryFran Anderson'!$M15) | N55: =IF('MaryFran Anderson'!$B15="","",'MaryFran Anderson'!$N15) | O55: =IF('MaryFran Anderson'!$B15="","",'MaryFran Anderson'!$O15) | P55: =IF('MaryFran Anderson'!$B15="","",'MaryFran Anderson'!$P15) | Q55: =IF('MaryFran Anderson'!$B15="","","MaryFran Anderson") | R55: =IF(OR($B55="",$I55="Complete",$L55=""),0,IF($L55<TODAY(),1,0)) -> 0 | S55: =IF(OR($B55="",$I55="Complete",$L55=""),0,IF(AND($L55>=TODAY(),$L55<=TODAY()+7),1,0)) -> 0 | T55: =IF(OR($B55="",$L55=""),"",$L55-TODAY()) | U55: =IF($B55="","",IF($I55="Complete",1,IF($J55="",0,$J55))) | V55: =IF($B55="",0,IF($N55="",0,1)) -> 0 | W55: =IF($B55="",0,1) -> 0
A56: =IF('MaryFran Anderson'!$B16="","",'MaryFran Anderson'!$A16) | B56: =IF('MaryFran Anderson'!$B16="","",'MaryFran Anderson'!$B16) | C56: =IF('MaryFran Anderson'!$B16="","",'MaryFran Anderson'!$C16) | D56: =IF('MaryFran Anderson'!$B16="","",'MaryFran Anderson'!$D16) | E56: =IF('MaryFran Anderson'!$B16="","",'MaryFran Anderson'!$E16) | F56: =IF('MaryFran Anderson'!$B16="","",'MaryFran Anderson'!$F16) | G56: =IF('MaryFran Anderson'!$B16="","",'MaryFran Anderson'!$G16) | H56: =IF('MaryFran Anderson'!$B16="","",'MaryFran Anderson'!$H16) | I56: =IF('MaryFran Anderson'!$B16="","",'MaryFran Anderson'!$I16) | J56: =IF('MaryFran Anderson'!$B16="","",'MaryFran Anderson'!$J16) | K56: =IF('MaryFran Anderson'!$B16="","",'MaryFran Anderson'!$K16) | L56: =IF('MaryFran Anderson'!$B16="","",'MaryFran Anderson'!$L16) | M56: =IF('MaryFran Anderson'!$B16="","",'MaryFran Anderson'!$M16) | N56: =IF('MaryFran Anderson'!$B16="","",'MaryFran Anderson'!$N16) | O56: =IF('MaryFran Anderson'!$B16="","",'MaryFran Anderson'!$O16) | P56: =IF('MaryFran Anderson'!$B16="","",'MaryFran Anderson'!$P16) | Q56: =IF('MaryFran Anderson'!$B16="","","MaryFran Anderson") | R56: =IF(OR($B56="",$I56="Complete",$L56=""),0,IF($L56<TODAY(),1,0)) -> 0 | S56: =IF(OR($B56="",$I56="Complete",$L56=""),0,IF(AND($L56>=TODAY(),$L56<=TODAY()+7),1,0)) -> 0 | T56: =IF(OR($B56="",$L56=""),"",$L56-TODAY()) | U56: =IF($B56="","",IF($I56="Complete",1,IF($J56="",0,$J56))) | V56: =IF($B56="",0,IF($N56="",0,1)) -> 0 | W56: =IF($B56="",0,1) -> 0
... A84: =IF('MaryFran Anderson'!$B44="","",'MaryFran Anderson'!$A44) | B84: =IF('MaryFran Anderson'!$B44="","",'MaryFran Anderson'!$B44) | C84: =IF('MaryFran Anderson'!$B44="","",'MaryFran Anderson'!$C44) | D84: =IF('MaryFran Anderson'!$B44="","",'MaryFran Anderson'!$D44) | E84: =IF('MaryFran Anderson'!$B44="","",'MaryFran Anderson'!$E44) | F84: =IF('MaryFran Anderson'!$B44="","",'MaryFran Anderson'!$F44) | G84: =IF('MaryFran Anderson'!$B44="","",'MaryFran Anderson'!$G44) | H84: =IF('MaryFran Anderson'!$B44="","",'MaryFran Anderson'!$H44) | I84: =IF('MaryFran Anderson'!$B44="","",'MaryFran Anderson'!$I44) | J84: =IF('MaryFran Anderson'!$B44="","",'MaryFran Anderson'!$J44) | K84: =IF('MaryFran Anderson'!$B44="","",'MaryFran Anderson'!$K44) | L84: =IF('MaryFran Anderson'!$B44="","",'MaryFran Anderson'!$L44) | M84: =IF('MaryFran Anderson'!$B44="","",'MaryFran Anderson'!$M44) | N84: =IF('MaryFran Anderson'!$B44="","",'MaryFran Anderson'!$N44) | O84: =IF('MaryFran Anderson'!$B44="","",'MaryFran Anderson'!$O44) | P84: =IF('MaryFran Anderson'!$B44="","",'MaryFran Anderson'!$P44) | Q84: =IF('MaryFran Anderson'!$B44="","","MaryFran Anderson") | R84: =IF(OR($B84="",$I84="Complete",$L84=""),0,IF($L84<TODAY(),1,0)) -> 0 | S84: =IF(OR($B84="",$I84="Complete",$L84=""),0,IF(AND($L84>=TODAY(),$L84<=TODAY()+7),1,0)) -> 0 | T84: =IF(OR($B84="",$L84=""),"",$L84-TODAY()) | U84: =IF($B84="","",IF($I84="Complete",1,IF($J84="",0,$J84))) | V84: =IF($B84="",0,IF($N84="",0,1)) -> 0 | W84: =IF($B84="",0,1) -> 0
A85: =IF('Shane Mattingly'!$B5="","",'Shane Mattingly'!$A5) -> SM-001 | B85: =IF('Shane Mattingly'!$B5="","",'Shane Mattingly'!$B5) -> P1-1 | C85: =IF('Shane Mattingly'!$B5="","",'Shane Mattingly'!$C5) -> 1 – Unified Development System | D85: =IF('Shane Mattingly'!$B5="","",'Shane Mattingly'!$D5) -> Implement standardized Mutual Evaluation Process (MEP) across all brands | E85: =IF('Shane Mattingly'!$B5="","",'Shane Mattingly'!$E5) -> Shane Mattingly | F85: =IF('Shane Mattingly'!$B5="","",'Shane Mattingly'!$F5) -> Contributor | G85: =IF('Shane Mattingly'!$B5="","",'Shane Mattingly'!$G5) -> Training Section 1-3 in Fran Dev 101 | H85: =IF('Shane Mattingly'!$B5="","",'Shane Mattingly'!$H5) -> Medium | I85: =IF('Shane Mattingly'!$B5="","",'Shane Mattingly'!$I5) -> In Progress | J85: =IF('Shane Mattingly'!$B5="","",'Shane Mattingly'!$J5) -> 0.5 | K85: =IF('Shane Mattingly'!$B5="","",'Shane Mattingly'!$K5) -> 46162 | L85: =IF('Shane Mattingly'!$B5="","",'Shane Mattingly'!$L5) -> 46186 | M85: =IF('Shane Mattingly'!$B5="","",'Shane Mattingly'!$M5) -> 0 | N85: =IF('Shane Mattingly'!$B5="","",'Shane Mattingly'!$N5) -> 0 | O85: =IF('Shane Mattingly'!$B5="","",'Shane Mattingly'!$O5) -> Assigned 5/20 | P85: =IF('Shane Mattingly'!$B5="","",'Shane Mattingly'!$P5) -> Complete sections 2-3 | Q85: =IF('Shane Mattingly'!$B5="","","Shane Mattingly") -> Shane Mattingly | R85: =IF(OR($B85="",$I85="Complete",$L85=""),0,IF($L85<TODAY(),1,0)) -> 0 | S85: =IF(OR($B85="",$I85="Complete",$L85=""),0,IF(AND($L85>=TODAY(),$L85<=TODAY()+7),1,0)) -> 0 | T85: =IF(OR($B85="",$L85=""),"",$L85-TODAY()) -> 16 | U85: =IF($B85="","",IF($I85="Complete",1,IF($J85="",0,$J85))) -> 0.5 | V85: =IF($B85="",0,IF($N85="",0,1)) -> 0 | W85: =IF($B85="",0,1) -> 1
A86: =IF('Shane Mattingly'!$B6="","",'Shane Mattingly'!$A6) -> SM-002 | B86: =IF('Shane Mattingly'!$B6="","",'Shane Mattingly'!$B6) -> P1-2 | C86: =IF('Shane Mattingly'!$B6="","",'Shane Mattingly'!$C6) -> 1 – Unified Development System | D86: =IF('Shane Mattingly'!$B6="","",'Shane Mattingly'!$D6) -> Standardize pipeline stages, definitions, and reporting in CRM | E86: =IF('Shane Mattingly'!$B6="","",'Shane Mattingly'!$E6) -> Shane Mattingly | F86: =IF('Shane Mattingly'!$B6="","",'Shane Mattingly'!$F6) -> Owner | G86: =IF('Shane Mattingly'!$B6="","",'Shane Mattingly'!$G6) -> Standardize pipeline stages, definitions & reporting in CRM | H86: =IF('Shane Mattingly'!$B6="","",'Shane Mattingly'!$H6) -> Critical | I86: =IF('Shane Mattingly'!$B6="","",'Shane Mattingly'!$I6) -> In Progress | J86: =IF('Shane Mattingly'!$B6="","",'Shane Mattingly'!$J6) -> 0.5 | K86: =IF('Shane Mattingly'!$B6="","",'Shane Mattingly'!$K6) -> 46143 | L86: =IF('Shane Mattingly'!$B6="","",'Shane Mattingly'!$L6) -> 46168 | M86: =IF('Shane Mattingly'!$B6="","",'Shane Mattingly'!$M6) -> 0 | N86: =IF('Shane Mattingly'!$B6="","",'Shane Mattingly'!$N6) -> 0 | O86: =IF('Shane Mattingly'!$B6="","",'Shane Mattingly'!$O6) -> Draft stage definitions circulated | P86: =IF('Shane Mattingly'!$B6="","",'Shane Mattingly'!$P6) -> Finalize stage definitions & lock CRM config | Q86: =IF('Shane Mattingly'!$B6="","","Shane Mattingly") -> Shane Mattingly | R86: =IF(OR($B86="",$I86="Complete",$L86=""),0,IF($L86<TODAY(),1,0)) -> 1 | S86: =IF(OR($B86="",$I86="Complete",$L86=""),0,IF(AND($L86>=TODAY(),$L86<=TODAY()+7),1,0)) -> 0 | T86: =IF(OR($B86="",$L86=""),"",$L86-TODAY()) -> -2 | U86: =IF($B86="","",IF($I86="Complete",1,IF($J86="",0,$J86))) -> 0.5 | V86: =IF($B86="",0,IF($N86="",0,1)) -> 0 | W86: =IF($B86="",0,1) -> 1
A87: =IF('Shane Mattingly'!$B7="","",'Shane Mattingly'!$A7) -> SM-003 | B87: =IF('Shane Mattingly'!$B7="","",'Shane Mattingly'!$B7) -> P3-2 | C87: =IF('Shane Mattingly'!$B7="","",'Shane Mattingly'!$C7) -> 3 – Broker Channel | D87: =IF('Shane Mattingly'!$B7="","",'Shane Mattingly'!$D7) -> Route 100% of broker leads through CRM for centralized intake and visibility. | E87: =IF('Shane Mattingly'!$B7="","",'Shane Mattingly'!$E7) -> Shane Mattingly | F87: =IF('Shane Mattingly'!$B7="","",'Shane Mattingly'!$F7) -> Owner | G87: =IF('Shane Mattingly'!$B7="","",'Shane Mattingly'!$G7) -> Route 100% of broker leads through CRM | H87: =IF('Shane Mattingly'!$B7="","",'Shane Mattingly'!$H7) -> High | I87: =IF('Shane Mattingly'!$B7="","",'Shane Mattingly'!$I7) -> In Progress | J87: =IF('Shane Mattingly'!$B7="","",'Shane Mattingly'!$J7) -> 0.4 | K87: =IF('Shane Mattingly'!$B7="","",'Shane Mattingly'!$K7) -> 46147 | L87: =IF('Shane Mattingly'!$B7="","",'Shane Mattingly'!$L7) -> 46193 | M87: =IF('Shane Mattingly'!$B7="","",'Shane Mattingly'!$M7) -> Broker portal update (MFA) | N87: =IF('Shane Mattingly'!$B7="","",'Shane Mattingly'!$N7) -> 0 | O87: =IF('Shane Mattingly'!$B7="","",'Shane Mattingly'!$O7) -> Building intake routing | P87: =IF('Shane Mattingly'!$B7="","",'Shane Mattingly'!$P7) -> Test routing with sample broker leads | Q87: =IF('Shane Mattingly'!$B7="","","Shane Mattingly") -> Shane Mattingly | R87: =IF(OR($B87="",$I87="Complete",$L87=""),0,IF($L87<TODAY(),1,0)) -> 0 | S87: =IF(OR($B87="",$I87="Complete",$L87=""),0,IF(AND($L87>=TODAY(),$L87<=TODAY()+7),1,0)) -> 0 | T87: =IF(OR($B87="",$L87=""),"",$L87-TODAY()) -> 23 | U87: =IF($B87="","",IF($I87="Complete",1,IF($J87="",0,$J87))) -> 0.4 | V87: =IF($B87="",0,IF($N87="",0,1)) -> 0 | W87: =IF($B87="",0,1) -> 1
A88: =IF('Shane Mattingly'!$B8="","",'Shane Mattingly'!$A8) -> SM-004 | B88: =IF('Shane Mattingly'!$B8="","",'Shane Mattingly'!$B8) -> P5-4 | C88: =IF('Shane Mattingly'!$B8="","",'Shane Mattingly'!$C8) -> 5 – Operational Infrastructure | D88: =IF('Shane Mattingly'!$B8="","",'Shane Mattingly'!$D8) -> Build centralized KPI dashboard and reporting visibility | E88: =IF('Shane Mattingly'!$B8="","",'Shane Mattingly'!$E8) -> Shane Mattingly | F88: =IF('Shane Mattingly'!$B8="","",'Shane Mattingly'!$F8) -> Owner | G88: =IF('Shane Mattingly'!$B8="","",'Shane Mattingly'!$G8) -> Build centralized KPI dashboard & reporting visibility | H88: =IF('Shane Mattingly'!$B8="","",'Shane Mattingly'!$H8) -> Critical | I88: =IF('Shane Mattingly'!$B8="","",'Shane Mattingly'!$I8) -> Not Started | J88: =IF('Shane Mattingly'!$B8="","",'Shane Mattingly'!$J8) -> 0 | K88: =IF('Shane Mattingly'!$B8="","",'Shane Mattingly'!$K8) -> 46174 | L88: =IF('Shane Mattingly'!$B8="","",'Shane Mattingly'!$L8) -> 46221 | M88: =IF('Shane Mattingly'!$B8="","",'Shane Mattingly'!$M8) -> Pipeline stage standardization (P1-2) | N88: =IF('Shane Mattingly'!$B8="","",'Shane Mattingly'!$N8) -> 0 | O88: =IF('Shane Mattingly'!$B8="","",'Shane Mattingly'!$O8) -> Pending stage standardization | P88: =IF('Shane Mattingly'!$B8="","",'Shane Mattingly'!$P8) -> Spec dashboard KPIs | Q88: =IF('Shane Mattingly'!$B8="","","Shane Mattingly") -> Shane Mattingly | R88: =IF(OR($B88="",$I88="Complete",$L88=""),0,IF($L88<TODAY(),1,0)) -> 0 | S88: =IF(OR($B88="",$I88="Complete",$L88=""),0,IF(AND($L88>=TODAY(),$L88<=TODAY()+7),1,0)) -> 0 | T88: =IF(OR($B88="",$L88=""),"",$L88-TODAY()) -> 51 | U88: =IF($B88="","",IF($I88="Complete",1,IF($J88="",0,$J88))) -> 0 | V88: =IF($B88="",0,IF($N88="",0,1)) -> 0 | W88: =IF($B88="",0,1) -> 1
A89: =IF('Shane Mattingly'!$B9="","",'Shane Mattingly'!$A9) -> SM-005 | B89: =IF('Shane Mattingly'!$B9="","",'Shane Mattingly'!$B9) -> P7-1 | C89: =IF('Shane Mattingly'!$B9="","",'Shane Mattingly'!$C9) -> 7 – Operating Rhythm | D89: =IF('Shane Mattingly'!$B9="","",'Shane Mattingly'!$D9) -> Implement weekly KPI scorecards by brand, developer, and source | E89: =IF('Shane Mattingly'!$B9="","",'Shane Mattingly'!$E9) -> Shane Mattingly | F89: =IF('Shane Mattingly'!$B9="","",'Shane Mattingly'!$F9) -> Owner | G89: =IF('Shane Mattingly'!$B9="","",'Shane Mattingly'!$G9) -> Implement weekly KPI scorecards by brand, developer & source | H89: =IF('Shane Mattingly'!$B9="","",'Shane Mattingly'!$H9) -> High | I89: =IF('Shane Mattingly'!$B9="","",'Shane Mattingly'!$I9) -> In Progress | J89: =IF('Shane Mattingly'!$B9="","",'Shane Mattingly'!$J9) -> 0.3 | K89: =IF('Shane Mattingly'!$B9="","",'Shane Mattingly'!$K9) -> 46152 | L89: =IF('Shane Mattingly'!$B9="","",'Shane Mattingly'!$L9) -> 46200 | M89: =IF('Shane Mattingly'!$B9="","",'Shane Mattingly'!$M9) -> 0 | N89: =IF('Shane Mattingly'!$B9="","",'Shane Mattingly'!$N9) -> 0 | O89: =IF('Shane Mattingly'!$B9="","",'Shane Mattingly'!$O9) -> Scorecard v1 drafted | P89: =IF('Shane Mattingly'!$B9="","",'Shane Mattingly'!$P9) -> Automate weekly refresh | Q89: =IF('Shane Mattingly'!$B9="","","Shane Mattingly") -> Shane Mattingly | R89: =IF(OR($B89="",$I89="Complete",$L89=""),0,IF($L89<TODAY(),1,0)) -> 0 | S89: =IF(OR($B89="",$I89="Complete",$L89=""),0,IF(AND($L89>=TODAY(),$L89<=TODAY()+7),1,0)) -> 0 | T89: =IF(OR($B89="",$L89=""),"",$L89-TODAY()) -> 30 | U89: =IF($B89="","",IF($I89="Complete",1,IF($J89="",0,$J89))) -> 0.3 | V89: =IF($B89="",0,IF($N89="",0,1)) -> 0 | W89: =IF($B89="",0,1) -> 1
A90: =IF('Shane Mattingly'!$B10="","",'Shane Mattingly'!$A10) -> SM-006 | B90: =IF('Shane Mattingly'!$B10="","",'Shane Mattingly'!$B10) -> P7-3 | C90: =IF('Shane Mattingly'!$B10="","",'Shane Mattingly'!$C10) -> 7 – Operating Rhythm | D90: =IF('Shane Mattingly'!$B10="","",'Shane Mattingly'!$D10) -> Standardize forecasting methodology | E90: =IF('Shane Mattingly'!$B10="","",'Shane Mattingly'!$E10) -> Shane Mattingly | F90: =IF('Shane Mattingly'!$B10="","",'Shane Mattingly'!$F10) -> Owner | G90: =IF('Shane Mattingly'!$B10="","",'Shane Mattingly'!$G10) -> Standardize forecasting methodology | H90: =IF('Shane Mattingly'!$B10="","",'Shane Mattingly'!$H10) -> High | I90: =IF('Shane Mattingly'!$B10="","",'Shane Mattingly'!$I10) -> In Progress | J90: =IF('Shane Mattingly'!$B10="","",'Shane Mattingly'!$J10) -> 0.2 | K90: =IF('Shane Mattingly'!$B10="","",'Shane Mattingly'!$K10) -> 46157 | L90: =IF('Shane Mattingly'!$B10="","",'Shane Mattingly'!$L10) -> 46206 | M90: =IF('Shane Mattingly'!$B10="","",'Shane Mattingly'!$M10) -> 0 | N90: =IF('Shane Mattingly'!$B10="","",'Shane Mattingly'!$N10) -> 0 | O90: =IF('Shane Mattingly'!$B10="","",'Shane Mattingly'!$O10) -> Reviewing brand forecast inputs | P90: =IF('Shane Mattingly'!$B10="","",'Shane Mattingly'!$P10) -> Align methodology across brands | Q90: =IF('Shane Mattingly'!$B10="","","Shane Mattingly") -> Shane Mattingly | R90: =IF(OR($B90="",$I90="Complete",$L90=""),0,IF($L90<TODAY(),1,0)) -> 0 | S90: =IF(OR($B90="",$I90="Complete",$L90=""),0,IF(AND($L90>=TODAY(),$L90<=TODAY()+7),1,0)) -> 0 | T90: =IF(OR($B90="",$L90=""),"",$L90-TODAY()) -> 36 | U90: =IF($B90="","",IF($I90="Complete",1,IF($J90="",0,$J90))) -> 0.2 | V90: =IF($B90="",0,IF($N90="",0,1)) -> 0 | W90: =IF($B90="",0,1) -> 1
A91: =IF('Shane Mattingly'!$B11="","",'Shane Mattingly'!$A11) -> SM-007 | B91: =IF('Shane Mattingly'!$B11="","",'Shane Mattingly'!$B11) -> P3-3 | C91: =IF('Shane Mattingly'!$B11="","",'Shane Mattingly'!$C11) -> 3 – Broker Channel | D91: =IF('Shane Mattingly'!$B11="","",'Shane Mattingly'!$D11) -> Implement rules-based lead distribution | E91: =IF('Shane Mattingly'!$B11="","",'Shane Mattingly'!$E11) -> Shane Mattingly | F91: =IF('Shane Mattingly'!$B11="","",'Shane Mattingly'!$F11) -> Owner | G91: =IF('Shane Mattingly'!$B11="","",'Shane Mattingly'!$G11) -> Implement rules-based lead distribution | H91: =IF('Shane Mattingly'!$B11="","",'Shane Mattingly'!$H11) -> Medium | I91: =IF('Shane Mattingly'!$B11="","",'Shane Mattingly'!$I11) -> Not Started | J91: =IF('Shane Mattingly'!$B11="","",'Shane Mattingly'!$J11) -> 0 | K91: =IF('Shane Mattingly'!$B11="","",'Shane Mattingly'!$K11) -> 46183 | L91: =IF('Shane Mattingly'!$B11="","",'Shane Mattingly'!$L11) -> 46228 | M91: =IF('Shane Mattingly'!$B11="","",'Shane Mattingly'!$M11) -> 0 | N91: =IF('Shane Mattingly'!$B11="","",'Shane Mattingly'!$N11) -> 0 | O91: =IF('Shane Mattingly'!$B11="","",'Shane Mattingly'!$O11) -> Not started | P91: =IF('Shane Mattingly'!$B11="","",'Shane Mattingly'!$P11) -> Define distribution rules | Q91: =IF('Shane Mattingly'!$B11="","","Shane Mattingly") -> Shane Mattingly | R91: =IF(OR($B91="",$I91="Complete",$L91=""),0,IF($L91<TODAY(),1,0)) -> 0 | S91: =IF(OR($B91="",$I91="Complete",$L91=""),0,IF(AND($L91>=TODAY(),$L91<=TODAY()+7),1,0)) -> 0 | T91: =IF(OR($B91="",$L91=""),"",$L91-TODAY()) -> 58 | U91: =IF($B91="","",IF($I91="Complete",1,IF($J91="",0,$J91))) -> 0 | V91: =IF($B91="",0,IF($N91="",0,1)) -> 0 | W91: =IF($B91="",0,1) -> 1
A92: =IF('Shane Mattingly'!$B12="","",'Shane Mattingly'!$A12) | B92: =IF('Shane Mattingly'!$B12="","",'Shane Mattingly'!$B12) | C92: =IF('Shane Mattingly'!$B12="","",'Shane Mattingly'!$C12) | D92: =IF('Shane Mattingly'!$B12="","",'Shane Mattingly'!$D12) | E92: =IF('Shane Mattingly'!$B12="","",'Shane Mattingly'!$E12) | F92: =IF('Shane Mattingly'!$B12="","",'Shane Mattingly'!$F12) | G92: =IF('Shane Mattingly'!$B12="","",'Shane Mattingly'!$G12) | H92: =IF('Shane Mattingly'!$B12="","",'Shane Mattingly'!$H12) | I92: =IF('Shane Mattingly'!$B12="","",'Shane Mattingly'!$I12) | J92: =IF('Shane Mattingly'!$B12="","",'Shane Mattingly'!$J12) | K92: =IF('Shane Mattingly'!$B12="","",'Shane Mattingly'!$K12) | L92: =IF('Shane Mattingly'!$B12="","",'Shane Mattingly'!$L12) | M92: =IF('Shane Mattingly'!$B12="","",'Shane Mattingly'!$M12) | N92: =IF('Shane Mattingly'!$B12="","",'Shane Mattingly'!$N12) | O92: =IF('Shane Mattingly'!$B12="","",'Shane Mattingly'!$O12) | P92: =IF('Shane Mattingly'!$B12="","",'Shane Mattingly'!$P12) | Q92: =IF('Shane Mattingly'!$B12="","","Shane Mattingly") | R92: =IF(OR($B92="",$I92="Complete",$L92=""),0,IF($L92<TODAY(),1,0)) -> 0 | S92: =IF(OR($B92="",$I92="Complete",$L92=""),0,IF(AND($L92>=TODAY(),$L92<=TODAY()+7),1,0)) -> 0 | T92: =IF(OR($B92="",$L92=""),"",$L92-TODAY()) | U92: =IF($B92="","",IF($I92="Complete",1,IF($J92="",0,$J92))) | V92: =IF($B92="",0,IF($N92="",0,1)) -> 0 | W92: =IF($B92="",0,1) -> 0
A93: =IF('Shane Mattingly'!$B13="","",'Shane Mattingly'!$A13) | B93: =IF('Shane Mattingly'!$B13="","",'Shane Mattingly'!$B13) | C93: =IF('Shane Mattingly'!$B13="","",'Shane Mattingly'!$C13) | D93: =IF('Shane Mattingly'!$B13="","",'Shane Mattingly'!$D13) | E93: =IF('Shane Mattingly'!$B13="","",'Shane Mattingly'!$E13) | F93: =IF('Shane Mattingly'!$B13="","",'Shane Mattingly'!$F13) | G93: =IF('Shane Mattingly'!$B13="","",'Shane Mattingly'!$G13) | H93: =IF('Shane Mattingly'!$B13="","",'Shane Mattingly'!$H13) | I93: =IF('Shane Mattingly'!$B13="","",'Shane Mattingly'!$I13) | J93: =IF('Shane Mattingly'!$B13="","",'Shane Mattingly'!$J13) | K93: =IF('Shane Mattingly'!$B13="","",'Shane Mattingly'!$K13) | L93: =IF('Shane Mattingly'!$B13="","",'Shane Mattingly'!$L13) | M93: =IF('Shane Mattingly'!$B13="","",'Shane Mattingly'!$M13) | N93: =IF('Shane Mattingly'!$B13="","",'Shane Mattingly'!$N13) | O93: =IF('Shane Mattingly'!$B13="","",'Shane Mattingly'!$O13) | P93: =IF('Shane Mattingly'!$B13="","",'Shane Mattingly'!$P13) | Q93: =IF('Shane Mattingly'!$B13="","","Shane Mattingly") | R93: =IF(OR($B93="",$I93="Complete",$L93=""),0,IF($L93<TODAY(),1,0)) -> 0 | S93: =IF(OR($B93="",$I93="Complete",$L93=""),0,IF(AND($L93>=TODAY(),$L93<=TODAY()+7),1,0)) -> 0 | T93: =IF(OR($B93="",$L93=""),"",$L93-TODAY()) | U93: =IF($B93="","",IF($I93="Complete",1,IF($J93="",0,$J93))) | V93: =IF($B93="",0,IF($N93="",0,1)) -> 0 | W93: =IF($B93="",0,1) -> 0
A94: =IF('Shane Mattingly'!$B14="","",'Shane Mattingly'!$A14) | B94: =IF('Shane Mattingly'!$B14="","",'Shane Mattingly'!$B14) | C94: =IF('Shane Mattingly'!$B14="","",'Shane Mattingly'!$C14) | D94: =IF('Shane Mattingly'!$B14="","",'Shane Mattingly'!$D14) | E94: =IF('Shane Mattingly'!$B14="","",'Shane Mattingly'!$E14) | F94: =IF('Shane Mattingly'!$B14="","",'Shane Mattingly'!$F14) | G94: =IF('Shane Mattingly'!$B14="","",'Shane Mattingly'!$G14) | H94: =IF('Shane Mattingly'!$B14="","",'Shane Mattingly'!$H14) | I94: =IF('Shane Mattingly'!$B14="","",'Shane Mattingly'!$I14) | J94: =IF('Shane Mattingly'!$B14="","",'Shane Mattingly'!$J14) | K94: =IF('Shane Mattingly'!$B14="","",'Shane Mattingly'!$K14) | L94: =IF('Shane Mattingly'!$B14="","",'Shane Mattingly'!$L14) | M94: =IF('Shane Mattingly'!$B14="","",'Shane Mattingly'!$M14) | N94: =IF('Shane Mattingly'!$B14="","",'Shane Mattingly'!$N14) | O94: =IF('Shane Mattingly'!$B14="","",'Shane Mattingly'!$O14) | P94: =IF('Shane Mattingly'!$B14="","",'Shane Mattingly'!$P14) | Q94: =IF('Shane Mattingly'!$B14="","","Shane Mattingly") | R94: =IF(OR($B94="",$I94="Complete",$L94=""),0,IF($L94<TODAY(),1,0)) -> 0 | S94: =IF(OR($B94="",$I94="Complete",$L94=""),0,IF(AND($L94>=TODAY(),$L94<=TODAY()+7),1,0)) -> 0 | T94: =IF(OR($B94="",$L94=""),"",$L94-TODAY()) | U94: =IF($B94="","",IF($I94="Complete",1,IF($J94="",0,$J94))) | V94: =IF($B94="",0,IF($N94="",0,1)) -> 0 | W94: =IF($B94="",0,1) -> 0
A95: =IF('Shane Mattingly'!$B15="","",'Shane Mattingly'!$A15) | B95: =IF('Shane Mattingly'!$B15="","",'Shane Mattingly'!$B15) | C95: =IF('Shane Mattingly'!$B15="","",'Shane Mattingly'!$C15) | D95: =IF('Shane Mattingly'!$B15="","",'Shane Mattingly'!$D15) | E95: =IF('Shane Mattingly'!$B15="","",'Shane Mattingly'!$E15) | F95: =IF('Shane Mattingly'!$B15="","",'Shane Mattingly'!$F15) | G95: =IF('Shane Mattingly'!$B15="","",'Shane Mattingly'!$G15) | H95: =IF('Shane Mattingly'!$B15="","",'Shane Mattingly'!$H15) | I95: =IF('Shane Mattingly'!$B15="","",'Shane Mattingly'!$I15) | J95: =IF('Shane Mattingly'!$B15="","",'Shane Mattingly'!$J15) | K95: =IF('Shane Mattingly'!$B15="","",'Shane Mattingly'!$K15) | L95: =IF('Shane Mattingly'!$B15="","",'Shane Mattingly'!$L15) | M95: =IF('Shane Mattingly'!$B15="","",'Shane Mattingly'!$M15) | N95: =IF('Shane Mattingly'!$B15="","",'Shane Mattingly'!$N15) | O95: =IF('Shane Mattingly'!$B15="","",'Shane Mattingly'!$O15) | P95: =IF('Shane Mattingly'!$B15="","",'Shane Mattingly'!$P15) | Q95: =IF('Shane Mattingly'!$B15="","","Shane Mattingly") | R95: =IF(OR($B95="",$I95="Complete",$L95=""),0,IF($L95<TODAY(),1,0)) -> 0 | S95: =IF(OR($B95="",$I95="Complete",$L95=""),0,IF(AND($L95>=TODAY(),$L95<=TODAY()+7),1,0)) -> 0 | T95: =IF(OR($B95="",$L95=""),"",$L95-TODAY()) | U95: =IF($B95="","",IF($I95="Complete",1,IF($J95="",0,$J95))) | V95: =IF($B95="",0,IF($N95="",0,1)) -> 0 | W95: =IF($B95="",0,1) -> 0
A96: =IF('Shane Mattingly'!$B16="","",'Shane Mattingly'!$A16) | B96: =IF('Shane Mattingly'!$B16="","",'Shane Mattingly'!$B16) | C96: =IF('Shane Mattingly'!$B16="","",'Shane Mattingly'!$C16) | D96: =IF('Shane Mattingly'!$B16="","",'Shane Mattingly'!$D16) | E96: =IF('Shane Mattingly'!$B16="","",'Shane Mattingly'!$E16) | F96: =IF('Shane Mattingly'!$B16="","",'Shane Mattingly'!$F16) | G96: =IF('Shane Mattingly'!$B16="","",'Shane Mattingly'!$G16) | H96: =IF('Shane Mattingly'!$B16="","",'Shane Mattingly'!$H16) | I96: =IF('Shane Mattingly'!$B16="","",'Shane Mattingly'!$I16) | J96: =IF('Shane Mattingly'!$B16="","",'Shane Mattingly'!$J16) | K96: =IF('Shane Mattingly'!$B16="","",'Shane Mattingly'!$K16) | L96: =IF('Shane Mattingly'!$B16="","",'Shane Mattingly'!$L16) | M96: =IF('Shane Mattingly'!$B16="","",'Shane Mattingly'!$M16) | N96: =IF('Shane Mattingly'!$B16="","",'Shane Mattingly'!$N16) | O96: =IF('Shane Mattingly'!$B16="","",'Shane Mattingly'!$O16) | P96: =IF('Shane Mattingly'!$B16="","",'Shane Mattingly'!$P16) | Q96: =IF('Shane Mattingly'!$B16="","","Shane Mattingly") | R96: =IF(OR($B96="",$I96="Complete",$L96=""),0,IF($L96<TODAY(),1,0)) -> 0 | S96: =IF(OR($B96="",$I96="Complete",$L96=""),0,IF(AND($L96>=TODAY(),$L96<=TODAY()+7),1,0)) -> 0 | T96: =IF(OR($B96="",$L96=""),"",$L96-TODAY()) | U96: =IF($B96="","",IF($I96="Complete",1,IF($J96="",0,$J96))) | V96: =IF($B96="",0,IF($N96="",0,1)) -> 0 | W96: =IF($B96="",0,1) -> 0
... A124: =IF('Shane Mattingly'!$B44="","",'Shane Mattingly'!$A44) | B124: =IF('Shane Mattingly'!$B44="","",'Shane Mattingly'!$B44) | C124: =IF('Shane Mattingly'!$B44="","",'Shane Mattingly'!$C44) | D124: =IF('Shane Mattingly'!$B44="","",'Shane Mattingly'!$D44) | E124: =IF('Shane Mattingly'!$B44="","",'Shane Mattingly'!$E44) | F124: =IF('Shane Mattingly'!$B44="","",'Shane Mattingly'!$F44) | G124: =IF('Shane Mattingly'!$B44="","",'Shane Mattingly'!$G44) | H124: =IF('Shane Mattingly'!$B44="","",'Shane Mattingly'!$H44) | I124: =IF('Shane Mattingly'!$B44="","",'Shane Mattingly'!$I44) | J124: =IF('Shane Mattingly'!$B44="","",'Shane Mattingly'!$J44) | K124: =IF('Shane Mattingly'!$B44="","",'Shane Mattingly'!$K44) | L124: =IF('Shane Mattingly'!$B44="","",'Shane Mattingly'!$L44) | M124: =IF('Shane Mattingly'!$B44="","",'Shane Mattingly'!$M44) | N124: =IF('Shane Mattingly'!$B44="","",'Shane Mattingly'!$N44) | O124: =IF('Shane Mattingly'!$B44="","",'Shane Mattingly'!$O44) | P124: =IF('Shane Mattingly'!$B44="","",'Shane Mattingly'!$P44) | Q124: =IF('Shane Mattingly'!$B44="","","Shane Mattingly") | R124: =IF(OR($B124="",$I124="Complete",$L124=""),0,IF($L124<TODAY(),1,0)) -> 0 | S124: =IF(OR($B124="",$I124="Complete",$L124=""),0,IF(AND($L124>=TODAY(),$L124<=TODAY()+7),1,0)) -> 0 | T124: =IF(OR($B124="",$L124=""),"",$L124-TODAY()) | U124: =IF($B124="","",IF($I124="Complete",1,IF($J124="",0,$J124))) | V124: =IF($B124="",0,IF($N124="",0,1)) -> 0 | W124: =IF($B124="",0,1) -> 0
A125: =IF('Leslie Toole'!$B5="","",'Leslie Toole'!$A5) -> LT-001 | B125: =IF('Leslie Toole'!$B5="","",'Leslie Toole'!$B5) -> P1-1 | C125: =IF('Leslie Toole'!$B5="","",'Leslie Toole'!$C5) -> 1 – Unified Development System | D125: =IF('Leslie Toole'!$B5="","",'Leslie Toole'!$D5) -> Implement standardized Mutual Evaluation Process (MEP) across all brands | E125: =IF('Leslie Toole'!$B5="","",'Leslie Toole'!$E5) -> Leslie Toole | F125: =IF('Leslie Toole'!$B5="","",'Leslie Toole'!$F5) -> Contributor | G125: =IF('Leslie Toole'!$B5="","",'Leslie Toole'!$G5) -> Training Section 1-3 in Fran Dev 101 | H125: =IF('Leslie Toole'!$B5="","",'Leslie Toole'!$H5) -> Medium | I125: =IF('Leslie Toole'!$B5="","",'Leslie Toole'!$I5) -> In Progress | J125: =IF('Leslie Toole'!$B5="","",'Leslie Toole'!$J5) -> 0.5 | K125: =IF('Leslie Toole'!$B5="","",'Leslie Toole'!$K5) -> 46162 | L125: =IF('Leslie Toole'!$B5="","",'Leslie Toole'!$L5) -> 46186 | M125: =IF('Leslie Toole'!$B5="","",'Leslie Toole'!$M5) -> 0 | N125: =IF('Leslie Toole'!$B5="","",'Leslie Toole'!$N5) -> 0 | O125: =IF('Leslie Toole'!$B5="","",'Leslie Toole'!$O5) -> Assigned 5/20 | P125: =IF('Leslie Toole'!$B5="","",'Leslie Toole'!$P5) -> Complete sections 2-3 | Q125: =IF('Leslie Toole'!$B5="","","Leslie Toole") -> Leslie Toole | R125: =IF(OR($B125="",$I125="Complete",$L125=""),0,IF($L125<TODAY(),1,0)) -> 0 | S125: =IF(OR($B125="",$I125="Complete",$L125=""),0,IF(AND($L125>=TODAY(),$L125<=TODAY()+7),1,0)) -> 0 | T125: =IF(OR($B125="",$L125=""),"",$L125-TODAY()) -> 16 | U125: =IF($B125="","",IF($I125="Complete",1,IF($J125="",0,$J125))) -> 0.5 | V125: =IF($B125="",0,IF($N125="",0,1)) -> 0 | W125: =IF($B125="",0,1) -> 1
A126: =IF('Leslie Toole'!$B6="","",'Leslie Toole'!$A6) | B126: =IF('Leslie Toole'!$B6="","",'Leslie Toole'!$B6) | C126: =IF('Leslie Toole'!$B6="","",'Leslie Toole'!$C6) | D126: =IF('Leslie Toole'!$B6="","",'Leslie Toole'!$D6) | E126: =IF('Leslie Toole'!$B6="","",'Leslie Toole'!$E6) | F126: =IF('Leslie Toole'!$B6="","",'Leslie Toole'!$F6) | G126: =IF('Leslie Toole'!$B6="","",'Leslie Toole'!$G6) | H126: =IF('Leslie Toole'!$B6="","",'Leslie Toole'!$H6) | I126: =IF('Leslie Toole'!$B6="","",'Leslie Toole'!$I6) | J126: =IF('Leslie Toole'!$B6="","",'Leslie Toole'!$J6) | K126: =IF('Leslie Toole'!$B6="","",'Leslie Toole'!$K6) | L126: =IF('Leslie Toole'!$B6="","",'Leslie Toole'!$L6) | M126: =IF('Leslie Toole'!$B6="","",'Leslie Toole'!$M6) | N126: =IF('Leslie Toole'!$B6="","",'Leslie Toole'!$N6) | O126: =IF('Leslie Toole'!$B6="","",'Leslie Toole'!$O6) | P126: =IF('Leslie Toole'!$B6="","",'Leslie Toole'!$P6) | Q126: =IF('Leslie Toole'!$B6="","","Leslie Toole") | R126: =IF(OR($B126="",$I126="Complete",$L126=""),0,IF($L126<TODAY(),1,0)) -> 0 | S126: =IF(OR($B126="",$I126="Complete",$L126=""),0,IF(AND($L126>=TODAY(),$L126<=TODAY()+7),1,0)) -> 0 | T126: =IF(OR($B126="",$L126=""),"",$L126-TODAY()) | U126: =IF($B126="","",IF($I126="Complete",1,IF($J126="",0,$J126))) | V126: =IF($B126="",0,IF($N126="",0,1)) -> 0 | W126: =IF($B126="",0,1) -> 0
A127: =IF('Leslie Toole'!$B7="","",'Leslie Toole'!$A7) | B127: =IF('Leslie Toole'!$B7="","",'Leslie Toole'!$B7) | C127: =IF('Leslie Toole'!$B7="","",'Leslie Toole'!$C7) | D127: =IF('Leslie Toole'!$B7="","",'Leslie Toole'!$D7) | E127: =IF('Leslie Toole'!$B7="","",'Leslie Toole'!$E7) | F127: =IF('Leslie Toole'!$B7="","",'Leslie Toole'!$F7) | G127: =IF('Leslie Toole'!$B7="","",'Leslie Toole'!$G7) | H127: =IF('Leslie Toole'!$B7="","",'Leslie Toole'!$H7) | I127: =IF('Leslie Toole'!$B7="","",'Leslie Toole'!$I7) | J127: =IF('Leslie Toole'!$B7="","",'Leslie Toole'!$J7) | K127: =IF('Leslie Toole'!$B7="","",'Leslie Toole'!$K7) | L127: =IF('Leslie Toole'!$B7="","",'Leslie Toole'!$L7) | M127: =IF('Leslie Toole'!$B7="","",'Leslie Toole'!$M7) | N127: =IF('Leslie Toole'!$B7="","",'Leslie Toole'!$N7) | O127: =IF('Leslie Toole'!$B7="","",'Leslie Toole'!$O7) | P127: =IF('Leslie Toole'!$B7="","",'Leslie Toole'!$P7) | Q127: =IF('Leslie Toole'!$B7="","","Leslie Toole") | R127: =IF(OR($B127="",$I127="Complete",$L127=""),0,IF($L127<TODAY(),1,0)) -> 0 | S127: =IF(OR($B127="",$I127="Complete",$L127=""),0,IF(AND($L127>=TODAY(),$L127<=TODAY()+7),1,0)) -> 0 | T127: =IF(OR($B127="",$L127=""),"",$L127-TODAY()) | U127: =IF($B127="","",IF($I127="Complete",1,IF($J127="",0,$J127))) | V127: =IF($B127="",0,IF($N127="",0,1)) -> 0 | W127: =IF($B127="",0,1) -> 0
A128: =IF('Leslie Toole'!$B8="","",'Leslie Toole'!$A8) | B128: =IF('Leslie Toole'!$B8="","",'Leslie Toole'!$B8) | C128: =IF('Leslie Toole'!$B8="","",'Leslie Toole'!$C8) | D128: =IF('Leslie Toole'!$B8="","",'Leslie Toole'!$D8) | E128: =IF('Leslie Toole'!$B8="","",'Leslie Toole'!$E8) | F128: =IF('Leslie Toole'!$B8="","",'Leslie Toole'!$F8) | G128: =IF('Leslie Toole'!$B8="","",'Leslie Toole'!$G8) | H128: =IF('Leslie Toole'!$B8="","",'Leslie Toole'!$H8) | I128: =IF('Leslie Toole'!$B8="","",'Leslie Toole'!$I8) | J128: =IF('Leslie Toole'!$B8="","",'Leslie Toole'!$J8) | K128: =IF('Leslie Toole'!$B8="","",'Leslie Toole'!$K8) | L128: =IF('Leslie Toole'!$B8="","",'Leslie Toole'!$L8) | M128: =IF('Leslie Toole'!$B8="","",'Leslie Toole'!$M8) | N128: =IF('Leslie Toole'!$B8="","",'Leslie Toole'!$N8) | O128: =IF('Leslie Toole'!$B8="","",'Leslie Toole'!$O8) | P128: =IF('Leslie Toole'!$B8="","",'Leslie Toole'!$P8) | Q128: =IF('Leslie Toole'!$B8="","","Leslie Toole") | R128: =IF(OR($B128="",$I128="Complete",$L128=""),0,IF($L128<TODAY(),1,0)) -> 0 | S128: =IF(OR($B128="",$I128="Complete",$L128=""),0,IF(AND($L128>=TODAY(),$L128<=TODAY()+7),1,0)) -> 0 | T128: =IF(OR($B128="",$L128=""),"",$L128-TODAY()) | U128: =IF($B128="","",IF($I128="Complete",1,IF($J128="",0,$J128))) | V128: =IF($B128="",0,IF($N128="",0,1)) -> 0 | W128: =IF($B128="",0,1) -> 0
A129: =IF('Leslie Toole'!$B9="","",'Leslie Toole'!$A9) | B129: =IF('Leslie Toole'!$B9="","",'Leslie Toole'!$B9) | C129: =IF('Leslie Toole'!$B9="","",'Leslie Toole'!$C9) | D129: =IF('Leslie Toole'!$B9="","",'Leslie Toole'!$D9) | E129: =IF('Leslie Toole'!$B9="","",'Leslie Toole'!$E9) | F129: =IF('Leslie Toole'!$B9="","",'Leslie Toole'!$F9) | G129: =IF('Leslie Toole'!$B9="","",'Leslie Toole'!$G9) | H129: =IF('Leslie Toole'!$B9="","",'Leslie Toole'!$H9) | I129: =IF('Leslie Toole'!$B9="","",'Leslie Toole'!$I9) | J129: =IF('Leslie Toole'!$B9="","",'Leslie Toole'!$J9) | K129: =IF('Leslie Toole'!$B9="","",'Leslie Toole'!$K9) | L129: =IF('Leslie Toole'!$B9="","",'Leslie Toole'!$L9) | M129: =IF('Leslie Toole'!$B9="","",'Leslie Toole'!$M9) | N129: =IF('Leslie Toole'!$B9="","",'Leslie Toole'!$N9) | O129: =IF('Leslie Toole'!$B9="","",'Leslie Toole'!$O9) | P129: =IF('Leslie Toole'!$B9="","",'Leslie Toole'!$P9) | Q129: =IF('Leslie Toole'!$B9="","","Leslie Toole") | R129: =IF(OR($B129="",$I129="Complete",$L129=""),0,IF($L129<TODAY(),1,0)) -> 0 | S129: =IF(OR($B129="",$I129="Complete",$L129=""),0,IF(AND($L129>=TODAY(),$L129<=TODAY()+7),1,0)) -> 0 | T129: =IF(OR($B129="",$L129=""),"",$L129-TODAY()) | U129: =IF($B129="","",IF($I129="Complete",1,IF($J129="",0,$J129))) | V129: =IF($B129="",0,IF($N129="",0,1)) -> 0 | W129: =IF($B129="",0,1) -> 0
A130: =IF('Leslie Toole'!$B10="","",'Leslie Toole'!$A10) | B130: =IF('Leslie Toole'!$B10="","",'Leslie Toole'!$B10) | C130: =IF('Leslie Toole'!$B10="","",'Leslie Toole'!$C10) | D130: =IF('Leslie Toole'!$B10="","",'Leslie Toole'!$D10) | E130: =IF('Leslie Toole'!$B10="","",'Leslie Toole'!$E10) | F130: =IF('Leslie Toole'!$B10="","",'Leslie Toole'!$F10) | G130: =IF('Leslie Toole'!$B10="","",'Leslie Toole'!$G10) | H130: =IF('Leslie Toole'!$B10="","",'Leslie Toole'!$H10) | I130: =IF('Leslie Toole'!$B10="","",'Leslie Toole'!$I10) | J130: =IF('Leslie Toole'!$B10="","",'Leslie Toole'!$J10) | K130: =IF('Leslie Toole'!$B10="","",'Leslie Toole'!$K10) | L130: =IF('Leslie Toole'!$B10="","",'Leslie Toole'!$L10) | M130: =IF('Leslie Toole'!$B10="","",'Leslie Toole'!$M10) | N130: =IF('Leslie Toole'!$B10="","",'Leslie Toole'!$N10) | O130: =IF('Leslie Toole'!$B10="","",'Leslie Toole'!$O10) | P130: =IF('Leslie Toole'!$B10="","",'Leslie Toole'!$P10) | Q130: =IF('Leslie Toole'!$B10="","","Leslie Toole") | R130: =IF(OR($B130="",$I130="Complete",$L130=""),0,IF($L130<TODAY(),1,0)) -> 0 | S130: =IF(OR($B130="",$I130="Complete",$L130=""),0,IF(AND($L130>=TODAY(),$L130<=TODAY()+7),1,0)) -> 0 | T130: =IF(OR($B130="",$L130=""),"",$L130-TODAY()) | U130: =IF($B130="","",IF($I130="Complete",1,IF($J130="",0,$J130))) | V130: =IF($B130="",0,IF($N130="",0,1)) -> 0 | W130: =IF($B130="",0,1) -> 0
A131: =IF('Leslie Toole'!$B11="","",'Leslie Toole'!$A11) | B131: =IF('Leslie Toole'!$B11="","",'Leslie Toole'!$B11) | C131: =IF('Leslie Toole'!$B11="","",'Leslie Toole'!$C11) | D131: =IF('Leslie Toole'!$B11="","",'Leslie Toole'!$D11) | E131: =IF('Leslie Toole'!$B11="","",'Leslie Toole'!$E11) | F131: =IF('Leslie Toole'!$B11="","",'Leslie Toole'!$F11) | G131: =IF('Leslie Toole'!$B11="","",'Leslie Toole'!$G11) | H131: =IF('Leslie Toole'!$B11="","",'Leslie Toole'!$H11) | I131: =IF('Leslie Toole'!$B11="","",'Leslie Toole'!$I11) | J131: =IF('Leslie Toole'!$B11="","",'Leslie Toole'!$J11) | K131: =IF('Leslie Toole'!$B11="","",'Leslie Toole'!$K11) | L131: =IF('Leslie Toole'!$B11="","",'Leslie Toole'!$L11) | M131: =IF('Leslie Toole'!$B11="","",'Leslie Toole'!$M11) | N131: =IF('Leslie Toole'!$B11="","",'Leslie Toole'!$N11) | O131: =IF('Leslie Toole'!$B11="","",'Leslie Toole'!$O11) | P131: =IF('Leslie Toole'!$B11="","",'Leslie Toole'!$P11) | Q131: =IF('Leslie Toole'!$B11="","","Leslie Toole") | R131: =IF(OR($B131="",$I131="Complete",$L131=""),0,IF($L131<TODAY(),1,0)) -> 0 | S131: =IF(OR($B131="",$I131="Complete",$L131=""),0,IF(AND($L131>=TODAY(),$L131<=TODAY()+7),1,0)) -> 0 | T131: =IF(OR($B131="",$L131=""),"",$L131-TODAY()) | U131: =IF($B131="","",IF($I131="Complete",1,IF($J131="",0,$J131))) | V131: =IF($B131="",0,IF($N131="",0,1)) -> 0 | W131: =IF($B131="",0,1) -> 0
A132: =IF('Leslie Toole'!$B12="","",'Leslie Toole'!$A12) | B132: =IF('Leslie Toole'!$B12="","",'Leslie Toole'!$B12) | C132: =IF('Leslie Toole'!$B12="","",'Leslie Toole'!$C12) | D132: =IF('Leslie Toole'!$B12="","",'Leslie Toole'!$D12) | E132: =IF('Leslie Toole'!$B12="","",'Leslie Toole'!$E12) | F132: =IF('Leslie Toole'!$B12="","",'Leslie Toole'!$F12) | G132: =IF('Leslie Toole'!$B12="","",'Leslie Toole'!$G12) | H132: =IF('Leslie Toole'!$B12="","",'Leslie Toole'!$H12) | I132: =IF('Leslie Toole'!$B12="","",'Leslie Toole'!$I12) | J132: =IF('Leslie Toole'!$B12="","",'Leslie Toole'!$J12) | K132: =IF('Leslie Toole'!$B12="","",'Leslie Toole'!$K12) | L132: =IF('Leslie Toole'!$B12="","",'Leslie Toole'!$L12) | M132: =IF('Leslie Toole'!$B12="","",'Leslie Toole'!$M12) | N132: =IF('Leslie Toole'!$B12="","",'Leslie Toole'!$N12) | O132: =IF('Leslie Toole'!$B12="","",'Leslie Toole'!$O12) | P132: =IF('Leslie Toole'!$B12="","",'Leslie Toole'!$P12) | Q132: =IF('Leslie Toole'!$B12="","","Leslie Toole") | R132: =IF(OR($B132="",$I132="Complete",$L132=""),0,IF($L132<TODAY(),1,0)) -> 0 | S132: =IF(OR($B132="",$I132="Complete",$L132=""),0,IF(AND($L132>=TODAY(),$L132<=TODAY()+7),1,0)) -> 0 | T132: =IF(OR($B132="",$L132=""),"",$L132-TODAY()) | U132: =IF($B132="","",IF($I132="Complete",1,IF($J132="",0,$J132))) | V132: =IF($B132="",0,IF($N132="",0,1)) -> 0 | W132: =IF($B132="",0,1) -> 0
A133: =IF('Leslie Toole'!$B13="","",'Leslie Toole'!$A13) | B133: =IF('Leslie Toole'!$B13="","",'Leslie Toole'!$B13) | C133: =IF('Leslie Toole'!$B13="","",'Leslie Toole'!$C13) | D133: =IF('Leslie Toole'!$B13="","",'Leslie Toole'!$D13) | E133: =IF('Leslie Toole'!$B13="","",'Leslie Toole'!$E13) | F133: =IF('Leslie Toole'!$B13="","",'Leslie Toole'!$F13) | G133: =IF('Leslie Toole'!$B13="","",'Leslie Toole'!$G13) | H133: =IF('Leslie Toole'!$B13="","",'Leslie Toole'!$H13) | I133: =IF('Leslie Toole'!$B13="","",'Leslie Toole'!$I13) | J133: =IF('Leslie Toole'!$B13="","",'Leslie Toole'!$J13) | K133: =IF('Leslie Toole'!$B13="","",'Leslie Toole'!$K13) | L133: =IF('Leslie Toole'!$B13="","",'Leslie Toole'!$L13) | M133: =IF('Leslie Toole'!$B13="","",'Leslie Toole'!$M13) | N133: =IF('Leslie Toole'!$B13="","",'Leslie Toole'!$N13) | O133: =IF('Leslie Toole'!$B13="","",'Leslie Toole'!$O13) | P133: =IF('Leslie Toole'!$B13="","",'Leslie Toole'!$P13) | Q133: =IF('Leslie Toole'!$B13="","","Leslie Toole") | R133: =IF(OR($B133="",$I133="Complete",$L133=""),0,IF($L133<TODAY(),1,0)) -> 0 | S133: =IF(OR($B133="",$I133="Complete",$L133=""),0,IF(AND($L133>=TODAY(),$L133<=TODAY()+7),1,0)) -> 0 | T133: =IF(OR($B133="",$L133=""),"",$L133-TODAY()) | U133: =IF($B133="","",IF($I133="Complete",1,IF($J133="",0,$J133))) | V133: =IF($B133="",0,IF($N133="",0,1)) -> 0 | W133: =IF($B133="",0,1) -> 0
A134: =IF('Leslie Toole'!$B14="","",'Leslie Toole'!$A14) | B134: =IF('Leslie Toole'!$B14="","",'Leslie Toole'!$B14) | C134: =IF('Leslie Toole'!$B14="","",'Leslie Toole'!$C14) | D134: =IF('Leslie Toole'!$B14="","",'Leslie Toole'!$D14) | E134: =IF('Leslie Toole'!$B14="","",'Leslie Toole'!$E14) | F134: =IF('Leslie Toole'!$B14="","",'Leslie Toole'!$F14) | G134: =IF('Leslie Toole'!$B14="","",'Leslie Toole'!$G14) | H134: =IF('Leslie Toole'!$B14="","",'Leslie Toole'!$H14) | I134: =IF('Leslie Toole'!$B14="","",'Leslie Toole'!$I14) | J134: =IF('Leslie Toole'!$B14="","",'Leslie Toole'!$J14) | K134: =IF('Leslie Toole'!$B14="","",'Leslie Toole'!$K14) | L134: =IF('Leslie Toole'!$B14="","",'Leslie Toole'!$L14) | M134: =IF('Leslie Toole'!$B14="","",'Leslie Toole'!$M14) | N134: =IF('Leslie Toole'!$B14="","",'Leslie Toole'!$N14) | O134: =IF('Leslie Toole'!$B14="","",'Leslie Toole'!$O14) | P134: =IF('Leslie Toole'!$B14="","",'Leslie Toole'!$P14) | Q134: =IF('Leslie Toole'!$B14="","","Leslie Toole") | R134: =IF(OR($B134="",$I134="Complete",$L134=""),0,IF($L134<TODAY(),1,0)) -> 0 | S134: =IF(OR($B134="",$I134="Complete",$L134=""),0,IF(AND($L134>=TODAY(),$L134<=TODAY()+7),1,0)) -> 0 | T134: =IF(OR($B134="",$L134=""),"",$L134-TODAY()) | U134: =IF($B134="","",IF($I134="Complete",1,IF($J134="",0,$J134))) | V134: =IF($B134="",0,IF($N134="",0,1)) -> 0 | W134: =IF($B134="",0,1) -> 0
A135: =IF('Leslie Toole'!$B15="","",'Leslie Toole'!$A15) | B135: =IF('Leslie Toole'!$B15="","",'Leslie Toole'!$B15) | C135: =IF('Leslie Toole'!$B15="","",'Leslie Toole'!$C15) | D135: =IF('Leslie Toole'!$B15="","",'Leslie Toole'!$D15) | E135: =IF('Leslie Toole'!$B15="","",'Leslie Toole'!$E15) | F135: =IF('Leslie Toole'!$B15="","",'Leslie Toole'!$F15) | G135: =IF('Leslie Toole'!$B15="","",'Leslie Toole'!$G15) | H135: =IF('Leslie Toole'!$B15="","",'Leslie Toole'!$H15) | I135: =IF('Leslie Toole'!$B15="","",'Leslie Toole'!$I15) | J135: =IF('Leslie Toole'!$B15="","",'Leslie Toole'!$J15) | K135: =IF('Leslie Toole'!$B15="","",'Leslie Toole'!$K15) | L135: =IF('Leslie Toole'!$B15="","",'Leslie Toole'!$L15) | M135: =IF('Leslie Toole'!$B15="","",'Leslie Toole'!$M15) | N135: =IF('Leslie Toole'!$B15="","",'Leslie Toole'!$N15) | O135: =IF('Leslie Toole'!$B15="","",'Leslie Toole'!$O15) | P135: =IF('Leslie Toole'!$B15="","",'Leslie Toole'!$P15) | Q135: =IF('Leslie Toole'!$B15="","","Leslie Toole") | R135: =IF(OR($B135="",$I135="Complete",$L135=""),0,IF($L135<TODAY(),1,0)) -> 0 | S135: =IF(OR($B135="",$I135="Complete",$L135=""),0,IF(AND($L135>=TODAY(),$L135<=TODAY()+7),1,0)) -> 0 | T135: =IF(OR($B135="",$L135=""),"",$L135-TODAY()) | U135: =IF($B135="","",IF($I135="Complete",1,IF($J135="",0,$J135))) | V135: =IF($B135="",0,IF($N135="",0,1)) -> 0 | W135: =IF($B135="",0,1) -> 0
A136: =IF('Leslie Toole'!$B16="","",'Leslie Toole'!$A16) | B136: =IF('Leslie Toole'!$B16="","",'Leslie Toole'!$B16) | C136: =IF('Leslie Toole'!$B16="","",'Leslie Toole'!$C16) | D136: =IF('Leslie Toole'!$B16="","",'Leslie Toole'!$D16) | E136: =IF('Leslie Toole'!$B16="","",'Leslie Toole'!$E16) | F136: =IF('Leslie Toole'!$B16="","",'Leslie Toole'!$F16) | G136: =IF('Leslie Toole'!$B16="","",'Leslie Toole'!$G16) | H136: =IF('Leslie Toole'!$B16="","",'Leslie Toole'!$H16) | I136: =IF('Leslie Toole'!$B16="","",'Leslie Toole'!$I16) | J136: =IF('Leslie Toole'!$B16="","",'Leslie Toole'!$J16) | K136: =IF('Leslie Toole'!$B16="","",'Leslie Toole'!$K16) | L136: =IF('Leslie Toole'!$B16="","",'Leslie Toole'!$L16) | M136: =IF('Leslie Toole'!$B16="","",'Leslie Toole'!$M16) | N136: =IF('Leslie Toole'!$B16="","",'Leslie Toole'!$N16) | O136: =IF('Leslie Toole'!$B16="","",'Leslie Toole'!$O16) | P136: =IF('Leslie Toole'!$B16="","",'Leslie Toole'!$P16) | Q136: =IF('Leslie Toole'!$B16="","","Leslie Toole") | R136: =IF(OR($B136="",$I136="Complete",$L136=""),0,IF($L136<TODAY(),1,0)) -> 0 | S136: =IF(OR($B136="",$I136="Complete",$L136=""),0,IF(AND($L136>=TODAY(),$L136<=TODAY()+7),1,0)) -> 0 | T136: =IF(OR($B136="",$L136=""),"",$L136-TODAY()) | U136: =IF($B136="","",IF($I136="Complete",1,IF($J136="",0,$J136))) | V136: =IF($B136="",0,IF($N136="",0,1)) -> 0 | W136: =IF($B136="",0,1) -> 0
... A164: =IF('Leslie Toole'!$B44="","",'Leslie Toole'!$A44) | B164: =IF('Leslie Toole'!$B44="","",'Leslie Toole'!$B44) | C164: =IF('Leslie Toole'!$B44="","",'Leslie Toole'!$C44) | D164: =IF('Leslie Toole'!$B44="","",'Leslie Toole'!$D44) | E164: =IF('Leslie Toole'!$B44="","",'Leslie Toole'!$E44) | F164: =IF('Leslie Toole'!$B44="","",'Leslie Toole'!$F44) | G164: =IF('Leslie Toole'!$B44="","",'Leslie Toole'!$G44) | H164: =IF('Leslie Toole'!$B44="","",'Leslie Toole'!$H44) | I164: =IF('Leslie Toole'!$B44="","",'Leslie Toole'!$I44) | J164: =IF('Leslie Toole'!$B44="","",'Leslie Toole'!$J44) | K164: =IF('Leslie Toole'!$B44="","",'Leslie Toole'!$K44) | L164: =IF('Leslie Toole'!$B44="","",'Leslie Toole'!$L44) | M164: =IF('Leslie Toole'!$B44="","",'Leslie Toole'!$M44) | N164: =IF('Leslie Toole'!$B44="","",'Leslie Toole'!$N44) | O164: =IF('Leslie Toole'!$B44="","",'Leslie Toole'!$O44) | P164: =IF('Leslie Toole'!$B44="","",'Leslie Toole'!$P44) | Q164: =IF('Leslie Toole'!$B44="","","Leslie Toole") | R164: =IF(OR($B164="",$I164="Complete",$L164=""),0,IF($L164<TODAY(),1,0)) -> 0 | S164: =IF(OR($B164="",$I164="Complete",$L164=""),0,IF(AND($L164>=TODAY(),$L164<=TODAY()+7),1,0)) -> 0 | T164: =IF(OR($B164="",$L164=""),"",$L164-TODAY()) | U164: =IF($B164="","",IF($I164="Complete",1,IF($J164="",0,$J164))) | V164: =IF($B164="",0,IF($N164="",0,1)) -> 0 | W164: =IF($B164="",0,1) -> 0
A165: =IF('Leah Hanlon'!$B5="","",'Leah Hanlon'!$A5) -> LH-001 | B165: =IF('Leah Hanlon'!$B5="","",'Leah Hanlon'!$B5) -> P1-1 | C165: =IF('Leah Hanlon'!$B5="","",'Leah Hanlon'!$C5) -> 1 – Unified Development System | D165: =IF('Leah Hanlon'!$B5="","",'Leah Hanlon'!$D5) -> Implement standardized Mutual Evaluation Process (MEP) across all brands | E165: =IF('Leah Hanlon'!$B5="","",'Leah Hanlon'!$E5) -> Leah Hanlon | F165: =IF('Leah Hanlon'!$B5="","",'Leah Hanlon'!$F5) -> Contributor | G165: =IF('Leah Hanlon'!$B5="","",'Leah Hanlon'!$G5) -> Training Section 1-3 in Fran Dev 101 | H165: =IF('Leah Hanlon'!$B5="","",'Leah Hanlon'!$H5) -> Medium | I165: =IF('Leah Hanlon'!$B5="","",'Leah Hanlon'!$I5) -> In Progress | J165: =IF('Leah Hanlon'!$B5="","",'Leah Hanlon'!$J5) -> 0.5 | K165: =IF('Leah Hanlon'!$B5="","",'Leah Hanlon'!$K5) -> 46162 | L165: =IF('Leah Hanlon'!$B5="","",'Leah Hanlon'!$L5) -> 46186 | M165: =IF('Leah Hanlon'!$B5="","",'Leah Hanlon'!$M5) -> 0 | N165: =IF('Leah Hanlon'!$B5="","",'Leah Hanlon'!$N5) -> 0 | O165: =IF('Leah Hanlon'!$B5="","",'Leah Hanlon'!$O5) -> Assigned 5/20 | P165: =IF('Leah Hanlon'!$B5="","",'Leah Hanlon'!$P5) -> Complete sections 2-3 | Q165: =IF('Leah Hanlon'!$B5="","","Leah Hanlon") -> Leah Hanlon | R165: =IF(OR($B165="",$I165="Complete",$L165=""),0,IF($L165<TODAY(),1,0)) -> 0 | S165: =IF(OR($B165="",$I165="Complete",$L165=""),0,IF(AND($L165>=TODAY(),$L165<=TODAY()+7),1,0)) -> 0 | T165: =IF(OR($B165="",$L165=""),"",$L165-TODAY()) -> 16 | U165: =IF($B165="","",IF($I165="Complete",1,IF($J165="",0,$J165))) -> 0.5 | V165: =IF($B165="",0,IF($N165="",0,1)) -> 0 | W165: =IF($B165="",0,1) -> 1
A166: =IF('Leah Hanlon'!$B6="","",'Leah Hanlon'!$A6) | B166: =IF('Leah Hanlon'!$B6="","",'Leah Hanlon'!$B6) | C166: =IF('Leah Hanlon'!$B6="","",'Leah Hanlon'!$C6) | D166: =IF('Leah Hanlon'!$B6="","",'Leah Hanlon'!$D6) | E166: =IF('Leah Hanlon'!$B6="","",'Leah Hanlon'!$E6) | F166: =IF('Leah Hanlon'!$B6="","",'Leah Hanlon'!$F6) | G166: =IF('Leah Hanlon'!$B6="","",'Leah Hanlon'!$G6) | H166: =IF('Leah Hanlon'!$B6="","",'Leah Hanlon'!$H6) | I166: =IF('Leah Hanlon'!$B6="","",'Leah Hanlon'!$I6) | J166: =IF('Leah Hanlon'!$B6="","",'Leah Hanlon'!$J6) | K166: =IF('Leah Hanlon'!$B6="","",'Leah Hanlon'!$K6) | L166: =IF('Leah Hanlon'!$B6="","",'Leah Hanlon'!$L6) | M166: =IF('Leah Hanlon'!$B6="","",'Leah Hanlon'!$M6) | N166: =IF('Leah Hanlon'!$B6="","",'Leah Hanlon'!$N6) | O166: =IF('Leah Hanlon'!$B6="","",'Leah Hanlon'!$O6) | P166: =IF('Leah Hanlon'!$B6="","",'Leah Hanlon'!$P6) | Q166: =IF('Leah Hanlon'!$B6="","","Leah Hanlon") | R166: =IF(OR($B166="",$I166="Complete",$L166=""),0,IF($L166<TODAY(),1,0)) -> 0 | S166: =IF(OR($B166="",$I166="Complete",$L166=""),0,IF(AND($L166>=TODAY(),$L166<=TODAY()+7),1,0)) -> 0 | T166: =IF(OR($B166="",$L166=""),"",$L166-TODAY()) | U166: =IF($B166="","",IF($I166="Complete",1,IF($J166="",0,$J166))) | V166: =IF($B166="",0,IF($N166="",0,1)) -> 0 | W166: =IF($B166="",0,1) -> 0
A167: =IF('Leah Hanlon'!$B7="","",'Leah Hanlon'!$A7) | B167: =IF('Leah Hanlon'!$B7="","",'Leah Hanlon'!$B7) | C167: =IF('Leah Hanlon'!$B7="","",'Leah Hanlon'!$C7) | D167: =IF('Leah Hanlon'!$B7="","",'Leah Hanlon'!$D7) | E167: =IF('Leah Hanlon'!$B7="","",'Leah Hanlon'!$E7) | F167: =IF('Leah Hanlon'!$B7="","",'Leah Hanlon'!$F7) | G167: =IF('Leah Hanlon'!$B7="","",'Leah Hanlon'!$G7) | H167: =IF('Leah Hanlon'!$B7="","",'Leah Hanlon'!$H7) | I167: =IF('Leah Hanlon'!$B7="","",'Leah Hanlon'!$I7) | J167: =IF('Leah Hanlon'!$B7="","",'Leah Hanlon'!$J7) | K167: =IF('Leah Hanlon'!$B7="","",'Leah Hanlon'!$K7) | L167: =IF('Leah Hanlon'!$B7="","",'Leah Hanlon'!$L7) | M167: =IF('Leah Hanlon'!$B7="","",'Leah Hanlon'!$M7) | N167: =IF('Leah Hanlon'!$B7="","",'Leah Hanlon'!$N7) | O167: =IF('Leah Hanlon'!$B7="","",'Leah Hanlon'!$O7) | P167: =IF('Leah Hanlon'!$B7="","",'Leah Hanlon'!$P7) | Q167: =IF('Leah Hanlon'!$B7="","","Leah Hanlon") | R167: =IF(OR($B167="",$I167="Complete",$L167=""),0,IF($L167<TODAY(),1,0)) -> 0 | S167: =IF(OR($B167="",$I167="Complete",$L167=""),0,IF(AND($L167>=TODAY(),$L167<=TODAY()+7),1,0)) -> 0 | T167: =IF(OR($B167="",$L167=""),"",$L167-TODAY()) | U167: =IF($B167="","",IF($I167="Complete",1,IF($J167="",0,$J167))) | V167: =IF($B167="",0,IF($N167="",0,1)) -> 0 | W167: =IF($B167="",0,1) -> 0
A168: =IF('Leah Hanlon'!$B8="","",'Leah Hanlon'!$A8) | B168: =IF('Leah Hanlon'!$B8="","",'Leah Hanlon'!$B8) | C168: =IF('Leah Hanlon'!$B8="","",'Leah Hanlon'!$C8) | D168: =IF('Leah Hanlon'!$B8="","",'Leah Hanlon'!$D8) | E168: =IF('Leah Hanlon'!$B8="","",'Leah Hanlon'!$E8) | F168: =IF('Leah Hanlon'!$B8="","",'Leah Hanlon'!$F8) | G168: =IF('Leah Hanlon'!$B8="","",'Leah Hanlon'!$G8) | H168: =IF('Leah Hanlon'!$B8="","",'Leah Hanlon'!$H8) | I168: =IF('Leah Hanlon'!$B8="","",'Leah Hanlon'!$I8) | J168: =IF('Leah Hanlon'!$B8="","",'Leah Hanlon'!$J8) | K168: =IF('Leah Hanlon'!$B8="","",'Leah Hanlon'!$K8) | L168: =IF('Leah Hanlon'!$B8="","",'Leah Hanlon'!$L8) | M168: =IF('Leah Hanlon'!$B8="","",'Leah Hanlon'!$M8) | N168: =IF('Leah Hanlon'!$B8="","",'Leah Hanlon'!$N8) | O168: =IF('Leah Hanlon'!$B8="","",'Leah Hanlon'!$O8) | P168: =IF('Leah Hanlon'!$B8="","",'Leah Hanlon'!$P8) | Q168: =IF('Leah Hanlon'!$B8="","","Leah Hanlon") | R168: =IF(OR($B168="",$I168="Complete",$L168=""),0,IF($L168<TODAY(),1,0)) -> 0 | S168: =IF(OR($B168="",$I168="Complete",$L168=""),0,IF(AND($L168>=TODAY(),$L168<=TODAY()+7),1,0)) -> 0 | T168: =IF(OR($B168="",$L168=""),"",$L168-TODAY()) | U168: =IF($B168="","",IF($I168="Complete",1,IF($J168="",0,$J168))) | V168: =IF($B168="",0,IF($N168="",0,1)) -> 0 | W168: =IF($B168="",0,1) -> 0
A169: =IF('Leah Hanlon'!$B9="","",'Leah Hanlon'!$A9) | B169: =IF('Leah Hanlon'!$B9="","",'Leah Hanlon'!$B9) | C169: =IF('Leah Hanlon'!$B9="","",'Leah Hanlon'!$C9) | D169: =IF('Leah Hanlon'!$B9="","",'Leah Hanlon'!$D9) | E169: =IF('Leah Hanlon'!$B9="","",'Leah Hanlon'!$E9) | F169: =IF('Leah Hanlon'!$B9="","",'Leah Hanlon'!$F9) | G169: =IF('Leah Hanlon'!$B9="","",'Leah Hanlon'!$G9) | H169: =IF('Leah Hanlon'!$B9="","",'Leah Hanlon'!$H9) | I169: =IF('Leah Hanlon'!$B9="","",'Leah Hanlon'!$I9) | J169: =IF('Leah Hanlon'!$B9="","",'Leah Hanlon'!$J9) | K169: =IF('Leah Hanlon'!$B9="","",'Leah Hanlon'!$K9) | L169: =IF('Leah Hanlon'!$B9="","",'Leah Hanlon'!$L9) | M169: =IF('Leah Hanlon'!$B9="","",'Leah Hanlon'!$M9) | N169: =IF('Leah Hanlon'!$B9="","",'Leah Hanlon'!$N9) | O169: =IF('Leah Hanlon'!$B9="","",'Leah Hanlon'!$O9) | P169: =IF('Leah Hanlon'!$B9="","",'Leah Hanlon'!$P9) | Q169: =IF('Leah Hanlon'!$B9="","","Leah Hanlon") | R169: =IF(OR($B169="",$I169="Complete",$L169=""),0,IF($L169<TODAY(),1,0)) -> 0 | S169: =IF(OR($B169="",$I169="Complete",$L169=""),0,IF(AND($L169>=TODAY(),$L169<=TODAY()+7),1,0)) -> 0 | T169: =IF(OR($B169="",$L169=""),"",$L169-TODAY()) | U169: =IF($B169="","",IF($I169="Complete",1,IF($J169="",0,$J169))) | V169: =IF($B169="",0,IF($N169="",0,1)) -> 0 | W169: =IF($B169="",0,1) -> 0
A170: =IF('Leah Hanlon'!$B10="","",'Leah Hanlon'!$A10) | B170: =IF('Leah Hanlon'!$B10="","",'Leah Hanlon'!$B10) | C170: =IF('Leah Hanlon'!$B10="","",'Leah Hanlon'!$C10) | D170: =IF('Leah Hanlon'!$B10="","",'Leah Hanlon'!$D10) | E170: =IF('Leah Hanlon'!$B10="","",'Leah Hanlon'!$E10) | F170: =IF('Leah Hanlon'!$B10="","",'Leah Hanlon'!$F10) | G170: =IF('Leah Hanlon'!$B10="","",'Leah Hanlon'!$G10) | H170: =IF('Leah Hanlon'!$B10="","",'Leah Hanlon'!$H10) | I170: =IF('Leah Hanlon'!$B10="","",'Leah Hanlon'!$I10) | J170: =IF('Leah Hanlon'!$B10="","",'Leah Hanlon'!$J10) | K170: =IF('Leah Hanlon'!$B10="","",'Leah Hanlon'!$K10) | L170: =IF('Leah Hanlon'!$B10="","",'Leah Hanlon'!$L10) | M170: =IF('Leah Hanlon'!$B10="","",'Leah Hanlon'!$M10) | N170: =IF('Leah Hanlon'!$B10="","",'Leah Hanlon'!$N10) | O170: =IF('Leah Hanlon'!$B10="","",'Leah Hanlon'!$O10) | P170: =IF('Leah Hanlon'!$B10="","",'Leah Hanlon'!$P10) | Q170: =IF('Leah Hanlon'!$B10="","","Leah Hanlon") | R170: =IF(OR($B170="",$I170="Complete",$L170=""),0,IF($L170<TODAY(),1,0)) -> 0 | S170: =IF(OR($B170="",$I170="Complete",$L170=""),0,IF(AND($L170>=TODAY(),$L170<=TODAY()+7),1,0)) -> 0 | T170: =IF(OR($B170="",$L170=""),"",$L170-TODAY()) | U170: =IF($B170="","",IF($I170="Complete",1,IF($J170="",0,$J170))) | V170: =IF($B170="",0,IF($N170="",0,1)) -> 0 | W170: =IF($B170="",0,1) -> 0
A171: =IF('Leah Hanlon'!$B11="","",'Leah Hanlon'!$A11) | B171: =IF('Leah Hanlon'!$B11="","",'Leah Hanlon'!$B11) | C171: =IF('Leah Hanlon'!$B11="","",'Leah Hanlon'!$C11) | D171: =IF('Leah Hanlon'!$B11="","",'Leah Hanlon'!$D11) | E171: =IF('Leah Hanlon'!$B11="","",'Leah Hanlon'!$E11) | F171: =IF('Leah Hanlon'!$B11="","",'Leah Hanlon'!$F11) | G171: =IF('Leah Hanlon'!$B11="","",'Leah Hanlon'!$G11) | H171: =IF('Leah Hanlon'!$B11="","",'Leah Hanlon'!$H11) | I171: =IF('Leah Hanlon'!$B11="","",'Leah Hanlon'!$I11) | J171: =IF('Leah Hanlon'!$B11="","",'Leah Hanlon'!$J11) | K171: =IF('Leah Hanlon'!$B11="","",'Leah Hanlon'!$K11) | L171: =IF('Leah Hanlon'!$B11="","",'Leah Hanlon'!$L11) | M171: =IF('Leah Hanlon'!$B11="","",'Leah Hanlon'!$M11) | N171: =IF('Leah Hanlon'!$B11="","",'Leah Hanlon'!$N11) | O171: =IF('Leah Hanlon'!$B11="","",'Leah Hanlon'!$O11) | P171: =IF('Leah Hanlon'!$B11="","",'Leah Hanlon'!$P11) | Q171: =IF('Leah Hanlon'!$B11="","","Leah Hanlon") | R171: =IF(OR($B171="",$I171="Complete",$L171=""),0,IF($L171<TODAY(),1,0)) -> 0 | S171: =IF(OR($B171="",$I171="Complete",$L171=""),0,IF(AND($L171>=TODAY(),$L171<=TODAY()+7),1,0)) -> 0 | T171: =IF(OR($B171="",$L171=""),"",$L171-TODAY()) | U171: =IF($B171="","",IF($I171="Complete",1,IF($J171="",0,$J171))) | V171: =IF($B171="",0,IF($N171="",0,1)) -> 0 | W171: =IF($B171="",0,1) -> 0
A172: =IF('Leah Hanlon'!$B12="","",'Leah Hanlon'!$A12) | B172: =IF('Leah Hanlon'!$B12="","",'Leah Hanlon'!$B12) | C172: =IF('Leah Hanlon'!$B12="","",'Leah Hanlon'!$C12) | D172: =IF('Leah Hanlon'!$B12="","",'Leah Hanlon'!$D12) | E172: =IF('Leah Hanlon'!$B12="","",'Leah Hanlon'!$E12) | F172: =IF('Leah Hanlon'!$B12="","",'Leah Hanlon'!$F12) | G172: =IF('Leah Hanlon'!$B12="","",'Leah Hanlon'!$G12) | H172: =IF('Leah Hanlon'!$B12="","",'Leah Hanlon'!$H12) | I172: =IF('Leah Hanlon'!$B12="","",'Leah Hanlon'!$I12) | J172: =IF('Leah Hanlon'!$B12="","",'Leah Hanlon'!$J12) | K172: =IF('Leah Hanlon'!$B12="","",'Leah Hanlon'!$K12) | L172: =IF('Leah Hanlon'!$B12="","",'Leah Hanlon'!$L12) | M172: =IF('Leah Hanlon'!$B12="","",'Leah Hanlon'!$M12) | N172: =IF('Leah Hanlon'!$B12="","",'Leah Hanlon'!$N12) | O172: =IF('Leah Hanlon'!$B12="","",'Leah Hanlon'!$O12) | P172: =IF('Leah Hanlon'!$B12="","",'Leah Hanlon'!$P12) | Q172: =IF('Leah Hanlon'!$B12="","","Leah Hanlon") | R172: =IF(OR($B172="",$I172="Complete",$L172=""),0,IF($L172<TODAY(),1,0)) -> 0 | S172: =IF(OR($B172="",$I172="Complete",$L172=""),0,IF(AND($L172>=TODAY(),$L172<=TODAY()+7),1,0)) -> 0 | T172: =IF(OR($B172="",$L172=""),"",$L172-TODAY()) | U172: =IF($B172="","",IF($I172="Complete",1,IF($J172="",0,$J172))) | V172: =IF($B172="",0,IF($N172="",0,1)) -> 0 | W172: =IF($B172="",0,1) -> 0
A173: =IF('Leah Hanlon'!$B13="","",'Leah Hanlon'!$A13) | B173: =IF('Leah Hanlon'!$B13="","",'Leah Hanlon'!$B13) | C173: =IF('Leah Hanlon'!$B13="","",'Leah Hanlon'!$C13) | D173: =IF('Leah Hanlon'!$B13="","",'Leah Hanlon'!$D13) | E173: =IF('Leah Hanlon'!$B13="","",'Leah Hanlon'!$E13) | F173: =IF('Leah Hanlon'!$B13="","",'Leah Hanlon'!$F13) | G173: =IF('Leah Hanlon'!$B13="","",'Leah Hanlon'!$G13) | H173: =IF('Leah Hanlon'!$B13="","",'Leah Hanlon'!$H13) | I173: =IF('Leah Hanlon'!$B13="","",'Leah Hanlon'!$I13) | J173: =IF('Leah Hanlon'!$B13="","",'Leah Hanlon'!$J13) | K173: =IF('Leah Hanlon'!$B13="","",'Leah Hanlon'!$K13) | L173: =IF('Leah Hanlon'!$B13="","",'Leah Hanlon'!$L13) | M173: =IF('Leah Hanlon'!$B13="","",'Leah Hanlon'!$M13) | N173: =IF('Leah Hanlon'!$B13="","",'Leah Hanlon'!$N13) | O173: =IF('Leah Hanlon'!$B13="","",'Leah Hanlon'!$O13) | P173: =IF('Leah Hanlon'!$B13="","",'Leah Hanlon'!$P13) | Q173: =IF('Leah Hanlon'!$B13="","","Leah Hanlon") | R173: =IF(OR($B173="",$I173="Complete",$L173=""),0,IF($L173<TODAY(),1,0)) -> 0 | S173: =IF(OR($B173="",$I173="Complete",$L173=""),0,IF(AND($L173>=TODAY(),$L173<=TODAY()+7),1,0)) -> 0 | T173: =IF(OR($B173="",$L173=""),"",$L173-TODAY()) | U173: =IF($B173="","",IF($I173="Complete",1,IF($J173="",0,$J173))) | V173: =IF($B173="",0,IF($N173="",0,1)) -> 0 | W173: =IF($B173="",0,1) -> 0
A174: =IF('Leah Hanlon'!$B14="","",'Leah Hanlon'!$A14) | B174: =IF('Leah Hanlon'!$B14="","",'Leah Hanlon'!$B14) | C174: =IF('Leah Hanlon'!$B14="","",'Leah Hanlon'!$C14) | D174: =IF('Leah Hanlon'!$B14="","",'Leah Hanlon'!$D14) | E174: =IF('Leah Hanlon'!$B14="","",'Leah Hanlon'!$E14) | F174: =IF('Leah Hanlon'!$B14="","",'Leah Hanlon'!$F14) | G174: =IF('Leah Hanlon'!$B14="","",'Leah Hanlon'!$G14) | H174: =IF('Leah Hanlon'!$B14="","",'Leah Hanlon'!$H14) | I174: =IF('Leah Hanlon'!$B14="","",'Leah Hanlon'!$I14) | J174: =IF('Leah Hanlon'!$B14="","",'Leah Hanlon'!$J14) | K174: =IF('Leah Hanlon'!$B14="","",'Leah Hanlon'!$K14) | L174: =IF('Leah Hanlon'!$B14="","",'Leah Hanlon'!$L14) | M174: =IF('Leah Hanlon'!$B14="","",'Leah Hanlon'!$M14) | N174: =IF('Leah Hanlon'!$B14="","",'Leah Hanlon'!$N14) | O174: =IF('Leah Hanlon'!$B14="","",'Leah Hanlon'!$O14) | P174: =IF('Leah Hanlon'!$B14="","",'Leah Hanlon'!$P14) | Q174: =IF('Leah Hanlon'!$B14="","","Leah Hanlon") | R174: =IF(OR($B174="",$I174="Complete",$L174=""),0,IF($L174<TODAY(),1,0)) -> 0 | S174: =IF(OR($B174="",$I174="Complete",$L174=""),0,IF(AND($L174>=TODAY(),$L174<=TODAY()+7),1,0)) -> 0 | T174: =IF(OR($B174="",$L174=""),"",$L174-TODAY()) | U174: =IF($B174="","",IF($I174="Complete",1,IF($J174="",0,$J174))) | V174: =IF($B174="",0,IF($N174="",0,1)) -> 0 | W174: =IF($B174="",0,1) -> 0
A175: =IF('Leah Hanlon'!$B15="","",'Leah Hanlon'!$A15) | B175: =IF('Leah Hanlon'!$B15="","",'Leah Hanlon'!$B15) | C175: =IF('Leah Hanlon'!$B15="","",'Leah Hanlon'!$C15) | D175: =IF('Leah Hanlon'!$B15="","",'Leah Hanlon'!$D15) | E175: =IF('Leah Hanlon'!$B15="","",'Leah Hanlon'!$E15) | F175: =IF('Leah Hanlon'!$B15="","",'Leah Hanlon'!$F15) | G175: =IF('Leah Hanlon'!$B15="","",'Leah Hanlon'!$G15) | H175: =IF('Leah Hanlon'!$B15="","",'Leah Hanlon'!$H15) | I175: =IF('Leah Hanlon'!$B15="","",'Leah Hanlon'!$I15) | J175: =IF('Leah Hanlon'!$B15="","",'Leah Hanlon'!$J15) | K175: =IF('Leah Hanlon'!$B15="","",'Leah Hanlon'!$K15) | L175: =IF('Leah Hanlon'!$B15="","",'Leah Hanlon'!$L15) | M175: =IF('Leah Hanlon'!$B15="","",'Leah Hanlon'!$M15) | N175: =IF('Leah Hanlon'!$B15="","",'Leah Hanlon'!$N15) | O175: =IF('Leah Hanlon'!$B15="","",'Leah Hanlon'!$O15) | P175: =IF('Leah Hanlon'!$B15="","",'Leah Hanlon'!$P15) | Q175: =IF('Leah Hanlon'!$B15="","","Leah Hanlon") | R175: =IF(OR($B175="",$I175="Complete",$L175=""),0,IF($L175<TODAY(),1,0)) -> 0 | S175: =IF(OR($B175="",$I175="Complete",$L175=""),0,IF(AND($L175>=TODAY(),$L175<=TODAY()+7),1,0)) -> 0 | T175: =IF(OR($B175="",$L175=""),"",$L175-TODAY()) | U175: =IF($B175="","",IF($I175="Complete",1,IF($J175="",0,$J175))) | V175: =IF($B175="",0,IF($N175="",0,1)) -> 0 | W175: =IF($B175="",0,1) -> 0
A176: =IF('Leah Hanlon'!$B16="","",'Leah Hanlon'!$A16) | B176: =IF('Leah Hanlon'!$B16="","",'Leah Hanlon'!$B16) | C176: =IF('Leah Hanlon'!$B16="","",'Leah Hanlon'!$C16) | D176: =IF('Leah Hanlon'!$B16="","",'Leah Hanlon'!$D16) | E176: =IF('Leah Hanlon'!$B16="","",'Leah Hanlon'!$E16) | F176: =IF('Leah Hanlon'!$B16="","",'Leah Hanlon'!$F16) | G176: =IF('Leah Hanlon'!$B16="","",'Leah Hanlon'!$G16) | H176: =IF('Leah Hanlon'!$B16="","",'Leah Hanlon'!$H16) | I176: =IF('Leah Hanlon'!$B16="","",'Leah Hanlon'!$I16) | J176: =IF('Leah Hanlon'!$B16="","",'Leah Hanlon'!$J16) | K176: =IF('Leah Hanlon'!$B16="","",'Leah Hanlon'!$K16) | L176: =IF('Leah Hanlon'!$B16="","",'Leah Hanlon'!$L16) | M176: =IF('Leah Hanlon'!$B16="","",'Leah Hanlon'!$M16) | N176: =IF('Leah Hanlon'!$B16="","",'Leah Hanlon'!$N16) | O176: =IF('Leah Hanlon'!$B16="","",'Leah Hanlon'!$O16) | P176: =IF('Leah Hanlon'!$B16="","",'Leah Hanlon'!$P16) | Q176: =IF('Leah Hanlon'!$B16="","","Leah Hanlon") | R176: =IF(OR($B176="",$I176="Complete",$L176=""),0,IF($L176<TODAY(),1,0)) -> 0 | S176: =IF(OR($B176="",$I176="Complete",$L176=""),0,IF(AND($L176>=TODAY(),$L176<=TODAY()+7),1,0)) -> 0 | T176: =IF(OR($B176="",$L176=""),"",$L176-TODAY()) | U176: =IF($B176="","",IF($I176="Complete",1,IF($J176="",0,$J176))) | V176: =IF($B176="",0,IF($N176="",0,1)) -> 0 | W176: =IF($B176="",0,1) -> 0
... A204: =IF('Leah Hanlon'!$B44="","",'Leah Hanlon'!$A44) | B204: =IF('Leah Hanlon'!$B44="","",'Leah Hanlon'!$B44) | C204: =IF('Leah Hanlon'!$B44="","",'Leah Hanlon'!$C44) | D204: =IF('Leah Hanlon'!$B44="","",'Leah Hanlon'!$D44) | E204: =IF('Leah Hanlon'!$B44="","",'Leah Hanlon'!$E44) | F204: =IF('Leah Hanlon'!$B44="","",'Leah Hanlon'!$F44) | G204: =IF('Leah Hanlon'!$B44="","",'Leah Hanlon'!$G44) | H204: =IF('Leah Hanlon'!$B44="","",'Leah Hanlon'!$H44) | I204: =IF('Leah Hanlon'!$B44="","",'Leah Hanlon'!$I44) | J204: =IF('Leah Hanlon'!$B44="","",'Leah Hanlon'!$J44) | K204: =IF('Leah Hanlon'!$B44="","",'Leah Hanlon'!$K44) | L204: =IF('Leah Hanlon'!$B44="","",'Leah Hanlon'!$L44) | M204: =IF('Leah Hanlon'!$B44="","",'Leah Hanlon'!$M44) | N204: =IF('Leah Hanlon'!$B44="","",'Leah Hanlon'!$N44) | O204: =IF('Leah Hanlon'!$B44="","",'Leah Hanlon'!$O44) | P204: =IF('Leah Hanlon'!$B44="","",'Leah Hanlon'!$P44) | Q204: =IF('Leah Hanlon'!$B44="","","Leah Hanlon") | R204: =IF(OR($B204="",$I204="Complete",$L204=""),0,IF($L204<TODAY(),1,0)) -> 0 | S204: =IF(OR($B204="",$I204="Complete",$L204=""),0,IF(AND($L204>=TODAY(),$L204<=TODAY()+7),1,0)) -> 0 | T204: =IF(OR($B204="",$L204=""),"",$L204-TODAY()) | U204: =IF($B204="","",IF($I204="Complete",1,IF($J204="",0,$J204))) | V204: =IF($B204="",0,IF($N204="",0,1)) -> 0 | W204: =IF($B204="",0,1) -> 0
A205: =IF('Jamie Lavigne'!$B5="","",'Jamie Lavigne'!$A5) -> JL-001 | B205: =IF('Jamie Lavigne'!$B5="","",'Jamie Lavigne'!$B5) -> P1-1 | C205: =IF('Jamie Lavigne'!$B5="","",'Jamie Lavigne'!$C5) -> 1 – Unified Development System | D205: =IF('Jamie Lavigne'!$B5="","",'Jamie Lavigne'!$D5) -> Implement standardized Mutual Evaluation Process (MEP) across all brands | E205: =IF('Jamie Lavigne'!$B5="","",'Jamie Lavigne'!$E5) -> Jamie Lavigne | F205: =IF('Jamie Lavigne'!$B5="","",'Jamie Lavigne'!$F5) -> Contributor | G205: =IF('Jamie Lavigne'!$B5="","",'Jamie Lavigne'!$G5) -> Training Section 1-3 in Fran Dev 101 | H205: =IF('Jamie Lavigne'!$B5="","",'Jamie Lavigne'!$H5) -> Medium | I205: =IF('Jamie Lavigne'!$B5="","",'Jamie Lavigne'!$I5) -> In Progress | J205: =IF('Jamie Lavigne'!$B5="","",'Jamie Lavigne'!$J5) -> 0.5 | K205: =IF('Jamie Lavigne'!$B5="","",'Jamie Lavigne'!$K5) -> 46162 | L205: =IF('Jamie Lavigne'!$B5="","",'Jamie Lavigne'!$L5) -> 46186 | M205: =IF('Jamie Lavigne'!$B5="","",'Jamie Lavigne'!$M5) -> 0 | N205: =IF('Jamie Lavigne'!$B5="","",'Jamie Lavigne'!$N5) -> 0 | O205: =IF('Jamie Lavigne'!$B5="","",'Jamie Lavigne'!$O5) -> Assigned 5/20 | P205: =IF('Jamie Lavigne'!$B5="","",'Jamie Lavigne'!$P5) -> Complete sections 2-3 | Q205: =IF('Jamie Lavigne'!$B5="","","Jamie Lavigne") -> Jamie Lavigne | R205: =IF(OR($B205="",$I205="Complete",$L205=""),0,IF($L205<TODAY(),1,0)) -> 0 | S205: =IF(OR($B205="",$I205="Complete",$L205=""),0,IF(AND($L205>=TODAY(),$L205<=TODAY()+7),1,0)) -> 0 | T205: =IF(OR($B205="",$L205=""),"",$L205-TODAY()) -> 16 | U205: =IF($B205="","",IF($I205="Complete",1,IF($J205="",0,$J205))) -> 0.5 | V205: =IF($B205="",0,IF($N205="",0,1)) -> 0 | W205: =IF($B205="",0,1) -> 1
A206: =IF('Jamie Lavigne'!$B6="","",'Jamie Lavigne'!$A6) -> JL-002 | B206: =IF('Jamie Lavigne'!$B6="","",'Jamie Lavigne'!$B6) -> P6-1 | C206: =IF('Jamie Lavigne'!$B6="","",'Jamie Lavigne'!$C6) -> 6 – Automation & Content | D206: =IF('Jamie Lavigne'!$B6="","",'Jamie Lavigne'!$D6) -> Develop standardized brand overview videos | E206: =IF('Jamie Lavigne'!$B6="","",'Jamie Lavigne'!$E6) -> Jamie Lavigne | F206: =IF('Jamie Lavigne'!$B6="","",'Jamie Lavigne'!$F6) -> Support | G206: =IF('Jamie Lavigne'!$B6="","",'Jamie Lavigne'!$G6) -> Provide Signature 7 sample / sub footage | H206: =IF('Jamie Lavigne'!$B6="","",'Jamie Lavigne'!$H6) -> Low | I206: =IF('Jamie Lavigne'!$B6="","",'Jamie Lavigne'!$I6) -> In Progress | J206: =IF('Jamie Lavigne'!$B6="","",'Jamie Lavigne'!$J6) -> 0.5 | K206: =IF('Jamie Lavigne'!$B6="","",'Jamie Lavigne'!$K6) -> 46152 | L206: =IF('Jamie Lavigne'!$B6="","",'Jamie Lavigne'!$L6) -> 46193 | M206: =IF('Jamie Lavigne'!$B6="","",'Jamie Lavigne'!$M6) -> 0 | N206: =IF('Jamie Lavigne'!$B6="","",'Jamie Lavigne'!$N6) -> 0 | O206: =IF('Jamie Lavigne'!$B6="","",'Jamie Lavigne'!$O6) -> Sample available for The Seals & Prism | P206: =IF('Jamie Lavigne'!$B6="","",'Jamie Lavigne'!$P6) -> Share footage with Chadwick | Q206: =IF('Jamie Lavigne'!$B6="","","Jamie Lavigne") -> Jamie Lavigne | R206: =IF(OR($B206="",$I206="Complete",$L206=""),0,IF($L206<TODAY(),1,0)) -> 0 | S206: =IF(OR($B206="",$I206="Complete",$L206=""),0,IF(AND($L206>=TODAY(),$L206<=TODAY()+7),1,0)) -> 0 | T206: =IF(OR($B206="",$L206=""),"",$L206-TODAY()) -> 23 | U206: =IF($B206="","",IF($I206="Complete",1,IF($J206="",0,$J206))) -> 0.5 | V206: =IF($B206="",0,IF($N206="",0,1)) -> 0 | W206: =IF($B206="",0,1) -> 1
A207: =IF('Jamie Lavigne'!$B7="","",'Jamie Lavigne'!$A7) | B207: =IF('Jamie Lavigne'!$B7="","",'Jamie Lavigne'!$B7) | C207: =IF('Jamie Lavigne'!$B7="","",'Jamie Lavigne'!$C7) | D207: =IF('Jamie Lavigne'!$B7="","",'Jamie Lavigne'!$D7) | E207: =IF('Jamie Lavigne'!$B7="","",'Jamie Lavigne'!$E7) | F207: =IF('Jamie Lavigne'!$B7="","",'Jamie Lavigne'!$F7) | G207: =IF('Jamie Lavigne'!$B7="","",'Jamie Lavigne'!$G7) | H207: =IF('Jamie Lavigne'!$B7="","",'Jamie Lavigne'!$H7) | I207: =IF('Jamie Lavigne'!$B7="","",'Jamie Lavigne'!$I7) | J207: =IF('Jamie Lavigne'!$B7="","",'Jamie Lavigne'!$J7) | K207: =IF('Jamie Lavigne'!$B7="","",'Jamie Lavigne'!$K7) | L207: =IF('Jamie Lavigne'!$B7="","",'Jamie Lavigne'!$L7) | M207: =IF('Jamie Lavigne'!$B7="","",'Jamie Lavigne'!$M7) | N207: =IF('Jamie Lavigne'!$B7="","",'Jamie Lavigne'!$N7) | O207: =IF('Jamie Lavigne'!$B7="","",'Jamie Lavigne'!$O7) | P207: =IF('Jamie Lavigne'!$B7="","",'Jamie Lavigne'!$P7) | Q207: =IF('Jamie Lavigne'!$B7="","","Jamie Lavigne") | R207: =IF(OR($B207="",$I207="Complete",$L207=""),0,IF($L207<TODAY(),1,0)) -> 0 | S207: =IF(OR($B207="",$I207="Complete",$L207=""),0,IF(AND($L207>=TODAY(),$L207<=TODAY()+7),1,0)) -> 0 | T207: =IF(OR($B207="",$L207=""),"",$L207-TODAY()) | U207: =IF($B207="","",IF($I207="Complete",1,IF($J207="",0,$J207))) | V207: =IF($B207="",0,IF($N207="",0,1)) -> 0 | W207: =IF($B207="",0,1) -> 0
A208: =IF('Jamie Lavigne'!$B8="","",'Jamie Lavigne'!$A8) | B208: =IF('Jamie Lavigne'!$B8="","",'Jamie Lavigne'!$B8) | C208: =IF('Jamie Lavigne'!$B8="","",'Jamie Lavigne'!$C8) | D208: =IF('Jamie Lavigne'!$B8="","",'Jamie Lavigne'!$D8) | E208: =IF('Jamie Lavigne'!$B8="","",'Jamie Lavigne'!$E8) | F208: =IF('Jamie Lavigne'!$B8="","",'Jamie Lavigne'!$F8) | G208: =IF('Jamie Lavigne'!$B8="","",'Jamie Lavigne'!$G8) | H208: =IF('Jamie Lavigne'!$B8="","",'Jamie Lavigne'!$H8) | I208: =IF('Jamie Lavigne'!$B8="","",'Jamie Lavigne'!$I8) | J208: =IF('Jamie Lavigne'!$B8="","",'Jamie Lavigne'!$J8) | K208: =IF('Jamie Lavigne'!$B8="","",'Jamie Lavigne'!$K8) | L208: =IF('Jamie Lavigne'!$B8="","",'Jamie Lavigne'!$L8) | M208: =IF('Jamie Lavigne'!$B8="","",'Jamie Lavigne'!$M8) | N208: =IF('Jamie Lavigne'!$B8="","",'Jamie Lavigne'!$N8) | O208: =IF('Jamie Lavigne'!$B8="","",'Jamie Lavigne'!$O8) | P208: =IF('Jamie Lavigne'!$B8="","",'Jamie Lavigne'!$P8) | Q208: =IF('Jamie Lavigne'!$B8="","","Jamie Lavigne") | R208: =IF(OR($B208="",$I208="Complete",$L208=""),0,IF($L208<TODAY(),1,0)) -> 0 | S208: =IF(OR($B208="",$I208="Complete",$L208=""),0,IF(AND($L208>=TODAY(),$L208<=TODAY()+7),1,0)) -> 0 | T208: =IF(OR($B208="",$L208=""),"",$L208-TODAY()) | U208: =IF($B208="","",IF($I208="Complete",1,IF($J208="",0,$J208))) | V208: =IF($B208="",0,IF($N208="",0,1)) -> 0 | W208: =IF($B208="",0,1) -> 0
A209: =IF('Jamie Lavigne'!$B9="","",'Jamie Lavigne'!$A9) | B209: =IF('Jamie Lavigne'!$B9="","",'Jamie Lavigne'!$B9) | C209: =IF('Jamie Lavigne'!$B9="","",'Jamie Lavigne'!$C9) | D209: =IF('Jamie Lavigne'!$B9="","",'Jamie Lavigne'!$D9) | E209: =IF('Jamie Lavigne'!$B9="","",'Jamie Lavigne'!$E9) | F209: =IF('Jamie Lavigne'!$B9="","",'Jamie Lavigne'!$F9) | G209: =IF('Jamie Lavigne'!$B9="","",'Jamie Lavigne'!$G9) | H209: =IF('Jamie Lavigne'!$B9="","",'Jamie Lavigne'!$H9) | I209: =IF('Jamie Lavigne'!$B9="","",'Jamie Lavigne'!$I9) | J209: =IF('Jamie Lavigne'!$B9="","",'Jamie Lavigne'!$J9) | K209: =IF('Jamie Lavigne'!$B9="","",'Jamie Lavigne'!$K9) | L209: =IF('Jamie Lavigne'!$B9="","",'Jamie Lavigne'!$L9) | M209: =IF('Jamie Lavigne'!$B9="","",'Jamie Lavigne'!$M9) | N209: =IF('Jamie Lavigne'!$B9="","",'Jamie Lavigne'!$N9) | O209: =IF('Jamie Lavigne'!$B9="","",'Jamie Lavigne'!$O9) | P209: =IF('Jamie Lavigne'!$B9="","",'Jamie Lavigne'!$P9) | Q209: =IF('Jamie Lavigne'!$B9="","","Jamie Lavigne") | R209: =IF(OR($B209="",$I209="Complete",$L209=""),0,IF($L209<TODAY(),1,0)) -> 0 | S209: =IF(OR($B209="",$I209="Complete",$L209=""),0,IF(AND($L209>=TODAY(),$L209<=TODAY()+7),1,0)) -> 0 | T209: =IF(OR($B209="",$L209=""),"",$L209-TODAY()) | U209: =IF($B209="","",IF($I209="Complete",1,IF($J209="",0,$J209))) | V209: =IF($B209="",0,IF($N209="",0,1)) -> 0 | W209: =IF($B209="",0,1) -> 0
A210: =IF('Jamie Lavigne'!$B10="","",'Jamie Lavigne'!$A10) | B210: =IF('Jamie Lavigne'!$B10="","",'Jamie Lavigne'!$B10) | C210: =IF('Jamie Lavigne'!$B10="","",'Jamie Lavigne'!$C10) | D210: =IF('Jamie Lavigne'!$B10="","",'Jamie Lavigne'!$D10) | E210: =IF('Jamie Lavigne'!$B10="","",'Jamie Lavigne'!$E10) | F210: =IF('Jamie Lavigne'!$B10="","",'Jamie Lavigne'!$F10) | G210: =IF('Jamie Lavigne'!$B10="","",'Jamie Lavigne'!$G10) | H210: =IF('Jamie Lavigne'!$B10="","",'Jamie Lavigne'!$H10) | I210: =IF('Jamie Lavigne'!$B10="","",'Jamie Lavigne'!$I10) | J210: =IF('Jamie Lavigne'!$B10="","",'Jamie Lavigne'!$J10) | K210: =IF('Jamie Lavigne'!$B10="","",'Jamie Lavigne'!$K10) | L210: =IF('Jamie Lavigne'!$B10="","",'Jamie Lavigne'!$L10) | M210: =IF('Jamie Lavigne'!$B10="","",'Jamie Lavigne'!$M10) | N210: =IF('Jamie Lavigne'!$B10="","",'Jamie Lavigne'!$N10) | O210: =IF('Jamie Lavigne'!$B10="","",'Jamie Lavigne'!$O10) | P210: =IF('Jamie Lavigne'!$B10="","",'Jamie Lavigne'!$P10) | Q210: =IF('Jamie Lavigne'!$B10="","","Jamie Lavigne") | R210: =IF(OR($B210="",$I210="Complete",$L210=""),0,IF($L210<TODAY(),1,0)) -> 0 | S210: =IF(OR($B210="",$I210="Complete",$L210=""),0,IF(AND($L210>=TODAY(),$L210<=TODAY()+7),1,0)) -> 0 | T210: =IF(OR($B210="",$L210=""),"",$L210-TODAY()) | U210: =IF($B210="","",IF($I210="Complete",1,IF($J210="",0,$J210))) | V210: =IF($B210="",0,IF($N210="",0,1)) -> 0 | W210: =IF($B210="",0,1) -> 0
A211: =IF('Jamie Lavigne'!$B11="","",'Jamie Lavigne'!$A11) | B211: =IF('Jamie Lavigne'!$B11="","",'Jamie Lavigne'!$B11) | C211: =IF('Jamie Lavigne'!$B11="","",'Jamie Lavigne'!$C11) | D211: =IF('Jamie Lavigne'!$B11="","",'Jamie Lavigne'!$D11) | E211: =IF('Jamie Lavigne'!$B11="","",'Jamie Lavigne'!$E11) | F211: =IF('Jamie Lavigne'!$B11="","",'Jamie Lavigne'!$F11) | G211: =IF('Jamie Lavigne'!$B11="","",'Jamie Lavigne'!$G11) | H211: =IF('Jamie Lavigne'!$B11="","",'Jamie Lavigne'!$H11) | I211: =IF('Jamie Lavigne'!$B11="","",'Jamie Lavigne'!$I11) | J211: =IF('Jamie Lavigne'!$B11="","",'Jamie Lavigne'!$J11) | K211: =IF('Jamie Lavigne'!$B11="","",'Jamie Lavigne'!$K11) | L211: =IF('Jamie Lavigne'!$B11="","",'Jamie Lavigne'!$L11) | M211: =IF('Jamie Lavigne'!$B11="","",'Jamie Lavigne'!$M11) | N211: =IF('Jamie Lavigne'!$B11="","",'Jamie Lavigne'!$N11) | O211: =IF('Jamie Lavigne'!$B11="","",'Jamie Lavigne'!$O11) | P211: =IF('Jamie Lavigne'!$B11="","",'Jamie Lavigne'!$P11) | Q211: =IF('Jamie Lavigne'!$B11="","","Jamie Lavigne") | R211: =IF(OR($B211="",$I211="Complete",$L211=""),0,IF($L211<TODAY(),1,0)) -> 0 | S211: =IF(OR($B211="",$I211="Complete",$L211=""),0,IF(AND($L211>=TODAY(),$L211<=TODAY()+7),1,0)) -> 0 | T211: =IF(OR($B211="",$L211=""),"",$L211-TODAY()) | U211: =IF($B211="","",IF($I211="Complete",1,IF($J211="",0,$J211))) | V211: =IF($B211="",0,IF($N211="",0,1)) -> 0 | W211: =IF($B211="",0,1) -> 0
A212: =IF('Jamie Lavigne'!$B12="","",'Jamie Lavigne'!$A12) | B212: =IF('Jamie Lavigne'!$B12="","",'Jamie Lavigne'!$B12) | C212: =IF('Jamie Lavigne'!$B12="","",'Jamie Lavigne'!$C12) | D212: =IF('Jamie Lavigne'!$B12="","",'Jamie Lavigne'!$D12) | E212: =IF('Jamie Lavigne'!$B12="","",'Jamie Lavigne'!$E12) | F212: =IF('Jamie Lavigne'!$B12="","",'Jamie Lavigne'!$F12) | G212: =IF('Jamie Lavigne'!$B12="","",'Jamie Lavigne'!$G12) | H212: =IF('Jamie Lavigne'!$B12="","",'Jamie Lavigne'!$H12) | I212: =IF('Jamie Lavigne'!$B12="","",'Jamie Lavigne'!$I12) | J212: =IF('Jamie Lavigne'!$B12="","",'Jamie Lavigne'!$J12) | K212: =IF('Jamie Lavigne'!$B12="","",'Jamie Lavigne'!$K12) | L212: =IF('Jamie Lavigne'!$B12="","",'Jamie Lavigne'!$L12) | M212: =IF('Jamie Lavigne'!$B12="","",'Jamie Lavigne'!$M12) | N212: =IF('Jamie Lavigne'!$B12="","",'Jamie Lavigne'!$N12) | O212: =IF('Jamie Lavigne'!$B12="","",'Jamie Lavigne'!$O12) | P212: =IF('Jamie Lavigne'!$B12="","",'Jamie Lavigne'!$P12) | Q212: =IF('Jamie Lavigne'!$B12="","","Jamie Lavigne") | R212: =IF(OR($B212="",$I212="Complete",$L212=""),0,IF($L212<TODAY(),1,0)) -> 0 | S212: =IF(OR($B212="",$I212="Complete",$L212=""),0,IF(AND($L212>=TODAY(),$L212<=TODAY()+7),1,0)) -> 0 | T212: =IF(OR($B212="",$L212=""),"",$L212-TODAY()) | U212: =IF($B212="","",IF($I212="Complete",1,IF($J212="",0,$J212))) | V212: =IF($B212="",0,IF($N212="",0,1)) -> 0 | W212: =IF($B212="",0,1) -> 0
A213: =IF('Jamie Lavigne'!$B13="","",'Jamie Lavigne'!$A13) | B213: =IF('Jamie Lavigne'!$B13="","",'Jamie Lavigne'!$B13) | C213: =IF('Jamie Lavigne'!$B13="","",'Jamie Lavigne'!$C13) | D213: =IF('Jamie Lavigne'!$B13="","",'Jamie Lavigne'!$D13) | E213: =IF('Jamie Lavigne'!$B13="","",'Jamie Lavigne'!$E13) | F213: =IF('Jamie Lavigne'!$B13="","",'Jamie Lavigne'!$F13) | G213: =IF('Jamie Lavigne'!$B13="","",'Jamie Lavigne'!$G13) | H213: =IF('Jamie Lavigne'!$B13="","",'Jamie Lavigne'!$H13) | I213: =IF('Jamie Lavigne'!$B13="","",'Jamie Lavigne'!$I13) | J213: =IF('Jamie Lavigne'!$B13="","",'Jamie Lavigne'!$J13) | K213: =IF('Jamie Lavigne'!$B13="","",'Jamie Lavigne'!$K13) | L213: =IF('Jamie Lavigne'!$B13="","",'Jamie Lavigne'!$L13) | M213: =IF('Jamie Lavigne'!$B13="","",'Jamie Lavigne'!$M13) | N213: =IF('Jamie Lavigne'!$B13="","",'Jamie Lavigne'!$N13) | O213: =IF('Jamie Lavigne'!$B13="","",'Jamie Lavigne'!$O13) | P213: =IF('Jamie Lavigne'!$B13="","",'Jamie Lavigne'!$P13) | Q213: =IF('Jamie Lavigne'!$B13="","","Jamie Lavigne") | R213: =IF(OR($B213="",$I213="Complete",$L213=""),0,IF($L213<TODAY(),1,0)) -> 0 | S213: =IF(OR($B213="",$I213="Complete",$L213=""),0,IF(AND($L213>=TODAY(),$L213<=TODAY()+7),1,0)) -> 0 | T213: =IF(OR($B213="",$L213=""),"",$L213-TODAY()) | U213: =IF($B213="","",IF($I213="Complete",1,IF($J213="",0,$J213))) | V213: =IF($B213="",0,IF($N213="",0,1)) -> 0 | W213: =IF($B213="",0,1) -> 0
A214: =IF('Jamie Lavigne'!$B14="","",'Jamie Lavigne'!$A14) | B214: =IF('Jamie Lavigne'!$B14="","",'Jamie Lavigne'!$B14) | C214: =IF('Jamie Lavigne'!$B14="","",'Jamie Lavigne'!$C14) | D214: =IF('Jamie Lavigne'!$B14="","",'Jamie Lavigne'!$D14) | E214: =IF('Jamie Lavigne'!$B14="","",'Jamie Lavigne'!$E14) | F214: =IF('Jamie Lavigne'!$B14="","",'Jamie Lavigne'!$F14) | G214: =IF('Jamie Lavigne'!$B14="","",'Jamie Lavigne'!$G14) | H214: =IF('Jamie Lavigne'!$B14="","",'Jamie Lavigne'!$H14) | I214: =IF('Jamie Lavigne'!$B14="","",'Jamie Lavigne'!$I14) | J214: =IF('Jamie Lavigne'!$B14="","",'Jamie Lavigne'!$J14) | K214: =IF('Jamie Lavigne'!$B14="","",'Jamie Lavigne'!$K14) | L214: =IF('Jamie Lavigne'!$B14="","",'Jamie Lavigne'!$L14) | M214: =IF('Jamie Lavigne'!$B14="","",'Jamie Lavigne'!$M14) | N214: =IF('Jamie Lavigne'!$B14="","",'Jamie Lavigne'!$N14) | O214: =IF('Jamie Lavigne'!$B14="","",'Jamie Lavigne'!$O14) | P214: =IF('Jamie Lavigne'!$B14="","",'Jamie Lavigne'!$P14) | Q214: =IF('Jamie Lavigne'!$B14="","","Jamie Lavigne") | R214: =IF(OR($B214="",$I214="Complete",$L214=""),0,IF($L214<TODAY(),1,0)) -> 0 | S214: =IF(OR($B214="",$I214="Complete",$L214=""),0,IF(AND($L214>=TODAY(),$L214<=TODAY()+7),1,0)) -> 0 | T214: =IF(OR($B214="",$L214=""),"",$L214-TODAY()) | U214: =IF($B214="","",IF($I214="Complete",1,IF($J214="",0,$J214))) | V214: =IF($B214="",0,IF($N214="",0,1)) -> 0 | W214: =IF($B214="",0,1) -> 0
A215: =IF('Jamie Lavigne'!$B15="","",'Jamie Lavigne'!$A15) | B215: =IF('Jamie Lavigne'!$B15="","",'Jamie Lavigne'!$B15) | C215: =IF('Jamie Lavigne'!$B15="","",'Jamie Lavigne'!$C15) | D215: =IF('Jamie Lavigne'!$B15="","",'Jamie Lavigne'!$D15) | E215: =IF('Jamie Lavigne'!$B15="","",'Jamie Lavigne'!$E15) | F215: =IF('Jamie Lavigne'!$B15="","",'Jamie Lavigne'!$F15) | G215: =IF('Jamie Lavigne'!$B15="","",'Jamie Lavigne'!$G15) | H215: =IF('Jamie Lavigne'!$B15="","",'Jamie Lavigne'!$H15) | I215: =IF('Jamie Lavigne'!$B15="","",'Jamie Lavigne'!$I15) | J215: =IF('Jamie Lavigne'!$B15="","",'Jamie Lavigne'!$J15) | K215: =IF('Jamie Lavigne'!$B15="","",'Jamie Lavigne'!$K15) | L215: =IF('Jamie Lavigne'!$B15="","",'Jamie Lavigne'!$L15) | M215: =IF('Jamie Lavigne'!$B15="","",'Jamie Lavigne'!$M15) | N215: =IF('Jamie Lavigne'!$B15="","",'Jamie Lavigne'!$N15) | O215: =IF('Jamie Lavigne'!$B15="","",'Jamie Lavigne'!$O15) | P215: =IF('Jamie Lavigne'!$B15="","",'Jamie Lavigne'!$P15) | Q215: =IF('Jamie Lavigne'!$B15="","","Jamie Lavigne") | R215: =IF(OR($B215="",$I215="Complete",$L215=""),0,IF($L215<TODAY(),1,0)) -> 0 | S215: =IF(OR($B215="",$I215="Complete",$L215=""),0,IF(AND($L215>=TODAY(),$L215<=TODAY()+7),1,0)) -> 0 | T215: =IF(OR($B215="",$L215=""),"",$L215-TODAY()) | U215: =IF($B215="","",IF($I215="Complete",1,IF($J215="",0,$J215))) | V215: =IF($B215="",0,IF($N215="",0,1)) -> 0 | W215: =IF($B215="",0,1) -> 0
A216: =IF('Jamie Lavigne'!$B16="","",'Jamie Lavigne'!$A16) | B216: =IF('Jamie Lavigne'!$B16="","",'Jamie Lavigne'!$B16) | C216: =IF('Jamie Lavigne'!$B16="","",'Jamie Lavigne'!$C16) | D216: =IF('Jamie Lavigne'!$B16="","",'Jamie Lavigne'!$D16) | E216: =IF('Jamie Lavigne'!$B16="","",'Jamie Lavigne'!$E16) | F216: =IF('Jamie Lavigne'!$B16="","",'Jamie Lavigne'!$F16) | G216: =IF('Jamie Lavigne'!$B16="","",'Jamie Lavigne'!$G16) | H216: =IF('Jamie Lavigne'!$B16="","",'Jamie Lavigne'!$H16) | I216: =IF('Jamie Lavigne'!$B16="","",'Jamie Lavigne'!$I16) | J216: =IF('Jamie Lavigne'!$B16="","",'Jamie Lavigne'!$J16) | K216: =IF('Jamie Lavigne'!$B16="","",'Jamie Lavigne'!$K16) | L216: =IF('Jamie Lavigne'!$B16="","",'Jamie Lavigne'!$L16) | M216: =IF('Jamie Lavigne'!$B16="","",'Jamie Lavigne'!$M16) | N216: =IF('Jamie Lavigne'!$B16="","",'Jamie Lavigne'!$N16) | O216: =IF('Jamie Lavigne'!$B16="","",'Jamie Lavigne'!$O16) | P216: =IF('Jamie Lavigne'!$B16="","",'Jamie Lavigne'!$P16) | Q216: =IF('Jamie Lavigne'!$B16="","","Jamie Lavigne") | R216: =IF(OR($B216="",$I216="Complete",$L216=""),0,IF($L216<TODAY(),1,0)) -> 0 | S216: =IF(OR($B216="",$I216="Complete",$L216=""),0,IF(AND($L216>=TODAY(),$L216<=TODAY()+7),1,0)) -> 0 | T216: =IF(OR($B216="",$L216=""),"",$L216-TODAY()) | U216: =IF($B216="","",IF($I216="Complete",1,IF($J216="",0,$J216))) | V216: =IF($B216="",0,IF($N216="",0,1)) -> 0 | W216: =IF($B216="",0,1) -> 0
